Workbook

Sheet Lançamentos de despesas
A1: Data do vencimento | B1: Data da emissão | C1: Data do pagamento | D1: Fornecedor | E1: Status | F1: Forma de pagamento | G1: Banco/conta | H1: Descrição | I1: Valor | J1: Valor descontos | K1: Valor pago | L1: Recorrência | M1: Parcelas | N1: Classificação | O1: MÊS/ANO VENCIMENTO | P1: MÊS/ANO PAGAMENTO | Q1: SUBCATEGORIA | R1: CATEGORIA | S1: DIA DO VENCIMENTO | T1: MÊS VENCIMENTO | U1: ANO VENCIMENTO | V1: DIA DO pagamento | W1: mes pagamento | X1: ano pagamento
A2: 45505 | C2: =IF(E2="pago",A2,"") -> 45505 | D2: ADELINO ALVES - ALUGUEL GALPÃO | E2: Pago | F2: Pix | G2: BANCO DO BRASIL - 65204-0 | H2: ALUGUEL | I2: 6000.63 | K2: =if(E2="pago",(I2-J2),"") -> 6000.63 | L2: Mensal | N2: ALUGUEIS | O2: =if(A2="","", TEXT(A2,"mm/yyyy")) -> 08/2024 | P2: =if(C2="","", TEXT(C2,"mm/yyyy")) -> 08/2024 | Q2: {=IFERROR(XLOOKUP(N2,'Classificação'!A:A,'Classificação'!B:B),"")} -> DESPESAS COM OCUPAÇÃO | R2: {=IFERROR(XLOOKUP(Q2,'Classificação'!B:B,'Classificação'!C:C),"")} -> DESPESAS FIXAS (-) | S2: =iferror(DAY(A2),"") -> 1 | T2: =iferror(MONTH(O2),"") -> 8 | U2: =iferror(YEAR(O2),"") -> 2024 | V2: =if(C2="","", IFERROR(DAY(C2),"")) -> 1 | W2: =if(C2="","",IFERROR(MONTH(C2),"")) -> 8 | X2: =if(C2="","",iferror(YEAR(C2),"")) -> 2024
A3: 45506 | C3: =IF(E3="pago",A3,"") -> 45506 | D3: RIVER FREIGHT LOGISTICS SERVICES | E3: Pago | F3: Transferência bancária | G3: BANCO DO BRASIL - 65204-0 | H3: PGTO DE IMPOSTOS AEREO COMPRA CHINA BROCAS | I3: 7610 | K3: =if(E3="pago",(I3-J3),"") -> 7610 | L3: Única | N3: COMPRA DE MERCADORIA | O3: =if(A3="","", TEXT(A3,"mm/yyyy")) -> 08/2024 | P3: =if(C3="","", TEXT(C3,"mm/yyyy")) -> 08/2024 | Q3: {=IFERROR(XLOOKUP(N3,'Classificação'!A:A,'Classificação'!B:B),"")} -> COMPRA DE MERCADORIA | R3: {=IFERROR(XLOOKUP(Q3,'Classificação'!B:B,'Classificação'!C:C),"")} -> CUSTOS VARIÁVEIS | S3: =iferror(DAY(A3),"") -> 2 | T3: =iferror(MONTH(O3),"") -> 8 | U3: =iferror(YEAR(O3),"") -> 2024 | V3: =if(C3="","", IFERROR(DAY(C3),"")) -> 2 | W3: =if(C3="","",IFERROR(MONTH(C3),"")) -> 8 | X3: =if(C3="","",iferror(YEAR(C3),"")) -> 2024
A4: 45506 | C4: =IF(E4="pago",A4,"") -> 45506 | D4: ELAINE CRISTINA DE MELO | E4: Pago | F4: Transferência bancária | G4: MERCADO PAGO SINCE - 9511092439-1 | I4: 4000 | K4: =if(E4="pago",(I4-J4),"") -> 4000 | L4: Única | N4: SALARIOS | O4: =if(A4="","", TEXT(A4,"mm/yyyy")) -> 08/2024 | P4: =if(C4="","", TEXT(C4,"mm/yyyy")) -> 08/2024 | Q4: {=IFERROR(XLOOKUP(N4,'Classificação'!A:A,'Classificação'!B:B),"")} -> DESPESAS COM PESSOAL | R4: {=IFERROR(XLOOKUP(Q4,'Classificação'!B:B,'Classificação'!C:C),"")} -> DESPESAS FIXAS (-) | S4: =iferror(DAY(A4),"") -> 2 | T4: =iferror(MONTH(O4),"") -> 8 | U4: =iferror(YEAR(O4),"") -> 2024 | V4: =if(C4="","", IFERROR(DAY(C4),"")) -> 2 | W4: =if(C4="","",IFERROR(MONTH(C4),"")) -> 8 | X4: =if(C4="","",iferror(YEAR(C4),"")) -> 2024
A5: 45509 | C5: =IF(E5="pago",A5,"") -> 45509 | D5: Prefeitura Municipal De Indaiatuba | E5: Pago | F5: Boleto | G5: BANCO DO BRASIL - 65204-0 | H5: ALVARA MATRIZ | I5: 111.33 | K5: =if(E5="pago",(I5-J5),"") -> 111.33 | L5: Única | N5: ALVARÁ DE FUNCIONAMENTO | O5: =if(A5="","", TEXT(A5,"mm/yyyy")) -> 08/2024 | P5: =if(C5="","", TEXT(C5,"mm/yyyy")) -> 08/2024 | Q5: {=IFERROR(XLOOKUP(N5,'Classificação'!A:A,'Classificação'!B:B),"")} -> DESPESAS COM OCUPAÇÃO | R5: {=IFERROR(XLOOKUP(Q5,'Classificação'!B:B,'Classificação'!C:C),"")} -> DESPESAS FIXAS (-) | S5: =iferror(DAY(A5),"") -> 5 | T5: =iferror(MONTH(O5),"") -> 8 | U5: =iferror(YEAR(O5),"") -> 2024 | V5: =if(C5="","", IFERROR(DAY(C5),"")) -> 5 | W5: =if(C5="","",IFERROR(MONTH(C5),"")) -> 8 | X5: =if(C5="","",iferror(YEAR(C5),"")) -> 2024
A6: 45509 | C6: =IF(E6="pago",A6,"") -> 45509 | D6: Prefeitura Municipal De Indaiatuba | E6: Pago | F6: Boleto | G6: BANCO DO BRASIL - 65204-0 | H6: ALVARA MATRIZ | I6: 111.33 | K6: =if(E6="pago",(I6-J6),"") -> 111.33 | L6: Única | N6: ALVARÁ DE FUNCIONAMENTO | O6: =if(A6="","", TEXT(A6,"mm/yyyy")) -> 08/2024 | P6: =if(C6="","", TEXT(C6,"mm/yyyy")) -> 08/2024 | Q6: {=IFERROR(XLOOKUP(N6,'Classificação'!A:A,'Classificação'!B:B),"")} -> DESPESAS COM OCUPAÇÃO | R6: {=IFERROR(XLOOKUP(Q6,'Classificação'!B:B,'Classificação'!C:C),"")} -> DESPESAS FIXAS (-) | S6: =iferror(DAY(A6),"") -> 5 | T6: =iferror(MONTH(O6),"") -> 8 | U6: =iferror(YEAR(O6),"") -> 2024 | V6: =if(C6="","", IFERROR(DAY(C6),"")) -> 5 | W6: =if(C6="","",IFERROR(MONTH(C6),"")) -> 8 | X6: =if(C6="","",iferror(YEAR(C6),"")) -> 2024
A7: 45510 | C7: =IF(E7="pago",A7,"") -> 45510 | D7: LARISSA FARINCHON BORGES | E7: Pago | F7: Transferência bancária | G7: BANCO DO BRASIL - 65204-0 | I7: 2500 | K7: =if(E7="pago",(I7-J7),"") -> 2500 | L7: Mensal | N7: SALARIOS | O7: =if(A7="","", TEXT(A7,"mm/yyyy")) -> 08/2024 | P7: =if(C7="","", TEXT(C7,"mm/yyyy")) -> 08/2024 | Q7: {=IFERROR(XLOOKUP(N7,'Classificação'!A:A,'Classificação'!B:B),"")} -> DESPESAS COM PESSOAL | R7: {=IFERROR(XLOOKUP(Q7,'Classificação'!B:B,'Classificação'!C:C),"")} -> DESPESAS FIXAS (-) | S7: =iferror(DAY(A7),"") -> 6 | T7: =iferror(MONTH(O7),"") -> 8 | U7: =iferror(YEAR(O7),"") -> 2024 | V7: =if(C7="","", IFERROR(DAY(C7),"")) -> 6 | W7: =if(C7="","",IFERROR(MONTH(C7),"")) -> 8 | X7: =if(C7="","",iferror(YEAR(C7),"")) -> 2024
A8: 45510 | C8: =IF(E8="pago",A8,"") -> 45510 | D8: BANCO DO BRASIL | E8: Pago | F8: Pagamento automático | G8: BANCO DO BRASIL - 65204-0 | H8: CESTA DE TARIFAS | I8: 73.8 | K8: =if(E8="pago",(I8-J8),"") -> 73.8 | L8: Mensal | N8: TARIFAS BANCÁRIAS | O8: =if(A8="","", TEXT(A8,"mm/yyyy")) -> 08/2024 | P8: =if(C8="","", TEXT(C8,"mm/yyyy")) -> 08/2024 | Q8: {=IFERROR(XLOOKUP(N8,'Classificação'!A:A,'Classificação'!B:B),"")} -> DESPESAS NÃO OPERACIONAIS | R8: {=IFERROR(XLOOKUP(Q8,'Classificação'!B:B,'Classificação'!C:C),"")} -> RESULTADO NÃO OPERACIONAL (+/-) | S8: =iferror(DAY(A8),"") -> 6 | T8: =iferror(MONTH(O8),"") -> 8 | U8: =iferror(YEAR(O8),"") -> 2024 | V8: =if(C8="","", IFERROR(DAY(C8),"")) -> 6 | W8: =if(C8="","",IFERROR(MONTH(C8),"")) -> 8 | X8: =if(C8="","",iferror(YEAR(C8),"")) -> 2024
A9: 45516 | C9: 45516 | D9: AMIL ASSISTENCIA MEDICA INTERNACIONAL S.A. - CONVENIO MEDICO | E9: Pago | F9: Boleto | G9: BANCO DO BRASIL - 65204-0 | I9: 1375.64 | K9: =if(E9="pago",(I9-J9),"") -> 1375.64 | L9: Mensal | N9: CONVÊNIO MÉDICO | O9: =if(A9="","", TEXT(A9,"mm/yyyy")) -> 08/2024 | P9: =if(C9="","", TEXT(C9,"mm/yyyy")) -> 08/2024 | Q9: {=IFERROR(XLOOKUP(N9,'Classificação'!A:A,'Classificação'!B:B),"")} -> DESPESAS COM PESSOAL | R9: {=IFERROR(XLOOKUP(Q9,'Classificação'!B:B,'Classificação'!C:C),"")} -> DESPESAS FIXAS (-) | S9: =iferror(DAY(A9),"") -> 12 | T9: =iferror(MONTH(O9),"") -> 8 | U9: =iferror(YEAR(O9),"") -> 2024 | V9: =if(C9="","", IFERROR(DAY(C9),"")) -> 12 | W9: =if(C9="","",IFERROR(MONTH(C9),"")) -> 8 | X9: =if(C9="","",iferror(YEAR(C9),"")) -> 2024
A10: 45516 | C10: 45516 | D10: DESKTOP S A - INTERNET WIFI | E10: Pago | F10: Pix | G10: BANCO DO BRASIL - 65204-0 | I10: 139.99 | K10: =if(E10="pago",(I10-J10),"") -> 139.99 | L10: Mensal | N10: INTERNET | O10: =if(A10="","", TEXT(A10,"mm/yyyy")) -> 08/2024 | P10: =if(C10="","", TEXT(C10,"mm/yyyy")) -> 08/2024 | Q10: {=IFERROR(XLOOKUP(N10,'Classificação'!A:A,'Classificação'!B:B),"")} -> DESPESAS COM OCUPAÇÃO | R10: {=IFERROR(XLOOKUP(Q10,'Classificação'!B:B,'Classificação'!C:C),"")} -> DESPESAS FIXAS (-) | S10: =iferror(DAY(A10),"") -> 12 | T10: =iferror(MONTH(O10),"") -> 8 | U10: =iferror(YEAR(O10),"") -> 2024 | V10: =if(C10="","", IFERROR(DAY(C10),"")) -> 12 | W10: =if(C10="","",IFERROR(MONTH(C10),"")) -> 8 | X10: =if(C10="","",iferror(YEAR(C10),"")) -> 2024
A11: 45516 | C11: 45516 | D11: BANCO DO BRASIL | E11: Pago | F11: Pagamento automático | G11: BANCO DO BRASIL - 65204-0 | H11: CONSORCIO | I11: 458.5 | K11: =if(E11="pago",(I11-J11),"") -> 458.5 | L11: Parcelado | M11: 9/48 | N11: PARCELA DO FINANCIAMENTO | O11: =if(A11="","", TEXT(A11,"mm/yyyy")) -> 08/2024 | P11: =if(C11="","", TEXT(C11,"mm/yyyy")) -> 08/2024 | Q11: {=IFERROR(XLOOKUP(N11,'Classificação'!A:A,'Classificação'!B:B),"")} -> DESPESAS NÃO OPERACIONAIS | R11: {=IFERROR(XLOOKUP(Q11,'Classificação'!B:B,'Classificação'!C:C),"")} -> RESULTADO NÃO OPERACIONAL (+/-) | S11: =iferror(DAY(A11),"") -> 12 | T11: =iferror(MONTH(O11),"") -> 8 | U11: =iferror(YEAR(O11),"") -> 2024 | V11: =if(C11="","", IFERROR(DAY(C11),"")) -> 12 | W11: =if(C11="","",IFERROR(MONTH(C11),"")) -> 8 | X11: =if(C11="","",iferror(YEAR(C11),"")) -> 2024
A12: 45516 | C12: 45516 | D12: CELIO LUIZ DE LIMA - VIGIA DA RUA | E12: Pago | F12: Pix | G12: MERCADO PAGO SINCE - 9511092439-1 | H12: VIGILANTE DA RUA | I12: 50 | K12: =if(E12="pago",(I12-J12),"") -> 50 | L12: Mensal | N12: SERVIÇOS TERCEIRIZADOS | O12: =if(A12="","", TEXT(A12,"mm/yyyy")) -> 08/2024 | P12: =if(C12="","", TEXT(C12,"mm/yyyy")) -> 08/2024 | Q12: {=IFERROR(XLOOKUP(N12,'Classificação'!A:A,'Classificação'!B:B),"")} -> DESPESAS ADMINISTRATIVAS | R12: {=IFERROR(XLOOKUP(Q12,'Classificação'!B:B,'Classificação'!C:C),"")} -> DESPESAS FIXAS (-) | S12: =iferror(DAY(A12),"") -> 12 | T12: =iferror(MONTH(O12),"") -> 8 | U12: =iferror(YEAR(O12),"") -> 2024 | V12: =if(C12="","", IFERROR(DAY(C12),"")) -> 12 | W12: =if(C12="","",IFERROR(MONTH(C12),"")) -> 8 | X12: =if(C12="","",iferror(YEAR(C12),"")) -> 2024
A13: 45516 | C13: 45516 | D13: Sidecont Contabilidade E Consultoria | E13: Pago | F13: Boleto | G13: MERCADO PAGO SINCE - 9511092439-1 | H13: CONTABILIDADE DA SINCE | I13: 397 | K13: =if(E13="pago",(I13-J13),"") -> 397 | L13: Mensal | N13: CONTABILIDADE | O13: =if(A13="","", TEXT(A13,"mm/yyyy")) -> 08/2024 | P13: =if(C13="","", TEXT(C13,"mm/yyyy")) -> 08/2024 | Q13: {=IFERROR(XLOOKUP(N13,'Classificação'!A:A,'Classificação'!B:B),"")} -> DESPESAS ADMINISTRATIVAS | R13: {=IFERROR(XLOOKUP(Q13,'Classificação'!B:B,'Classificação'!C:C),"")} -> DESPESAS FIXAS (-) | S13: =iferror(DAY(A13),"") -> 12 | T13: =iferror(MONTH(O13),"") -> 8 | U13: =iferror(YEAR(O13),"") -> 2024 | V13: =if(C13="","", IFERROR(DAY(C13),"")) -> 12 | W13: =if(C13="","",IFERROR(MONTH(C13),"")) -> 8 | X13: =if(C13="","",iferror(YEAR(C13),"")) -> 2024
A14: 45516 | B14: 45516 | C14: =IF(E14="pago",A14,"") -> 45516 | D14: MEDPREVENT EXAME ADMISSIONAL | E14: Pago | F14: Pix | G14: BANCO DO BRASIL - 65204-0 | H14: EXAME ADMISSIONAL ADRIANE | I14: 65 | K14: =if(E14="pago",(I14-J14),"") -> 65 | L14: Única | N14: OUTRAS DESPESAS COM PESSOAL | O14: =if(A14="","", TEXT(A14,"mm/yyyy")) -> 08/2024 | P14: =if(C14="","", TEXT(C14,"mm/yyyy")) -> 08/2024 | Q14: {=IFERROR(XLOOKUP(N14,'Classificação'!A:A,'Classificação'!B:B),"")} -> DESPESAS COM PESSOAL | R14: {=IFERROR(XLOOKUP(Q14,'Classificação'!B:B,'Classificação'!C:C),"")} -> DESPESAS FIXAS (-) | S14: =iferror(DAY(A14),"") -> 12 | T14: =iferror(MONTH(O14),"") -> 8 | U14: =iferror(YEAR(O14),"") -> 2024 | V14: =if(C14="","", IFERROR(DAY(C14),"")) -> 12 | W14: =if(C14="","",IFERROR(MONTH(C14),"")) -> 8 | X14: =if(C14="","",iferror(YEAR(C14),"")) -> 2024
A15: 45516 | C15: =IF(E15="pago",A15,"") -> 45516 | D15: ELAINE CRISTINA DE MELO | E15: Pago | F15: Transferência bancária | G15: BANCO DO BRASIL - 65204-0 | I15: 1000 | K15: =if(E15="pago",(I15-J15),"") -> 1000 | L15: Mensal | N15: SALARIOS | O15: =if(A15="","", TEXT(A15,"mm/yyyy")) -> 08/2024 | P15: =if(C15="","", TEXT(C15,"mm/yyyy")) -> 08/2024 | Q15: {=IFERROR(XLOOKUP(N15,'Classificação'!A:A,'Classificação'!B:B),"")} -> DESPESAS COM PESSOAL | R15: {=IFERROR(XLOOKUP(Q15,'Classificação'!B:B,'Classificação'!C:C),"")} -> DESPESAS FIXAS (-) | S15: =iferror(DAY(A15),"") -> 12 | T15: =iferror(MONTH(O15),"") -> 8 | U15: =iferror(YEAR(O15),"") -> 2024 | V15: =if(C15="","", IFERROR(DAY(C15),"")) -> 12 | W15: =if(C15="","",IFERROR(MONTH(C15),"")) -> 8 | X15: =if(C15="","",iferror(YEAR(C15),"")) -> 2024
A16: 45516 | C16: =IF(E16="pago",A16,"") -> 45516 | D16: LARISSA FARINCHON BORGES | E16: Pago | F16: Transferência bancária | G16: BANCO DO BRASIL - 65204-0 | I16: 2500 | K16: =if(E16="pago",(I16-J16),"") -> 2500 | L16: Única | N16: SALARIOS | O16: =if(A16="","", TEXT(A16,"mm/yyyy")) -> 08/2024 | P16: =if(C16="","", TEXT(C16,"mm/yyyy")) -> 08/2024 | Q16: {=IFERROR(XLOOKUP(N16,'Classificação'!A:A,'Classificação'!B:B),"")} -> DESPESAS COM PESSOAL | R16: {=IFERROR(XLOOKUP(Q16,'Classificação'!B:B,'Classificação'!C:C),"")} -> DESPESAS FIXAS (-) | S16: =iferror(DAY(A16),"") -> 12 | T16: =iferror(MONTH(O16),"") -> 8 | U16: =iferror(YEAR(O16),"") -> 2024 | V16: =if(C16="","", IFERROR(DAY(C16),"")) -> 12 | W16: =if(C16="","",IFERROR(MONTH(C16),"")) -> 8 | X16: =if(C16="","",iferror(YEAR(C16),"")) -> 2024
A17: 45517 | C17: =IF(E17="pago",A17,"") -> 45517 | D17: MERCADO LIVRE | E17: Pago | F17: Pagamento automático | G17: MERCADO PAGO FARMEL - | H17: CUSTO DO FULL FARMEL (COLETA E ARMAZENAGEM) | I17: 1010.16 | K17: =if(E17="pago",(I17-J17),"") -> 1010.16 | L17: Mensal | N17: FRETE DE VENDAS | O17: =if(A17="","", TEXT(A17,"mm/yyyy")) -> 08/2024 | P17: =if(C17="","", TEXT(C17,"mm/yyyy")) -> 08/2024 | Q17: {=IFERROR(XLOOKUP(N17,'Classificação'!A:A,'Classificação'!B:B),"")} -> FRETE DE VENDAS | R17: {=IFERROR(XLOOKUP(Q17,'Classificação'!B:B,'Classificação'!C:C),"")} -> CUSTOS VARIÁVEIS | S17: =iferror(DAY(A17),"") -> 13 | T17: =iferror(MONTH(O17),"") -> 8 | U17: =iferror(YEAR(O17),"") -> 2024 | V17: =if(C17="","", IFERROR(DAY(C17),"")) -> 13 | W17: =if(C17="","",IFERROR(MONTH(C17),"")) -> 8 | X17: =if(C17="","",iferror(YEAR(C17),"")) -> 2024
A18: 45517 | C18: =IF(E18="pago",A18,"") -> 45517 | D18: TAKATA TAKATA COMERCIO DE DOCES E SALGADOS | E18: Pago | F18: Pix | G18: MERCADO PAGO SINCE - 9511092439-1 | H18: BOLO NIVER ELAINE | I18: 90 | K18: =if(E18="pago",(I18-J18),"") -> 90 | L18: Única | N18: COMPRA DE MERCADO/PADARIA | O18: =if(A18="","", TEXT(A18,"mm/yyyy")) -> 08/2024 | Q18: {=IFERROR(XLOOKUP(N18,'Classificação'!A:A,'Classificação'!B:B),"")} -> DESPESAS DIVERSAS | R18: {=IFERROR(XLOOKUP(Q18,'Classificação'!B:B,'Classificação'!C:C),"")} -> DESPESAS FIXAS (-) | S18: =iferror(DAY(A18),"") -> 13 | T18: =iferror(MONTH(O18),"") -> 8 | U18: =iferror(YEAR(O18),"") -> 2024 | V18: =if(C18="","", IFERROR(DAY(C18),"")) -> 13 | W18: =if(C18="","",IFERROR(MONTH(C18),"")) -> 8 | X18: =if(C18="","",iferror(YEAR(C18),"")) -> 2024
A19: 45518 | C19: =IF(E19="pago",A19,"") -> 45518 | D19: BANCO DO BRASIL | E19: Pago | F19: Pagamento automático | G19: BANCO DO BRASIL - 65204-0 | H19: CAPITAL DE GIRO PEAC FGI JUROS | I19: 2786.78 | K19: =if(E19="pago",(I19-J19),"") -> 2786.78 | L19: Parcelado | M19: 45445 | N19: PAGAMENTO DE EMPRESTIMOS (BANCOS) | O19: =if(A19="","", TEXT(A19,"mm/yyyy")) -> 08/2024 | P19: =if(C19="","", TEXT(C19,"mm/yyyy")) -> 08/2024 | Q19: {=IFERROR(XLOOKUP(N19,'Classificação'!A:A,'Classificação'!B:B),"")} -> DESPESAS NÃO OPERACIONAIS | R19: {=IFERROR(XLOOKUP(Q19,'Classificação'!B:B,'Classificação'!C:C),"")} -> RESULTADO NÃO OPERACIONAL (+/-) | S19: =iferror(DAY(A19),"") -> 14 | T19: =iferror(MONTH(O19),"") -> 8 | U19: =iferror(YEAR(O19),"") -> 2024 | V19: =if(C19="","", IFERROR(DAY(C19),"")) -> 14 | W19: =if(C19="","",IFERROR(MONTH(C19),"")) -> 8 | X19: =if(C19="","",iferror(YEAR(C19),"")) -> 2024
A20: 45519 | C20: =IF(E20="pago",A20,"") -> 45519 | D20: ADRIANE CRISTINA GOMES | E20: Pago | F20: Pix | G20: MERCADO PAGO SINCE - 9511092439-1 | I20: 592 | K20: =if(E20="pago",(I20-J20),"") -> 592 | L20: Mensal | N20: ADIANTAMENTO DE SALARIO | O20: =if(A20="","", TEXT(A20,"mm/yyyy")) -> 08/2024 | P20: =if(C20="","", TEXT(C20,"mm/yyyy")) -> 08/2024 | Q20: {=IFERROR(XLOOKUP(N20,'Classificação'!A:A,'Classificação'!B:B),"")} -> DESPESAS COM PESSOAL | R20: {=IFERROR(XLOOKUP(Q20,'Classificação'!B:B,'Classificação'!C:C),"")} -> DESPESAS FIXAS (-) | S20: =iferror(DAY(A20),"") -> 15 | T20: =iferror(MONTH(O20),"") -> 8 | U20: =iferror(YEAR(O20),"") -> 2024 | V20: =if(C20="","", IFERROR(DAY(C20),"")) -> 15 | W20: =if(C20="","",IFERROR(MONTH(C20),"")) -> 8 | X20: =if(C20="","",iferror(YEAR(C20),"")) -> 2024
A21: 45519 | C21: =IF(E21="pago",A21,"") -> 45519 | D21: William Bezerra de Melo | E21: Pago | F21: Transferência bancária | G21: BANCO DO BRASIL - 65204-0 | H21: COMPRA DE BOLO - REEMBOLSO WILLIAM | I21: 24 | K21: =if(E21="pago",(I21-J21),"") -> 24 | L21: Única | N21: ALIMENTAÇÃO FUNCIONARIOS | O21: =if(A21="","", TEXT(A21,"mm/yyyy")) -> 08/2024 | P21: =if(C21="","", TEXT(C21,"mm/yyyy")) -> 08/2024 | Q21: {=IFERROR(XLOOKUP(N21,'Classificação'!A:A,'Classificação'!B:B),"")} -> DESPESAS COM PESSOAL | R21: {=IFERROR(XLOOKUP(Q21,'Classificação'!B:B,'Classificação'!C:C),"")} -> DESPESAS FIXAS (-) | S21: =iferror(DAY(A21),"") -> 15 | T21: =iferror(MONTH(O21),"") -> 8 | U21: =iferror(YEAR(O21),"") -> 2024 | V21: =if(C21="","", IFERROR(DAY(C21),"")) -> 15 | W21: =if(C21="","",IFERROR(MONTH(C21),"")) -> 8 | X21: =if(C21="","",iferror(YEAR(C21),"")) -> 2024
A22: 45519 | C22: =IF(E22="pago",A22,"") -> 45519 | D22: Debora Morales de Melo | E22: Pago | F22: Pix | G22: MERCADO PAGO SINCE - 9511092439-1 | I22: 750 | K22: =if(E22="pago",(I22-J22),"") -> 750 | L22: Mensal | N22: SALARIOS | O22: =if(A22="","", TEXT(A22,"mm/yyyy")) -> 08/2024 | P22: =if(C22="","", TEXT(C22,"mm/yyyy")) -> 08/2024 | Q22: {=IFERROR(XLOOKUP(N22,'Classificação'!A:A,'Classificação'!B:B),"")} -> DESPESAS COM PESSOAL | R22: {=IFERROR(XLOOKUP(Q22,'Classificação'!B:B,'Classificação'!C:C),"")} -> DESPESAS FIXAS (-) | S22: =iferror(DAY(A22),"") -> 15 | T22: =iferror(MONTH(O22),"") -> 8 | U22: =iferror(YEAR(O22),"") -> 2024 | V22: =if(C22="","", IFERROR(DAY(C22),"")) -> 15 | W22: =if(C22="","",IFERROR(MONTH(C22),"")) -> 8 | X22: =if(C22="","",iferror(YEAR(C22),"")) -> 2024
A23: 45519 | C23: =IF(E23="pago",A23,"") -> 45519 | D23: Priscila Zaghi Da Silva | E23: Pago | F23: Transferência bancária | G23: BANCO DO BRASIL - 65204-0 | I23: 720 | K23: =if(E23="pago",(I23-J23),"") -> 720 | L23: Mensal | N23: ADIANTAMENTO DE SALARIO | O23: =if(A23="","", TEXT(A23,"mm/yyyy")) -> 08/2024 | P23: =if(C23="","", TEXT(C23,"mm/yyyy")) -> 08/2024 | Q23: {=IFERROR(XLOOKUP(N23,'Classificação'!A:A,'Classificação'!B:B),"")} -> DESPESAS COM PESSOAL | R23: {=IFERROR(XLOOKUP(Q23,'Classificação'!B:B,'Classificação'!C:C),"")} -> DESPESAS FIXAS (-) | S23: =iferror(DAY(A23),"") -> 15 | T23: =iferror(MONTH(O23),"") -> 8 | U23: =iferror(YEAR(O23),"") -> 2024 | V23: =if(C23="","", IFERROR(DAY(C23),"")) -> 15 | W23: =if(C23="","",IFERROR(MONTH(C23),"")) -> 8 | X23: =if(C23="","",iferror(YEAR(C23),"")) -> 2024
A24: 45519 | C24: =IF(E24="pago",A24,"") -> 45519 | D24: Sumerbol Supermercados Ltda | E24: Pago | F24: Pix | G24: MERCADO PAGO SINCE - 9511092439-1 | H24: CAFÉ - REEMBOLSO WILLIAM | I24: 20.99 | K24: =if(E24="pago",(I24-J24),"") -> 20.99 | L24: Única | N24: COMPRA DE MERCADO/PADARIA | O24: =if(A24="","", TEXT(A24,"mm/yyyy")) -> 08/2024 | P24: =if(C24="","", TEXT(C24,"mm/yyyy")) -> 08/2024 | Q24: {=IFERROR(XLOOKUP(N24,'Classificação'!A:A,'Classificação'!B:B),"")} -> DESPESAS DIVERSAS | R24: {=IFERROR(XLOOKUP(Q24,'Classificação'!B:B,'Classificação'!C:C),"")} -> DESPESAS FIXAS (-) | S24: =iferror(DAY(A24),"") -> 15 | T24: =iferror(MONTH(O24),"") -> 8 | U24: =iferror(YEAR(O24),"") -> 2024 | V24: =if(C24="","", IFERROR(DAY(C24),"")) -> 15 | W24: =if(C24="","",IFERROR(MONTH(C24),"")) -> 8 | X24: =if(C24="","",iferror(YEAR(C24),"")) -> 2024
A25: 45519 | C25: =IF(E25="pago",A25,"") -> 45519 | D25: THIAGO MAURICIO BERTI | E25: Pago | F25: Transferência bancária | G25: BANCO DO BRASIL - 65204-0 | I25: 744 | K25: =if(E25="pago",(I25-J25),"") -> 744 | L25: Mensal | N25: ADIANTAMENTO DE SALARIO | O25: =if(A25="","", TEXT(A25,"mm/yyyy")) -> 08/2024 | P25: =if(C25="","", TEXT(C25,"mm/yyyy")) -> 08/2024 | Q25: {=IFERROR(XLOOKUP(N25,'Classificação'!A:A,'Classificação'!B:B),"")} -> DESPESAS COM PESSOAL | R25: {=IFERROR(XLOOKUP(Q25,'Classificação'!B:B,'Classificação'!C:C),"")} -> DESPESAS FIXAS (-) | S25: =iferror(DAY(A25),"") -> 15 | T25: =iferror(MONTH(O25),"") -> 8 | U25: =iferror(YEAR(O25),"") -> 2024 | V25: =if(C25="","", IFERROR(DAY(C25),"")) -> 15 | W25: =if(C25="","",IFERROR(MONTH(C25),"")) -> 8 | X25: =if(C25="","",iferror(YEAR(C25),"")) -> 2024
A26: 45519 | C26: =IF(E26="pago",A26,"") -> 45519 | D26: William Bezerra de Melo | E26: Pago | F26: Pix | G26: BANCO DO BRASIL - 65204-0 | H26: Empréstimo para importação - QUANTUM a ser pago para William, pix: CPF04767793408 | I26: 2500 | K26: =if(E26="pago",(I26-J26),"") -> 2500 | L26: Parcelado | M26: 45512 | N26: EMPRESTIMOS PARA TERCEIROS | O26: =if(A26="","", TEXT(A26,"mm/yyyy")) -> 08/2024 | P26: =if(C26="","", TEXT(C26,"mm/yyyy")) -> 08/2024 | Q26: {=IFERROR(XLOOKUP(N26,'Classificação'!A:A,'Classificação'!B:B),"")} -> DESPESAS NÃO OPERACIONAIS | R26: {=IFERROR(XLOOKUP(Q26,'Classificação'!B:B,'Classificação'!C:C),"")} -> RESULTADO NÃO OPERACIONAL (+/-) | S26: =iferror(DAY(A26),"") -> 15 | T26: =iferror(MONTH(O26),"") -> 8 | U26: =iferror(YEAR(O26),"") -> 2024 | V26: =if(C26="","", IFERROR(DAY(C26),"")) -> 15 | W26: =if(C26="","",IFERROR(MONTH(C26),"")) -> 8 | X26: =if(C26="","",iferror(YEAR(C26),"")) -> 2024
A27: 45520 | C27: =IF(E27="pago",A27,"") -> 45520 | D27: Regina Celia Moura de Oliveira - Barbara Bolsas | E27: Pago | F27: Cheque | G27: BANCO DO BRASIL - 65204-0 | H27: PEDIDO DE COMPRA 318 CHEQUE 850030 | I27: 1127.5 | K27: =if(E27="pago",(I27-J27),"") -> 1127.5 | L27: Parcelado | M27: 45352 | N27: COMPRA DE MERCADORIA | O27: =if(A27="","", TEXT(A27,"mm/yyyy")) -> 08/2024 | P27: =if(C27="","", TEXT(C27,"mm/yyyy")) -> 08/2024 | Q27: {=IFERROR(XLOOKUP(N27,'Classificação'!A:A,'Classificação'!B:B),"")} -> COMPRA DE MERCADORIA | R27: {=IFERROR(XLOOKUP(Q27,'Classificação'!B:B,'Classificação'!C:C),"")} -> CUSTOS VARIÁVEIS | S27: =iferror(DAY(A27),"") -> 16 | T27: =iferror(MONTH(O27),"") -> 8 | U27: =iferror(YEAR(O27),"") -> 2024 | V27: =if(C27="","", IFERROR(DAY(C27),"")) -> 16 | W27: =if(C27="","",IFERROR(MONTH(C27),"")) -> 8 | X27: =if(C27="","",iferror(YEAR(C27),"")) -> 2024
A28: 45520 | C28: =IF(E28="pago",A28,"") -> 45520 | D28: Regina Celia Moura de Oliveira - Barbara Bolsas | E28: Pago | F28: Cheque | G28: BANCO DO BRASIL - 65204-0 | H28: PEDIDO DE COMPRA 313 CHEQUE 850025 | I28: 1533 | K28: =if(E28="pago",(I28-J28),"") -> 1533 | L28: Parcelado | M28: 45323 | N28: COMPRA DE MERCADORIA | O28: =if(A28="","", TEXT(A28,"mm/yyyy")) -> 08/2024 | P28: =if(C28="","", TEXT(C28,"mm/yyyy")) -> 08/2024 | Q28: {=IFERROR(XLOOKUP(N28,'Classificação'!A:A,'Classificação'!B:B),"")} -> COMPRA DE MERCADORIA | R28: {=IFERROR(XLOOKUP(Q28,'Classificação'!B:B,'Classificação'!C:C),"")} -> CUSTOS VARIÁVEIS | S28: =iferror(DAY(A28),"") -> 16 | T28: =iferror(MONTH(O28),"") -> 8 | U28: =iferror(YEAR(O28),"") -> 2024 | V28: =if(C28="","", IFERROR(DAY(C28),"")) -> 16 | W28: =if(C28="","",IFERROR(MONTH(C28),"")) -> 8 | X28: =if(C28="","",iferror(YEAR(C28),"")) -> 2024
A29: 45520 | C29: =IF(E29="pago",A29,"") -> 45520 | D29: CPFL - COMPAHIA DE FORÇA E LUZ | E29: Pago | F29: Boleto | G29: BANCO DO BRASIL - 65204-0 | H29: PROVISIONAMENTO CPFL | I29: 374.8 | K29: =if(E29="pago",(I29-J29),"") -> 374.8 | L29: Mensal | N29: ENERGIA ELETRICA | O29: =if(A29="","", TEXT(A29,"mm/yyyy")) -> 08/2024 | P29: =if(C29="","", TEXT(C29,"mm/yyyy")) -> 08/2024 | Q29: {=IFERROR(XLOOKUP(N29,'Classificação'!A:A,'Classificação'!B:B),"")} -> DESPESAS COM OCUPAÇÃO | R29: {=IFERROR(XLOOKUP(Q29,'Classificação'!B:B,'Classificação'!C:C),"")} -> DESPESAS FIXAS (-) | S29: =iferror(DAY(A29),"") -> 16 | T29: =iferror(MONTH(O29),"") -> 8 | U29: =iferror(YEAR(O29),"") -> 2024 | V29: =if(C29="","", IFERROR(DAY(C29),"")) -> 16 | W29: =if(C29="","",IFERROR(MONTH(C29),"")) -> 8 | X29: =if(C29="","",iferror(YEAR(C29),"")) -> 2024
A30: 45520 | B30: 45520 | C30: =IF(E30="pago",A30,"") -> 45520 | D30: PONTO AZUL | E30: Pago | F30: Pix | G30: MERCADO PAGO SINCE - 9511092439-1 | H30: CABO PARA NOTEBOOK | I30: 20 | K30: =if(E30="pago",(I30-J30),"") -> 20 | L30: Única | N30: COMPRA DE BENS/EQUIPAMENTOS | O30: =if(A30="","", TEXT(A30,"mm/yyyy")) -> 08/2024 | Q30: {=IFERROR(XLOOKUP(N30,'Classificação'!A:A,'Classificação'!B:B),"")} -> DESPESAS NÃO OPERACIONAIS | R30: {=IFERROR(XLOOKUP(Q30,'Classificação'!B:B,'Classificação'!C:C),"")} -> RESULTADO NÃO OPERACIONAL (+/-) | S30: =iferror(DAY(A30),"") -> 16 | T30: =iferror(MONTH(O30),"") -> 8 | U30: =iferror(YEAR(O30),"") -> 2024 | V30: =if(C30="","", IFERROR(DAY(C30),"")) -> 16 | W30: =if(C30="","",IFERROR(MONTH(C30),"")) -> 8 | X30: =if(C30="","",iferror(YEAR(C30),"")) -> 2024
A31: 45520 | C31: =IF(E31="pago",A31,"") -> 45520 | D31: BANCO DO BRASIL | E31: Pago | F31: Pagamento automático | G31: BANCO DO BRASIL - 65204-0 | H31: Tarifa Agrupada | I31: 7.36 | K31: =if(E31="pago",(I31-J31),"") -> 7.36 | L31: Única | N31: TARIFAS DE PIX | O31: =if(A31="","", TEXT(A31,"mm/yyyy")) -> 08/2024 | Q31: {=IFERROR(XLOOKUP(N31,'Classificação'!A:A,'Classificação'!B:B),"")} -> TARIFAS DE PIX | R31: {=IFERROR(XLOOKUP(Q31,'Classificação'!B:B,'Classificação'!C:C),"")} -> (+/-) RESULTADO FINANCEIRO LÍQUIDO | S31: =iferror(DAY(A31),"") -> 16 | T31: =iferror(MONTH(O31),"") -> 8 | U31: =iferror(YEAR(O31),"") -> 2024 | V31: =if(C31="","", IFERROR(DAY(C31),"")) -> 16 | W31: =if(C31="","",IFERROR(MONTH(C31),"")) -> 8 | X31: =if(C31="","",iferror(YEAR(C31),"")) -> 2024
A32: 45523 | C32: =IF(E32="pago",A32,"") -> 45523 | D32: BANCO DO BRASIL | E32: Pago | F32: Pagamento automático | G32: BANCO DO BRASIL - 65204-0 | H32: PRONAMPE 1º CONTRATO | I32: 3511.72 | K32: =if(E32="pago",(I32-J32),"") -> 3511.72 | L32: Parcelado | M32: 2/48 | N32: PAGAMENTO DE EMPRESTIMOS (BANCOS) | O32: =if(A32="","", TEXT(A32,"mm/yyyy")) -> 08/2024 | P32: =if(C32="","", TEXT(C32,"mm/yyyy")) -> 08/2024 | Q32: {=IFERROR(XLOOKUP(N32,'Classificação'!A:A,'Classificação'!B:B),"")} -> DESPESAS NÃO OPERACIONAIS | R32: {=IFERROR(XLOOKUP(Q32,'Classificação'!B:B,'Classificação'!C:C),"")} -> RESULTADO NÃO OPERACIONAL (+/-) | S32: =iferror(DAY(A32),"") -> 19 | T32: =iferror(MONTH(O32),"") -> 8 | U32: =iferror(YEAR(O32),"") -> 2024 | V32: =if(C32="","", IFERROR(DAY(C32),"")) -> 19 | W32: =if(C32="","",IFERROR(MONTH(C32),"")) -> 8 | X32: =if(C32="","",iferror(YEAR(C32),"")) -> 2024
A33: 45523 | C33: =IF(E33="pago",A33,"") -> 45523 | D33: DAS - SIMPLES NACIONAL | E33: Pago | F33: Boleto | G33: MERCADO PAGO SINCE - 9511092439-1 | I33: 78.93 | K33: =if(E33="pago",(I33-J33),"") -> 78.93 | L33: Mensal | N33: IMPOSTO DE RENDA - DAS | O33: =if(A33="","", TEXT(A33,"mm/yyyy")) -> 08/2024 | P33: =if(C33="","", TEXT(C33,"mm/yyyy")) -> 08/2024 | Q33: {=IFERROR(XLOOKUP(N33,'Classificação'!A:A,'Classificação'!B:B),"")} -> IMPOSTO DE RENDA - DAS | R33: {=IFERROR(XLOOKUP(Q33,'Classificação'!B:B,'Classificação'!C:C),"")} -> DEDUÇÕES DA RECEITA BRUTA (-) | S33: =iferror(DAY(A33),"") -> 19 | T33: =iferror(MONTH(O33),"") -> 8 | U33: =iferror(YEAR(O33),"") -> 2024 | V33: =if(C33="","", IFERROR(DAY(C33),"")) -> 19 | W33: =if(C33="","",IFERROR(MONTH(C33),"")) -> 8 | X33: =if(C33="","",iferror(YEAR(C33),"")) -> 2024
A34: 45523 | C34: =IF(E34="pago",A34,"") -> 45523 | D34: ELAINE CRISTINA DE MELO | E34: Pago | F34: Transferência bancária | G34: MERCADO PAGO SINCE - 9511092439-1 | I34: 3250 | K34: =if(E34="pago",(I34-J34),"") -> 3250 | L34: Mensal | N34: SALARIOS | O34: =if(A34="","", TEXT(A34,"mm/yyyy")) -> 08/2024 | P34: =if(C34="","", TEXT(C34,"mm/yyyy")) -> 08/2024 | Q34: {=IFERROR(XLOOKUP(N34,'Classificação'!A:A,'Classificação'!B:B),"")} -> DESPESAS COM PESSOAL | R34: {=IFERROR(XLOOKUP(Q34,'Classificação'!B:B,'Classificação'!C:C),"")} -> DESPESAS FIXAS (-) | S34: =iferror(DAY(A34),"") -> 19 | T34: =iferror(MONTH(O34),"") -> 8 | U34: =iferror(YEAR(O34),"") -> 2024 | V34: =if(C34="","", IFERROR(DAY(C34),"")) -> 19 | W34: =if(C34="","",IFERROR(MONTH(C34),"")) -> 8 | X34: =if(C34="","",iferror(YEAR(C34),"")) -> 2024
A35: 45523 | C35: =IF(E35="pago",A35,"") -> 45523 | D35: LARISSA FARINCHON BORGES | E35: Pago | F35: Transferência bancária | G35: MERCADO PAGO SINCE - 9511092439-1 | I35: 3250 | K35: =if(E35="pago",(I35-J35),"") -> 3250 | L35: Mensal | N35: SALARIOS | O35: =if(A35="","", TEXT(A35,"mm/yyyy")) -> 08/2024 | P35: =if(C35="","", TEXT(C35,"mm/yyyy")) -> 08/2024 | Q35: {=IFERROR(XLOOKUP(N35,'Classificação'!A:A,'Classificação'!B:B),"")} -> DESPESAS COM PESSOAL | R35: {=IFERROR(XLOOKUP(Q35,'Classificação'!B:B,'Classificação'!C:C),"")} -> DESPESAS FIXAS (-) | S35: =iferror(DAY(A35),"") -> 19 | T35: =iferror(MONTH(O35),"") -> 8 | U35: =iferror(YEAR(O35),"") -> 2024 | V35: =if(C35="","", IFERROR(DAY(C35),"")) -> 19 | W35: =if(C35="","",IFERROR(MONTH(C35),"")) -> 8 | X35: =if(C35="","",iferror(YEAR(C35),"")) -> 2024
A36: 45524 | C36: =IF(E36="pago",A36,"") -> 45524 | D36: Jose Alberto | E36: Pago | F36: Pix | G36: MERCADO PAGO SINCE - 9511092439-1 | I36: 500 | K36: =if(E36="pago",(I36-J36),"") -> 500 | L36: Única | N36: SERVIÇOS TERCEIRIZADOS | O36: =if(A36="","", TEXT(A36,"mm/yyyy")) -> 08/2024 | P36: =if(C36="","", TEXT(C36,"mm/yyyy")) -> 08/2024 | Q36: {=IFERROR(XLOOKUP(N36,'Classificação'!A:A,'Classificação'!B:B),"")} -> DESPESAS ADMINISTRATIVAS | R36: {=IFERROR(XLOOKUP(Q36,'Classificação'!B:B,'Classificação'!C:C),"")} -> DESPESAS FIXAS (-) | S36: =iferror(DAY(A36),"") -> 20 | T36: =iferror(MONTH(O36),"") -> 8 | U36: =iferror(YEAR(O36),"") -> 2024 | V36: =if(C36="","", IFERROR(DAY(C36),"")) -> 20 | W36: =if(C36="","",IFERROR(MONTH(C36),"")) -> 8 | X36: =if(C36="","",iferror(YEAR(C36),"")) -> 2024
A37: 45524 | C37: =IF(E37="pago",A37,"") -> 45524 | D37: MERCADO LIVRE | E37: Pago | F37: Pagamento automático | G37: MERCADO PAGO SINCE - 9511092439-1 | H37: CUSTO DO FULL SINCE(COLETA E ARMAZENAGEM) | I37: 826.14 | K37: =if(E37="pago",(I37-J37),"") -> 826.14 | L37: Mensal | N37: FRETE DE VENDAS | O37: =if(A37="","", TEXT(A37,"mm/yyyy")) -> 08/2024 | P37: =if(C37="","", TEXT(C37,"mm/yyyy")) -> 08/2024 | Q37: {=IFERROR(XLOOKUP(N37,'Classificação'!A:A,'Classificação'!B:B),"")} -> FRETE DE VENDAS | R37: {=IFERROR(XLOOKUP(Q37,'Classificação'!B:B,'Classificação'!C:C),"")} -> CUSTOS VARIÁVEIS | S37: =iferror(DAY(A37),"") -> 20 | T37: =iferror(MONTH(O37),"") -> 8 | U37: =iferror(YEAR(O37),"") -> 2024 | V37: =if(C37="","", IFERROR(DAY(C37),"")) -> 20 | W37: =if(C37="","",IFERROR(MONTH(C37),"")) -> 8 | X37: =if(C37="","",iferror(YEAR(C37),"")) -> 2024
A38: 45524 | C38: =IF(E38="pago",A38,"") -> 45524 | D38: BLING SISTEMA ERP | E38: Pago | F38: Boleto | G38: BANCO DO BRASIL - 65204-0 | I38: 400 | K38: =if(E38="pago",(I38-J38),"") -> 400 | L38: Mensal | N38: DESPESA COM SISTEMAS | O38: =if(A38="","", TEXT(A38,"mm/yyyy")) -> 08/2024 | P38: =if(C38="","", TEXT(C38,"mm/yyyy")) -> 08/2024 | Q38: {=IFERROR(XLOOKUP(N38,'Classificação'!A:A,'Classificação'!B:B),"")} -> DESPESAS ADMINISTRATIVAS | R38: {=IFERROR(XLOOKUP(Q38,'Classificação'!B:B,'Classificação'!C:C),"")} -> DESPESAS FIXAS (-) | S38: =iferror(DAY(A38),"") -> 20 | T38: =iferror(MONTH(O38),"") -> 8 | U38: =iferror(YEAR(O38),"") -> 2024 | V38: =if(C38="","", IFERROR(DAY(C38),"")) -> 20 | W38: =if(C38="","",IFERROR(MONTH(C38),"")) -> 8 | X38: =if(C38="","",iferror(YEAR(C38),"")) -> 2024
A39: 45524 | B39: 45458 | C39: =IF(E39="pago",A39,"") -> 45524 | D39: BRASTEMP | E39: Pago | F39: Cartão de Crédito ELO | G39: BANCO DO BRASIL - 65204-0 | H39: CARTÃO ELO - FRIGOBAR | I39: 278.01 | K39: =if(E39="pago",(I39-J39),"") -> 278.01 | L39: Parcelado | M39: 45474 | N39: COMPRA DE BENS/EQUIPAMENTOS | O39: =if(A39="","", TEXT(A39,"mm/yyyy")) -> 08/2024 | P39: =if(C39="","", TEXT(C39,"mm/yyyy")) -> 08/2024 | Q39: {=IFERROR(XLOOKUP(N39,'Classificação'!A:A,'Classificação'!B:B),"")} -> DESPESAS NÃO OPERACIONAIS | R39: {=IFERROR(XLOOKUP(Q39,'Classificação'!B:B,'Classificação'!C:C),"")} -> RESULTADO NÃO OPERACIONAL (+/-) | S39: =iferror(DAY(A39),"") -> 20 | T39: =iferror(MONTH(O39),"") -> 8 | U39: =iferror(YEAR(O39),"") -> 2024 | V39: =if(C39="","", IFERROR(DAY(C39),"")) -> 20 | W39: =if(C39="","",IFERROR(MONTH(C39),"")) -> 8 | X39: =if(C39="","",iferror(YEAR(C39),"")) -> 2024
A40: 45524 | C40: =IF(E40="pago",A40,"") -> 45524 | D40: CANVA - PLATAFORMA ONLINE DE MARKETING | E40: Pago | F40: Cartão de Crédito VISA | G40: BANCO DO BRASIL - 65204-0 | H40: Cartão VISA - PLATAFORMA DE MARKETING ONLINE | I40: 24.25 | K40: =if(E40="pago",(I40-J40),"") -> 24.25 | L40: Mensal | N40: DESPESA COM SISTEMAS | O40: =if(A40="","", TEXT(A40,"mm/yyyy")) -> 08/2024 | P40: =if(C40="","", TEXT(C40,"mm/yyyy")) -> 08/2024 | Q40: {=IFERROR(XLOOKUP(N40,'Classificação'!A:A,'Classificação'!B:B),"")} -> DESPESAS ADMINISTRATIVAS | R40: {=IFERROR(XLOOKUP(Q40,'Classificação'!B:B,'Classificação'!C:C),"")} -> DESPESAS FIXAS (-) | S40: =iferror(DAY(A40),"") -> 20 | T40: =iferror(MONTH(O40),"") -> 8 | U40: =iferror(YEAR(O40),"") -> 2024 | V40: =if(C40="","", IFERROR(DAY(C40),"")) -> 20 | W40: =if(C40="","",IFERROR(MONTH(C40),"")) -> 8 | X40: =if(C40="","",iferror(YEAR(C40),"")) -> 2024
A41: 45524 | B41: 45497 | C41: =IF(E41="pago",A41,"") -> 45524 | D41: CARREFOUR - SUPERMERCADO | E41: Pago | F41: Cartão de Crédito ELO | G41: BANCO DO BRASIL - 65204-0 | H41: Cartão Elo - CAFÉ, CAPSULAS E BOLACHAS | I41: 102.83 | K41: =if(E41="pago",(I41-J41),"") -> 102.83 | L41: Única | N41: COMPRA DE MERCADO/PADARIA | O41: =if(A41="","", TEXT(A41,"mm/yyyy")) -> 08/2024 | P41: =if(C41="","", TEXT(C41,"mm/yyyy")) -> 08/2024 | Q41: {=IFERROR(XLOOKUP(N41,'Classificação'!A:A,'Classificação'!B:B),"")} -> DESPESAS DIVERSAS | R41: {=IFERROR(XLOOKUP(Q41,'Classificação'!B:B,'Classificação'!C:C),"")} -> DESPESAS FIXAS (-) | S41: =iferror(DAY(A41),"") -> 20 | T41: =iferror(MONTH(O41),"") -> 8 | U41: =iferror(YEAR(O41),"") -> 2024 | V41: =if(C41="","", IFERROR(DAY(C41),"")) -> 20 | W41: =if(C41="","",IFERROR(MONTH(C41),"")) -> 8 | X41: =if(C41="","",iferror(YEAR(C41),"")) -> 2024
A42: 45524 | C42: =IF(E42="pago",A42,"") -> 45524 | D42: Casa das Embalagens e Limpeza Ltda | E42: Pago | F42: Cartão de Crédito VISA | G42: BANCO DO BRASIL - 65204-0 | H42: CARTÃO VISA - BOLHA, DETERGENTE, PAPEL, ETC. | I42: 162.17 | K42: =if(E42="pago",(I42-J42),"") -> 162.17 | L42: Única | N42: MATERIAL PAPELARIA/COPA/COZINHA | O42: =if(A42="","", TEXT(A42,"mm/yyyy")) -> 08/2024 | P42: =if(C42="","", TEXT(C42,"mm/yyyy")) -> 08/2024 | Q42: {=IFERROR(XLOOKUP(N42,'Classificação'!A:A,'Classificação'!B:B),"")} -> DESPESAS COM OCUPAÇÃO | R42: {=IFERROR(XLOOKUP(Q42,'Classificação'!B:B,'Classificação'!C:C),"")} -> DESPESAS FIXAS (-) | S42: =iferror(DAY(A42),"") -> 20 | T42: =iferror(MONTH(O42),"") -> 8 | U42: =iferror(YEAR(O42),"") -> 2024 | V42: =if(C42="","", IFERROR(DAY(C42),"")) -> 20 | W42: =if(C42="","",IFERROR(MONTH(C42),"")) -> 8 | X42: =if(C42="","",iferror(YEAR(C42),"")) -> 2024
A43: 45524 | C43: =IF(E43="pago",A43,"") -> 45524 | D43: DAS - SIMPLES NACIONAL | E43: Pago | F43: Boleto | G43: BANCO DO BRASIL - 65204-0 | H43: DAS | I43: 19501.98 | K43: =if(E43="pago",(I43-J43),"") -> 19501.98 | L43: Mensal | N43: IMPOSTO DE RENDA - DAS | O43: =if(A43="","", TEXT(A43,"mm/yyyy")) -> 08/2024 | P43: =if(C43="","", TEXT(C43,"mm/yyyy")) -> 08/2024 | Q43: {=IFERROR(XLOOKUP(N43,'Classificação'!A:A,'Classificação'!B:B),"")} -> IMPOSTO DE RENDA - DAS | R43: {=IFERROR(XLOOKUP(Q43,'Classificação'!B:B,'Classificação'!C:C),"")} -> DEDUÇÕES DA RECEITA BRUTA (-) | S43: =iferror(DAY(A43),"") -> 20 | T43: =iferror(MONTH(O43),"") -> 8 | U43: =iferror(YEAR(O43),"") -> 2024 | V43: =if(C43="","", IFERROR(DAY(C43),"")) -> 20 | W43: =if(C43="","",IFERROR(MONTH(C43),"")) -> 8 | X43: =if(C43="","",iferror(YEAR(C43),"")) -> 2024
A44: 45524 | B44: 45453 | C44: =IF(E44="pago",A44,"") -> 45524 | D44: EC OSASCOLAS | E44: Pago | F44: Cartão de Crédito ELO | G44: BANCO DO BRASIL - 65204-0 | H44: CARTÃO ELO - LETREIRO FARMEL | I44: 288.33 | K44: =if(E44="pago",(I44-J44),"") -> 288.33 | L44: Parcelado | M44: 45353 | N44: MARKETING E PUBLICIDADE | O44: =if(A44="","", TEXT(A44,"mm/yyyy")) -> 08/2024 | P44: =if(C44="","", TEXT(C44,"mm/yyyy")) -> 08/2024 | Q44: {=IFERROR(XLOOKUP(N44,'Classificação'!A:A,'Classificação'!B:B),"")} -> DESPESAS ADMINISTRATIVAS | R44: {=IFERROR(XLOOKUP(Q44,'Classificação'!B:B,'Classificação'!C:C),"")} -> DESPESAS FIXAS (-) | S44: =iferror(DAY(A44),"") -> 20 | T44: =iferror(MONTH(O44),"") -> 8 | U44: =iferror(YEAR(O44),"") -> 2024 | V44: =if(C44="","", IFERROR(DAY(C44),"")) -> 20 | W44: =if(C44="","",IFERROR(MONTH(C44),"")) -> 8 | X44: =if(C44="","",iferror(YEAR(C44),"")) -> 2024
A45: 45524 | C45: =IF(E45="pago",A45,"") -> 45524 | D45: EDUZZ MELIPRO | E45: Pago | F45: Cartão de Crédito VISA | G45: BANCO DO BRASIL - 65204-0 | H45: CARTÃO VISA - AVANTPROML | I45: 29.9 | K45: =if(E45="pago",(I45-J45),"") -> 29.9 | L45: Mensal | N45: DESPESA COM SISTEMAS | O45: =if(A45="","", TEXT(A45,"mm/yyyy")) -> 08/2024 | P45: =if(C45="","", TEXT(C45,"mm/yyyy")) -> 08/2024 | Q45: {=IFERROR(XLOOKUP(N45,'Classificação'!A:A,'Classificação'!B:B),"")} -> DESPESAS ADMINISTRATIVAS | R45: {=IFERROR(XLOOKUP(Q45,'Classificação'!B:B,'Classificação'!C:C),"")} -> DESPESAS FIXAS (-) | S45: =iferror(DAY(A45),"") -> 20 | T45: =iferror(MONTH(O45),"") -> 8 | U45: =iferror(YEAR(O45),"") -> 2024 | V45: =if(C45="","", IFERROR(DAY(C45),"")) -> 20 | W45: =if(C45="","",IFERROR(MONTH(C45),"")) -> 8 | X45: =if(C45="","",iferror(YEAR(C45),"")) -> 2024
A46: 45524 | C46: =IF(E46="pago",A46,"") -> 45524 | D46: FGTS | E46: Pago | F46: Boleto | G46: BANCO DO BRASIL - 65204-0 | I46: 335.27 | K46: =if(E46="pago",(I46-J46),"") -> 335.27 | L46: Mensal | N46: FGTS | O46: =if(A46="","", TEXT(A46,"mm/yyyy")) -> 08/2024 | P46: =if(C46="","", TEXT(C46,"mm/yyyy")) -> 08/2024 | Q46: {=IFERROR(XLOOKUP(N46,'Classificação'!A:A,'Classificação'!B:B),"")} -> DESPESAS COM PESSOAL | R46: {=IFERROR(XLOOKUP(Q46,'Classificação'!B:B,'Classificação'!C:C),"")} -> DESPESAS FIXAS (-) | S46: =iferror(DAY(A46),"") -> 20 | T46: =iferror(MONTH(O46),"") -> 8 | U46: =iferror(YEAR(O46),"") -> 2024 | V46: =if(C46="","", IFERROR(DAY(C46),"")) -> 20 | W46: =if(C46="","",IFERROR(MONTH(C46),"")) -> 8 | X46: =if(C46="","",iferror(YEAR(C46),"")) -> 2024
A47: 45524 | B47: 45175 | C47: =IF(E47="pago",A47,"") -> 45524 | D47: William Bezerra de Melo | E47: Pago | F47: Cartão de Crédito ELO | G47: BANCO DO BRASIL - 65204-0 | H47: CARTÃO ELO | I47: 300.5 | K47: =if(E47="pago",(I47-J47),"") -> 300.5 | L47: Parcelado | M47: 45637 | N47: OUTRAS DESPESAS COM PESSOAL | O47: =if(A47="","", TEXT(A47,"mm/yyyy")) -> 08/2024 | P47: =if(C47="","", TEXT(C47,"mm/yyyy")) -> 08/2024 | Q47: {=IFERROR(XLOOKUP(N47,'Classificação'!A:A,'Classificação'!B:B),"")} -> DESPESAS COM PESSOAL | R47: {=IFERROR(XLOOKUP(Q47,'Classificação'!B:B,'Classificação'!C:C),"")} -> DESPESAS FIXAS (-) | S47: =iferror(DAY(A47),"") -> 20 | T47: =iferror(MONTH(O47),"") -> 8 | U47: =iferror(YEAR(O47),"") -> 2024 | V47: =if(C47="","", IFERROR(DAY(C47),"")) -> 20 | W47: =if(C47="","",IFERROR(MONTH(C47),"")) -> 8 | X47: =if(C47="","",iferror(YEAR(C47),"")) -> 2024
A48: 45524 | B48: 45450 | C48: =IF(E48="pago",A48,"") -> 45524 | D48: HAVAN | E48: Pago | F48: Cartão de Crédito ELO | G48: BANCO DO BRASIL - 65204-0 | H48: CARTÃO ELO | I48: 64.75 | K48: =if(E48="pago",(I48-J48),"") -> 64.75 | L48: Parcelado | M48: 45414 | N48: COMPRA DE BENS/EQUIPAMENTOS | O48: =if(A48="","", TEXT(A48,"mm/yyyy")) -> 08/2024 | P48: =if(C48="","", TEXT(C48,"mm/yyyy")) -> 08/2024 | Q48: {=IFERROR(XLOOKUP(N48,'Classificação'!A:A,'Classificação'!B:B),"")} -> DESPESAS NÃO OPERACIONAIS | R48: {=IFERROR(XLOOKUP(Q48,'Classificação'!B:B,'Classificação'!C:C),"")} -> RESULTADO NÃO OPERACIONAL (+/-) | S48: =iferror(DAY(A48),"") -> 20 | T48: =iferror(MONTH(O48),"") -> 8 | U48: =iferror(YEAR(O48),"") -> 2024 | V48: =if(C48="","", IFERROR(DAY(C48),"")) -> 20 | W48: =if(C48="","",IFERROR(MONTH(C48),"")) -> 8 | X48: =if(C48="","",iferror(YEAR(C48),"")) -> 2024
A49: 45524 | C49: =IF(E49="pago",A49,"") -> 45524 | D49: INSS | E49: Pago | F49: Boleto | G49: BANCO DO BRASIL - 65204-0 | I49: 521.38 | K49: =if(E49="pago",(I49-J49),"") -> 521.38 | L49: Mensal | N49: INSS | O49: =if(A49="","", TEXT(A49,"mm/yyyy")) -> 08/2024 | P49: =if(C49="","", TEXT(C49,"mm/yyyy")) -> 08/2024 | Q49: {=IFERROR(XLOOKUP(N49,'Classificação'!A:A,'Classificação'!B:B),"")} -> DESPESAS COM PESSOAL | R49: {=IFERROR(XLOOKUP(Q49,'Classificação'!B:B,'Classificação'!C:C),"")} -> DESPESAS FIXAS (-) | S49: =iferror(DAY(A49),"") -> 20 | T49: =iferror(MONTH(O49),"") -> 8 | U49: =iferror(YEAR(O49),"") -> 2024 | V49: =if(C49="","", IFERROR(DAY(C49),"")) -> 20 | W49: =if(C49="","",IFERROR(MONTH(C49),"")) -> 8 | X49: =if(C49="","",iferror(YEAR(C49),"")) -> 2024
A50: 45524 | C50: =IF(E50="pago",A50,"") -> 45524 | D50: JOVINA MOREIRA MENDES DIARISTA | E50: Pago | F50: Pix | G50: MERCADO PAGO SINCE - 9511092439-1 | H50: Inicio em 23/01/24 Ter/qua/qui e sab por + ou - 2 horas PEDIDO 54026 R$ 119,40 (descontar em 2x mes 7 e mes 8) | I50: 540.3 | K50: =if(E50="pago",(I50-J50),"") -> 540.3 | L50: Mensal | N50: SERVIÇOS TERCEIRIZADOS | O50: =if(A50="","", TEXT(A50,"mm/yyyy")) -> 08/2024 | P50: =if(C50="","", TEXT(C50,"mm/yyyy")) -> 08/2024 | Q50: {=IFERROR(XLOOKUP(N50,'Classificação'!A:A,'Classificação'!B:B),"")} -> DESPESAS ADMINISTRATIVAS | R50: {=IFERROR(XLOOKUP(Q50,'Classificação'!B:B,'Classificação'!C:C),"")} -> DESPESAS FIXAS (-) | S50: =iferror(DAY(A50),"") -> 20 | T50: =iferror(MONTH(O50),"") -> 8 | U50: =iferror(YEAR(O50),"") -> 2024 | V50: =if(C50="","", IFERROR(DAY(C50),"")) -> 20 | W50: =if(C50="","",IFERROR(MONTH(C50),"")) -> 8 | X50: =if(C50="","",iferror(YEAR(C50),"")) -> 2024
A51: 45524 | B51: 45485 | C51: =IF(E51="pago",A51,"") -> 45524 | D51: Larissa Moraes | E51: Pago | F51: Cartão de Crédito ELO | G51: BANCO DO BRASIL - 65204-0 | H51: Cartão Elo | I51: 330 | K51: =if(E51="pago",(I51-J51),"") -> 330 | L51: Parcelado | M51: 45413 | N51: COMPRA DE BENS/EQUIPAMENTOS | O51: =if(A51="","", TEXT(A51,"mm/yyyy")) -> 08/2024 | P51: =if(C51="","", TEXT(C51,"mm/yyyy")) -> 08/2024 | Q51: {=IFERROR(XLOOKUP(N51,'Classificação'!A:A,'Classificação'!B:B),"")} -> DESPESAS NÃO OPERACIONAIS | R51: {=IFERROR(XLOOKUP(Q51,'Classificação'!B:B,'Classificação'!C:C),"")} -> RESULTADO NÃO OPERACIONAL (+/-) | S51: =iferror(DAY(A51),"") -> 20 | T51: =iferror(MONTH(O51),"") -> 8 | U51: =iferror(YEAR(O51),"") -> 2024 | V51: =if(C51="","", IFERROR(DAY(C51),"")) -> 20 | W51: =if(C51="","",IFERROR(MONTH(C51),"")) -> 8 | X51: =if(C51="","",iferror(YEAR(C51),"")) -> 2024
A52: 45524 | B52: 45427 | C52: =IF(E52="pago",A52,"") -> 45524 | D52: LIBERTY SEGURO - SEGURADORA | E52: Pago | F52: Cartão de Crédito ELO | G52: BANCO DO BRASIL - 65204-0 | H52: Cartão Elo - | I52: 249.33 | K52: =if(E52="pago",(I52-J52),"") -> 249.33 | L52: Parcelado | M52: 45629 | N52: SEGUROS DE VEÍCULOS | O52: =if(A52="","", TEXT(A52,"mm/yyyy")) -> 08/2024 | P52: =if(C52="","", TEXT(C52,"mm/yyyy")) -> 08/2024 | Q52: {=IFERROR(XLOOKUP(N52,'Classificação'!A:A,'Classificação'!B:B),"")} -> DESPESAS COM VEICULOS | R52: {=IFERROR(XLOOKUP(Q52,'Classificação'!B:B,'Classificação'!C:C),"")} -> DESPESAS FIXAS (-) | S52: =iferror(DAY(A52),"") -> 20 | T52: =iferror(MONTH(O52),"") -> 8 | U52: =iferror(YEAR(O52),"") -> 2024 | V52: =if(C52="","", IFERROR(DAY(C52),"")) -> 20 | W52: =if(C52="","",IFERROR(MONTH(C52),"")) -> 8 | X52: =if(C52="","",iferror(YEAR(C52),"")) -> 2024
A53: 45524 | C53: =IF(E53="pago",A53,"") -> 45524 | D53: LIMPA MAIS | E53: Pago | F53: Cartão de Crédito VISA | G53: BANCO DO BRASIL - 65204-0 | H53: CARTÃO VISA - CANDIDA, INTERFOLHA, AZULIN, SACO LIXO | I53: 89.35 | K53: =if(E53="pago",(I53-J53),"") -> 89.35 | L53: Única | N53: MATERIAL LIMPEZA/CONSERVAÇÃO | O53: =if(A53="","", TEXT(A53,"mm/yyyy")) -> 08/2024 | P53: =if(C53="","", TEXT(C53,"mm/yyyy")) -> 08/2024 | Q53: {=IFERROR(XLOOKUP(N53,'Classificação'!A:A,'Classificação'!B:B),"")} -> DESPESAS COM OCUPAÇÃO | R53: {=IFERROR(XLOOKUP(Q53,'Classificação'!B:B,'Classificação'!C:C),"")} -> DESPESAS FIXAS (-) | S53: =iferror(DAY(A53),"") -> 20 | T53: =iferror(MONTH(O53),"") -> 8 | U53: =iferror(YEAR(O53),"") -> 2024 | V53: =if(C53="","", IFERROR(DAY(C53),"")) -> 20 | W53: =if(C53="","",IFERROR(MONTH(C53),"")) -> 8 | X53: =if(C53="","",iferror(YEAR(C53),"")) -> 2024
A54: 45524 | B54: 45481 | C54: =IF(E54="pago",A54,"") -> 45524 | D54: MELHOR ENVIO | E54: Pago | F54: Cartão de Crédito ELO | G54: BANCO DO BRASIL - 65204-0 | H54: Cartão Elo - FRETE PEDIDOS AMAZON | I54: 33.56 | K54: =if(E54="pago",(I54-J54),"") -> 33.56 | L54: Única | N54: FRETE DE VENDAS | O54: =if(A54="","", TEXT(A54,"mm/yyyy")) -> 08/2024 | P54: =if(C54="","", TEXT(C54,"mm/yyyy")) -> 08/2024 | Q54: {=IFERROR(XLOOKUP(N54,'Classificação'!A:A,'Classificação'!B:B),"")} -> FRETE DE VENDAS | R54: {=IFERROR(XLOOKUP(Q54,'Classificação'!B:B,'Classificação'!C:C),"")} -> CUSTOS VARIÁVEIS | S54: =iferror(DAY(A54),"") -> 20 | T54: =iferror(MONTH(O54),"") -> 8 | U54: =iferror(YEAR(O54),"") -> 2024 | V54: =if(C54="","", IFERROR(DAY(C54),"")) -> 20 | W54: =if(C54="","",IFERROR(MONTH(C54),"")) -> 8 | X54: =if(C54="","",iferror(YEAR(C54),"")) -> 2024
A55: 45524 | B55: 45481 | C55: =IF(E55="pago",A55,"") -> 45524 | D55: MELHOR ENVIO | E55: Pago | F55: Cartão de Crédito ELO | G55: BANCO DO BRASIL - 65204-0 | H55: Cartão Elo - FRETE PEDIDOS AMAZON | I55: 240.62 | K55: =if(E55="pago",(I55-J55),"") -> 240.62 | L55: Única | N55: FRETE DE VENDAS | O55: =if(A55="","", TEXT(A55,"mm/yyyy")) -> 08/2024 | P55: =if(C55="","", TEXT(C55,"mm/yyyy")) -> 08/2024 | Q55: {=IFERROR(XLOOKUP(N55,'Classificação'!A:A,'Classificação'!B:B),"")} -> FRETE DE VENDAS | R55: {=IFERROR(XLOOKUP(Q55,'Classificação'!B:B,'Classificação'!C:C),"")} -> CUSTOS VARIÁVEIS | S55: =iferror(DAY(A55),"") -> 20 | T55: =iferror(MONTH(O55),"") -> 8 | U55: =iferror(YEAR(O55),"") -> 2024 | V55: =if(C55="","", IFERROR(DAY(C55),"")) -> 20 | W55: =if(C55="","",IFERROR(MONTH(C55),"")) -> 8 | X55: =if(C55="","",iferror(YEAR(C55),"")) -> 2024
A56: 45524 | B56: 45481 | C56: =IF(E56="pago",A56,"") -> 45524 | D56: MELHOR ENVIO | E56: Pago | F56: Cartão de Crédito ELO | G56: BANCO DO BRASIL - 65204-0 | H56: Cartão Elo - FRETE PEDIDOS AMAZON | I56: 22.39 | K56: =if(E56="pago",(I56-J56),"") -> 22.39 | L56: Única | N56: FRETE DE VENDAS | O56: =if(A56="","", TEXT(A56,"mm/yyyy")) -> 08/2024 | P56: =if(C56="","", TEXT(C56,"mm/yyyy")) -> 08/2024 | Q56: {=IFERROR(XLOOKUP(N56,'Classificação'!A:A,'Classificação'!B:B),"")} -> FRETE DE VENDAS | R56: {=IFERROR(XLOOKUP(Q56,'Classificação'!B:B,'Classificação'!C:C),"")} -> CUSTOS VARIÁVEIS | S56: =iferror(DAY(A56),"") -> 20 | T56: =iferror(MONTH(O56),"") -> 8 | U56: =iferror(YEAR(O56),"") -> 2024 | V56: =if(C56="","", IFERROR(DAY(C56),"")) -> 20 | W56: =if(C56="","",IFERROR(MONTH(C56),"")) -> 8 | X56: =if(C56="","",iferror(YEAR(C56),"")) -> 2024
A57: 45524 | B57: 45483 | C57: =IF(E57="pago",A57,"") -> 45524 | D57: MELHOR ENVIO | E57: Pago | F57: Cartão de Crédito ELO | G57: BANCO DO BRASIL - 65204-0 | H57: Cartão Elo - FRETE PEDIDOS AMAZON | I57: 189.111 | K57: =if(E57="pago",(I57-J57),"") -> 189.111 | L57: Única | N57: FRETE DE VENDAS | O57: =if(A57="","", TEXT(A57,"mm/yyyy")) -> 08/2024 | P57: =if(C57="","", TEXT(C57,"mm/yyyy")) -> 08/2024 | Q57: {=IFERROR(XLOOKUP(N57,'Classificação'!A:A,'Classificação'!B:B),"")} -> FRETE DE VENDAS | R57: {=IFERROR(XLOOKUP(Q57,'Classificação'!B:B,'Classificação'!C:C),"")} -> CUSTOS VARIÁVEIS | S57: =iferror(DAY(A57),"") -> 20 | T57: =iferror(MONTH(O57),"") -> 8 | U57: =iferror(YEAR(O57),"") -> 2024 | V57: =if(C57="","", IFERROR(DAY(C57),"")) -> 20 | W57: =if(C57="","",IFERROR(MONTH(C57),"")) -> 8 | X57: =if(C57="","",iferror(YEAR(C57),"")) -> 2024
A58: 45524 | B58: 45417 | C58: =IF(E58="pago",A58,"") -> 45524 | D58: MERCADO LIVRE | E58: Pago | F58: Cartão de Crédito ELO | G58: BANCO DO BRASIL - 65204-0 | H58: CARTÃO ELO - FONE DE OUVIDO ELAINE | I58: 85.82 | K58: =if(E58="pago",(I58-J58),"") -> 85.82 | L58: Única | N58: OUTRAS DESPESAS COM PESSOAL | O58: =if(A58="","", TEXT(A58,"mm/yyyy")) -> 08/2024 | P58: =if(C58="","", TEXT(C58,"mm/yyyy")) -> 08/2024 | Q58: {=IFERROR(XLOOKUP(N58,'Classificação'!A:A,'Classificação'!B:B),"")} -> DESPESAS COM PESSOAL | R58: {=IFERROR(XLOOKUP(Q58,'Classificação'!B:B,'Classificação'!C:C),"")} -> DESPESAS FIXAS (-) | S58: =iferror(DAY(A58),"") -> 20 | T58: =iferror(MONTH(O58),"") -> 8 | U58: =iferror(YEAR(O58),"") -> 2024 | V58: =if(C58="","", IFERROR(DAY(C58),"")) -> 20 | W58: =if(C58="","",IFERROR(MONTH(C58),"")) -> 8 | X58: =if(C58="","",iferror(YEAR(C58),"")) -> 2024
A59: 45524 | B59: 45272 | C59: =IF(E59="pago",A59,"") -> 45524 | D59: MERCADO LIVRE | E59: Pago | F59: Cartão de Crédito ELO | G59: BANCO DO BRASIL - 65204-0 | H59: CARTÃO ELO - NOTEBOOK | I59: 126.9 | K59: =if(E59="pago",(I59-J59),"") -> 126.9 | L59: Parcelado | M59: 45573 | N59: COMPRA DE BENS/EQUIPAMENTOS | O59: =if(A59="","", TEXT(A59,"mm/yyyy")) -> 08/2024 | P59: =if(C59="","", TEXT(C59,"mm/yyyy")) -> 08/2024 | Q59: {=IFERROR(XLOOKUP(N59,'Classificação'!A:A,'Classificação'!B:B),"")} -> DESPESAS NÃO OPERACIONAIS | R59: {=IFERROR(XLOOKUP(Q59,'Classificação'!B:B,'Classificação'!C:C),"")} -> RESULTADO NÃO OPERACIONAL (+/-) | S59: =iferror(DAY(A59),"") -> 20 | T59: =iferror(MONTH(O59),"") -> 8 | U59: =iferror(YEAR(O59),"") -> 2024 | V59: =if(C59="","", IFERROR(DAY(C59),"")) -> 20 | W59: =if(C59="","",IFERROR(MONTH(C59),"")) -> 8 | X59: =if(C59="","",iferror(YEAR(C59),"")) -> 2024
A60: 45524 | B60: 45349 | C60: =IF(E60="pago",A60,"") -> 45524 | D60: MERCADO LIVRE | E60: Pago | F60: Cartão de Crédito ELO | G60: BANCO DO BRASIL - 65204-0 | H60: CARTÃO ELO - 2 ventiladores de parede | I60: 79.92 | K60: =if(E60="pago",(I60-J60),"") -> 79.92 | L60: Parcelado | M60: 45571 | N60: COMPRA DE BENS/EQUIPAMENTOS | O60: =if(A60="","", TEXT(A60,"mm/yyyy")) -> 08/2024 | P60: =if(C60="","", TEXT(C60,"mm/yyyy")) -> 08/2024 | Q60: {=IFERROR(XLOOKUP(N60,'Classificação'!A:A,'Classificação'!B:B),"")} -> DESPESAS NÃO OPERACIONAIS | R60: {=IFERROR(XLOOKUP(Q60,'Classificação'!B:B,'Classificação'!C:C),"")} -> RESULTADO NÃO OPERACIONAL (+/-) | S60: =iferror(DAY(A60),"") -> 20 | T60: =iferror(MONTH(O60),"") -> 8 | U60: =iferror(YEAR(O60),"") -> 2024 | V60: =if(C60="","", IFERROR(DAY(C60),"")) -> 20 | W60: =if(C60="","",IFERROR(MONTH(C60),"")) -> 8 | X60: =if(C60="","",iferror(YEAR(C60),"")) -> 2024
A61: 45524 | C61: =IF(E61="pago",A61,"") -> 45524 | D61: MERCADO LIVRE | E61: Pago | F61: Cartão de Crédito ELO | G61: BANCO DO BRASIL - 65204-0 | H61: CARTÃO ELO - ENVELOPES PARA ENVIO | I61: 36.7 | K61: =if(E61="pago",(I61-J61),"") -> 36.7 | L61: Única | N61: EMBALAGENS/FITAS/GERAL | O61: =if(A61="","", TEXT(A61,"mm/yyyy")) -> 08/2024 | P61: =if(C61="","", TEXT(C61,"mm/yyyy")) -> 08/2024 | Q61: {=IFERROR(XLOOKUP(N61,'Classificação'!A:A,'Classificação'!B:B),"")} -> EMBALAGENS/FITAS/GERAL | R61: {=IFERROR(XLOOKUP(Q61,'Classificação'!B:B,'Classificação'!C:C),"")} -> CUSTOS VARIÁVEIS | S61: =iferror(DAY(A61),"") -> 20 | T61: =iferror(MONTH(O61),"") -> 8 | U61: =iferror(YEAR(O61),"") -> 2024 | V61: =if(C61="","", IFERROR(DAY(C61),"")) -> 20 | W61: =if(C61="","",IFERROR(MONTH(C61),"")) -> 8 | X61: =if(C61="","",iferror(YEAR(C61),"")) -> 2024
A62: 45524 | B62: 45393 | C62: =IF(E62="pago",A62,"") -> 45524 | D62: MERCADO LIVRE | E62: Pago | F62: Cartão de Crédito ELO | G62: BANCO DO BRASIL - 65204-0 | H62: CARTÃO ELO - pistão para cadeira | I62: 32.47 | K62: =if(E62="pago",(I62-J62),"") -> 32.47 | L62: Única | N62: MANUTENÇÃO BENS DE EXPEDIENTE | O62: =if(A62="","", TEXT(A62,"mm/yyyy")) -> 08/2024 | P62: =if(C62="","", TEXT(C62,"mm/yyyy")) -> 08/2024 | Q62: {=IFERROR(XLOOKUP(N62,'Classificação'!A:A,'Classificação'!B:B),"")} -> DESPESAS ADMINISTRATIVAS | R62: {=IFERROR(XLOOKUP(Q62,'Classificação'!B:B,'Classificação'!C:C),"")} -> DESPESAS FIXAS (-) | S62: =iferror(DAY(A62),"") -> 20 | T62: =iferror(MONTH(O62),"") -> 8 | U62: =iferror(YEAR(O62),"") -> 2024 | V62: =if(C62="","", IFERROR(DAY(C62),"")) -> 20 | W62: =if(C62="","",IFERROR(MONTH(C62),"")) -> 8 | X62: =if(C62="","",iferror(YEAR(C62),"")) -> 2024
A63: 45524 | B63: 45411 | C63: =IF(E63="pago",A63,"") -> 45524 | D63: MERCADO LIVRE | E63: Pago | F63: Cartão de Crédito ELO | G63: BANCO DO BRASIL - 65204-0 | H63: CARTÃO ELO - pistão para cadeira | I63: 32.48 | K63: =if(E63="pago",(I63-J63),"") -> 32.48 | L63: Única | N63: MANUTENÇÃO BENS DE EXPEDIENTE | O63: =if(A63="","", TEXT(A63,"mm/yyyy")) -> 08/2024 | P63: =if(C63="","", TEXT(C63,"mm/yyyy")) -> 08/2024 | Q63: {=IFERROR(XLOOKUP(N63,'Classificação'!A:A,'Classificação'!B:B),"")} -> DESPESAS ADMINISTRATIVAS | R63: {=IFERROR(XLOOKUP(Q63,'Classificação'!B:B,'Classificação'!C:C),"")} -> DESPESAS FIXAS (-) | S63: =iferror(DAY(A63),"") -> 20 | T63: =iferror(MONTH(O63),"") -> 8 | U63: =iferror(YEAR(O63),"") -> 2024 | V63: =if(C63="","", IFERROR(DAY(C63),"")) -> 20 | W63: =if(C63="","",IFERROR(MONTH(C63),"")) -> 8 | X63: =if(C63="","",iferror(YEAR(C63),"")) -> 2024
A64: 45524 | B64: 45439 | C64: =IF(E64="pago",A64,"") -> 45524 | D64: MERCADO LIVRE | E64: Pago | F64: Cartão de Crédito ELO | G64: BANCO DO BRASIL - 65204-0 | H64: CARTÃO ELO - CELULAR ATENDIMENTO FARMEL | I64: 64.9 | K64: =if(E64="pago",(I64-J64),"") -> 64.9 | L64: Parcelado | M64: 45568 | N64: COMPRA DE BENS/EQUIPAMENTOS | O64: =if(A64="","", TEXT(A64,"mm/yyyy")) -> 08/2024 | P64: =if(C64="","", TEXT(C64,"mm/yyyy")) -> 08/2024 | Q64: {=IFERROR(XLOOKUP(N64,'Classificação'!A:A,'Classificação'!B:B),"")} -> DESPESAS NÃO OPERACIONAIS | R64: {=IFERROR(XLOOKUP(Q64,'Classificação'!B:B,'Classificação'!C:C),"")} -> RESULTADO NÃO OPERACIONAL (+/-) | S64: =iferror(DAY(A64),"") -> 20 | T64: =iferror(MONTH(O64),"") -> 8 | U64: =iferror(YEAR(O64),"") -> 2024 | V64: =if(C64="","", IFERROR(DAY(C64),"")) -> 20 | W64: =if(C64="","",IFERROR(MONTH(C64),"")) -> 8 | X64: =if(C64="","",iferror(YEAR(C64),"")) -> 2024
A65: 45524 | B65: 45474 | C65: =IF(E65="pago",A65,"") -> 45524 | D65: MERCADO LIVRE | E65: Pago | F65: Cartão de Crédito ELO | G65: BANCO DO BRASIL - 65204-0 | H65: CARTÃO ELO - transformador 220-110 para Adriane | I65: 93.37 | K65: =if(E65="pago",(I65-J65),"") -> 93.37 | L65: Única | N65: OUTRAS DESPESAS COM PESSOAL | O65: =if(A65="","", TEXT(A65,"mm/yyyy")) -> 08/2024 | P65: =if(C65="","", TEXT(C65,"mm/yyyy")) -> 08/2024 | Q65: {=IFERROR(XLOOKUP(N65,'Classificação'!A:A,'Classificação'!B:B),"")} -> DESPESAS COM PESSOAL | R65: {=IFERROR(XLOOKUP(Q65,'Classificação'!B:B,'Classificação'!C:C),"")} -> DESPESAS FIXAS (-) | S65: =iferror(DAY(A65),"") -> 20 | T65: =iferror(MONTH(O65),"") -> 8 | U65: =iferror(YEAR(O65),"") -> 2024 | V65: =if(C65="","", IFERROR(DAY(C65),"")) -> 20 | W65: =if(C65="","",IFERROR(MONTH(C65),"")) -> 8 | X65: =if(C65="","",iferror(YEAR(C65),"")) -> 2024
A66: 45524 | B66: 45467 | C66: =IF(E66="pago",A66,"") -> 45524 | D66: MERCADO LIVRE | E66: Pago | F66: Cartão de Crédito ELO | G66: BANCO DO BRASIL - 65204-0 | H66: CARTÃO ELO - Envelopes, fita mágica, adesivos | I66: 36.6 | K66: =if(E66="pago",(I66-J66),"") -> 36.6 | L66: Parcelado | M66: 45384 | N66: EMBALAGENS/FITAS/GERAL | O66: =if(A66="","", TEXT(A66,"mm/yyyy")) -> 08/2024 | P66: =if(C66="","", TEXT(C66,"mm/yyyy")) -> 08/2024 | Q66: {=IFERROR(XLOOKUP(N66,'Classificação'!A:A,'Classificação'!B:B),"")} -> EMBALAGENS/FITAS/GERAL | R66: {=IFERROR(XLOOKUP(Q66,'Classificação'!B:B,'Classificação'!C:C),"")} -> CUSTOS VARIÁVEIS | S66: =iferror(DAY(A66),"") -> 20 | T66: =iferror(MONTH(O66),"") -> 8 | U66: =iferror(YEAR(O66),"") -> 2024 | V66: =if(C66="","", IFERROR(DAY(C66),"")) -> 20 | W66: =if(C66="","",IFERROR(MONTH(C66),"")) -> 8 | X66: =if(C66="","",iferror(YEAR(C66),"")) -> 2024
A67: 45524 | B67: 45462 | C67: =IF(E67="pago",A67,"") -> 45524 | D67: MERCADO LIVRE | E67: Pago | F67: Cartão de Crédito ELO | G67: BANCO DO BRASIL - 65204-0 | H67: CARTÃO ELO -Fita embalagem, tonner | I67: 30.94 | K67: =if(E67="pago",(I67-J67),"") -> 30.94 | L67: Parcelado | M67: 45353 | N67: EMBALAGENS/FITAS/GERAL | O67: =if(A67="","", TEXT(A67,"mm/yyyy")) -> 08/2024 | P67: =if(C67="","", TEXT(C67,"mm/yyyy")) -> 08/2024 | Q67: {=IFERROR(XLOOKUP(N67,'Classificação'!A:A,'Classificação'!B:B),"")} -> EMBALAGENS/FITAS/GERAL | R67: {=IFERROR(XLOOKUP(Q67,'Classificação'!B:B,'Classificação'!C:C),"")} -> CUSTOS VARIÁVEIS | S67: =iferror(DAY(A67),"") -> 20 | T67: =iferror(MONTH(O67),"") -> 8 | U67: =iferror(YEAR(O67),"") -> 2024 | V67: =if(C67="","", IFERROR(DAY(C67),"")) -> 20 | W67: =if(C67="","",IFERROR(MONTH(C67),"")) -> 8 | X67: =if(C67="","",iferror(YEAR(C67),"")) -> 2024
A68: 45524 | B68: 45450 | C68: =IF(E68="pago",A68,"") -> 45524 | D68: MERCADO LIVRE | E68: Pago | F68: Cartão de Crédito ELO | G68: BANCO DO BRASIL - 65204-0 | H68: CARTÃO ELO - Espelho e Suporte Banheiro | I68: 202.87 | K68: =if(E68="pago",(I68-J68),"") -> 202.87 | L68: Única | N68: COMPRA DE BENS/EQUIPAMENTOS | O68: =if(A68="","", TEXT(A68,"mm/yyyy")) -> 08/2024 | P68: =if(C68="","", TEXT(C68,"mm/yyyy")) -> 08/2024 | Q68: {=IFERROR(XLOOKUP(N68,'Classificação'!A:A,'Classificação'!B:B),"")} -> DESPESAS NÃO OPERACIONAIS | R68: {=IFERROR(XLOOKUP(Q68,'Classificação'!B:B,'Classificação'!C:C),"")} -> RESULTADO NÃO OPERACIONAL (+/-) | S68: =iferror(DAY(A68),"") -> 20 | T68: =iferror(MONTH(O68),"") -> 8 | U68: =iferror(YEAR(O68),"") -> 2024 | V68: =if(C68="","", IFERROR(DAY(C68),"")) -> 20 | W68: =if(C68="","",IFERROR(MONTH(C68),"")) -> 8 | X68: =if(C68="","",iferror(YEAR(C68),"")) -> 2024
A69: 45524 | B69: 45450 | C69: =IF(E69="pago",A69,"") -> 45524 | D69: MERCADO LIVRE | E69: Pago | F69: Cartão de Crédito ELO | G69: BANCO DO BRASIL - 65204-0 | H69: CARTÃO ELO - Envelopes, fitas | I69: 328.58 | K69: =if(E69="pago",(I69-J69),"") -> 328.58 | L69: Única | N69: COMPRA DE BENS/EQUIPAMENTOS | O69: =if(A69="","", TEXT(A69,"mm/yyyy")) -> 08/2024 | P69: =if(C69="","", TEXT(C69,"mm/yyyy")) -> 08/2024 | Q69: {=IFERROR(XLOOKUP(N69,'Classificação'!A:A,'Classificação'!B:B),"")} -> DESPESAS NÃO OPERACIONAIS | R69: {=IFERROR(XLOOKUP(Q69,'Classificação'!B:B,'Classificação'!C:C),"")} -> RESULTADO NÃO OPERACIONAL (+/-) | S69: =iferror(DAY(A69),"") -> 20 | T69: =iferror(MONTH(O69),"") -> 8 | U69: =iferror(YEAR(O69),"") -> 2024 | V69: =if(C69="","", IFERROR(DAY(C69),"")) -> 20 | W69: =if(C69="","",IFERROR(MONTH(C69),"")) -> 8 | X69: =if(C69="","",iferror(YEAR(C69),"")) -> 2024
A70: 45524 | B70: 45485 | C70: =IF(E70="pago",A70,"") -> 45524 | D70: MERCADO LIVRE | E70: Pago | F70: Cartão de Crédito ELO | G70: BANCO DO BRASIL - 65204-0 | H70: CARTÃO ELO - FITAS, ISOPOR E ENVELOPE | I70: 175.45 | K70: =if(E70="pago",(I70-J70),"") -> 175.45 | L70: Única | N70: COMPRA DE BENS/EQUIPAMENTOS | O70: =if(A70="","", TEXT(A70,"mm/yyyy")) -> 08/2024 | P70: =if(C70="","", TEXT(C70,"mm/yyyy")) -> 08/2024 | Q70: {=IFERROR(XLOOKUP(N70,'Classificação'!A:A,'Classificação'!B:B),"")} -> DESPESAS NÃO OPERACIONAIS | R70: {=IFERROR(XLOOKUP(Q70,'Classificação'!B:B,'Classificação'!C:C),"")} -> RESULTADO NÃO OPERACIONAL (+/-) | S70: =iferror(DAY(A70),"") -> 20 | T70: =iferror(MONTH(O70),"") -> 8 | U70: =iferror(YEAR(O70),"") -> 2024 | V70: =if(C70="","", IFERROR(DAY(C70),"")) -> 20 | W70: =if(C70="","",IFERROR(MONTH(C70),"")) -> 8 | X70: =if(C70="","",iferror(YEAR(C70),"")) -> 2024
A71: 45524 | B71: 45485 | C71: =IF(E71="pago",A71,"") -> 45524 | D71: MERCADO LIVRE | E71: Pago | F71: Cartão de Crédito ELO | G71: BANCO DO BRASIL - 65204-0 | H71: CARTÃO ELO - FITAS, ISOPOR E ENVELOPE | I71: 56.51 | K71: =if(E71="pago",(I71-J71),"") -> 56.51 | L71: Parcelado | M71: 45352 | N71: EMBALAGENS/FITAS/GERAL | O71: =if(A71="","", TEXT(A71,"mm/yyyy")) -> 08/2024 | P71: =if(C71="","", TEXT(C71,"mm/yyyy")) -> 08/2024 | Q71: {=IFERROR(XLOOKUP(N71,'Classificação'!A:A,'Classificação'!B:B),"")} -> EMBALAGENS/FITAS/GERAL | R71: {=IFERROR(XLOOKUP(Q71,'Classificação'!B:B,'Classificação'!C:C),"")} -> CUSTOS VARIÁVEIS | S71: =iferror(DAY(A71),"") -> 20 | T71: =iferror(MONTH(O71),"") -> 8 | U71: =iferror(YEAR(O71),"") -> 2024 | V71: =if(C71="","", IFERROR(DAY(C71),"")) -> 20 | W71: =if(C71="","",IFERROR(MONTH(C71),"")) -> 8 | X71: =if(C71="","",iferror(YEAR(C71),"")) -> 2024
A72: 45524 | B72: 45483 | C72: =IF(E72="pago",A72,"") -> 45524 | D72: MERCADO LIVRE | E72: Pago | F72: Cartão de Crédito ELO | G72: BANCO DO BRASIL - 65204-0 | H72: CARTÃO ELO - ENVELOPE, FITA, SULFITE | I72: 406.16 | K72: =if(E72="pago",(I72-J72),"") -> 406.16 | L72: Única | N72: EMBALAGENS/FITAS/GERAL | O72: =if(A72="","", TEXT(A72,"mm/yyyy")) -> 08/2024 | P72: =if(C72="","", TEXT(C72,"mm/yyyy")) -> 08/2024 | Q72: {=IFERROR(XLOOKUP(N72,'Classificação'!A:A,'Classificação'!B:B),"")} -> EMBALAGENS/FITAS/GERAL | R72: {=IFERROR(XLOOKUP(Q72,'Classificação'!B:B,'Classificação'!C:C),"")} -> CUSTOS VARIÁVEIS | S72: =iferror(DAY(A72),"") -> 20 | T72: =iferror(MONTH(O72),"") -> 8 | U72: =iferror(YEAR(O72),"") -> 2024 | V72: =if(C72="","", IFERROR(DAY(C72),"")) -> 20 | W72: =if(C72="","",IFERROR(MONTH(C72),"")) -> 8 | X72: =if(C72="","",iferror(YEAR(C72),"")) -> 2024
A73: 45524 | B73: 45460 | C73: =IF(E73="pago",A73,"") -> 45524 | D73: MERCADO LIVRE | E73: Pago | F73: Cartão de Crédito ELO | G73: BANCO DO BRASIL - 65204-0 | H73: CARTÃO ELO - LUMINÁRIA SALA ADMINISTRAÇÃO | I73: 48.89 | K73: =if(E73="pago",(I73-J73),"") -> 48.89 | L73: Única | N73: COMPRA DE BENS/EQUIPAMENTOS | O73: =if(A73="","", TEXT(A73,"mm/yyyy")) -> 08/2024 | P73: =if(C73="","", TEXT(C73,"mm/yyyy")) -> 08/2024 | Q73: {=IFERROR(XLOOKUP(N73,'Classificação'!A:A,'Classificação'!B:B),"")} -> DESPESAS NÃO OPERACIONAIS | R73: {=IFERROR(XLOOKUP(Q73,'Classificação'!B:B,'Classificação'!C:C),"")} -> RESULTADO NÃO OPERACIONAL (+/-) | S73: =iferror(DAY(A73),"") -> 20 | T73: =iferror(MONTH(O73),"") -> 8 | U73: =iferror(YEAR(O73),"") -> 2024 | V73: =if(C73="","", IFERROR(DAY(C73),"")) -> 20 | W73: =if(C73="","",IFERROR(MONTH(C73),"")) -> 8 | X73: =if(C73="","",iferror(YEAR(C73),"")) -> 2024
A74: 45524 | B74: 45861 | C74: =IF(E74="pago",A74,"") -> 45524 | D74: MERCADO LIVRE | E74: Pago | F74: Cartão de Crédito ELO | G74: BANCO DO BRASIL - 65204-0 | H74: CARTÃO ELO - Leitor código de barras | I74: 65.44 | K74: =if(E74="pago",(I74-J74),"") -> 65.44 | L74: Única | N74: COMPRA DE BENS/EQUIPAMENTOS | O74: =if(A74="","", TEXT(A74,"mm/yyyy")) -> 08/2024 | P74: =if(C74="","", TEXT(C74,"mm/yyyy")) -> 08/2024 | Q74: {=IFERROR(XLOOKUP(N74,'Classificação'!A:A,'Classificação'!B:B),"")} -> DESPESAS NÃO OPERACIONAIS | R74: {=IFERROR(XLOOKUP(Q74,'Classificação'!B:B,'Classificação'!C:C),"")} -> RESULTADO NÃO OPERACIONAL (+/-) | S74: =iferror(DAY(A74),"") -> 20 | T74: =iferror(MONTH(O74),"") -> 8 | U74: =iferror(YEAR(O74),"") -> 2024 | V74: =if(C74="","", IFERROR(DAY(C74),"")) -> 20 | W74: =if(C74="","",IFERROR(MONTH(C74),"")) -> 8 | X74: =if(C74="","",iferror(YEAR(C74),"")) -> 2024
A75: 45524 | B75: 45497 | C75: =IF(E75="pago",A75,"") -> 45524 | D75: MERCADO LIVRE | E75: Pago | F75: Cartão de Crédito ELO | G75: BANCO DO BRASIL - 65204-0 | H75: CARTÃO ELO - ETIQUETA ENVIO, ENVELOPE | I75: 353.9 | K75: =if(E75="pago",(I75-J75),"") -> 353.9 | L75: Única | N75: EMBALAGENS/FITAS/GERAL | O75: =if(A75="","", TEXT(A75,"mm/yyyy")) -> 08/2024 | P75: =if(C75="","", TEXT(C75,"mm/yyyy")) -> 08/2024 | Q75: {=IFERROR(XLOOKUP(N75,'Classificação'!A:A,'Classificação'!B:B),"")} -> EMBALAGENS/FITAS/GERAL | R75: {=IFERROR(XLOOKUP(Q75,'Classificação'!B:B,'Classificação'!C:C),"")} -> CUSTOS VARIÁVEIS | S75: =iferror(DAY(A75),"") -> 20 | T75: =iferror(MONTH(O75),"") -> 8 | U75: =iferror(YEAR(O75),"") -> 2024 | V75: =if(C75="","", IFERROR(DAY(C75),"")) -> 20 | W75: =if(C75="","",IFERROR(MONTH(C75),"")) -> 8 | X75: =if(C75="","",iferror(YEAR(C75),"")) -> 2024
A76: 45524 | B76: 45497 | C76: =IF(E76="pago",A76,"") -> 45524 | D76: MERCADO LIVRE | E76: Pago | F76: Cartão de Crédito ELO | G76: BANCO DO BRASIL - 65204-0 | H76: CARTÃO ELO - SULFITE, ROLO, PAPELÃO | I76: 35.98 | K76: =if(E76="pago",(I76-J76),"") -> 35.98 | L76: Parcelado | M76: 45413 | N76: EMBALAGENS/FITAS/GERAL | O76: =if(A76="","", TEXT(A76,"mm/yyyy")) -> 08/2024 | P76: =if(C76="","", TEXT(C76,"mm/yyyy")) -> 08/2024 | Q76: {=IFERROR(XLOOKUP(N76,'Classificação'!A:A,'Classificação'!B:B),"")} -> EMBALAGENS/FITAS/GERAL | R76: {=IFERROR(XLOOKUP(Q76,'Classificação'!B:B,'Classificação'!C:C),"")} -> CUSTOS VARIÁVEIS | S76: =iferror(DAY(A76),"") -> 20 | T76: =iferror(MONTH(O76),"") -> 8 | U76: =iferror(YEAR(O76),"") -> 2024 | V76: =if(C76="","", IFERROR(DAY(C76),"")) -> 20 | W76: =if(C76="","",IFERROR(MONTH(C76),"")) -> 8 | X76: =if(C76="","",iferror(YEAR(C76),"")) -> 2024
A77: 45524 | C77: =IF(E77="pago",A77,"") -> 45524 | D77: MERCADO LIVRE | E77: Pago | F77: Pix | G77: MERCADO PAGO SINCE - 9511092439-1 | H77: COMPRA INTERFONE - REEMBOLSO LARISSA | I77: 67.49 | K77: =if(E77="pago",(I77-J77),"") -> 67.49 | L77: Parcelado | M77: 45572 | N77: COMPRA DE BENS/EQUIPAMENTOS | O77: =if(A77="","", TEXT(A77,"mm/yyyy")) -> 08/2024 | P77: =if(C77="","", TEXT(C77,"mm/yyyy")) -> 08/2024 | Q77: {=IFERROR(XLOOKUP(N77,'Classificação'!A:A,'Classificação'!B:B),"")} -> DESPESAS NÃO OPERACIONAIS | R77: {=IFERROR(XLOOKUP(Q77,'Classificação'!B:B,'Classificação'!C:C),"")} -> RESULTADO NÃO OPERACIONAL (+/-) | S77: =iferror(DAY(A77),"") -> 20 | T77: =iferror(MONTH(O77),"") -> 8 | U77: =iferror(YEAR(O77),"") -> 2024 | V77: =if(C77="","", IFERROR(DAY(C77),"")) -> 20 | W77: =if(C77="","",IFERROR(MONTH(C77),"")) -> 8 | X77: =if(C77="","",iferror(YEAR(C77),"")) -> 2024
A78: 45524 | B78: 45861 | C78: =IF(E78="pago",A78,"") -> 45524 | D78: MERCADO LIVRE | E78: Pago | F78: Cartão de Crédito ELO | G78: BANCO DO BRASIL - 65204-0 | H78: CARTÃO ELO - ETIQUETA FULL AMAZON | I78: 20.85 | K78: =if(E78="pago",(I78-J78),"") -> 20.85 | L78: Única | N78: EMBALAGENS/FITAS/GERAL | O78: =if(A78="","", TEXT(A78,"mm/yyyy")) -> 08/2024 | P78: =if(C78="","", TEXT(C78,"mm/yyyy")) -> 08/2024 | Q78: {=IFERROR(XLOOKUP(N78,'Classificação'!A:A,'Classificação'!B:B),"")} -> EMBALAGENS/FITAS/GERAL | R78: {=IFERROR(XLOOKUP(Q78,'Classificação'!B:B,'Classificação'!C:C),"")} -> CUSTOS VARIÁVEIS | S78: =iferror(DAY(A78),"") -> 20 | T78: =iferror(MONTH(O78),"") -> 8 | U78: =iferror(YEAR(O78),"") -> 2024 | V78: =if(C78="","", IFERROR(DAY(C78),"")) -> 20 | W78: =if(C78="","",IFERROR(MONTH(C78),"")) -> 8 | X78: =if(C78="","",iferror(YEAR(C78),"")) -> 2024
A79: 45524 | C79: =IF(E79="pago",A79,"") -> 45524 | D79: MERCADO LIVRE | E79: Pago | F79: Pix | G79: MERCADO PAGO SINCE - 9511092439-1 | H79: ENVELOPES, CABO E FITAS - REEMBOLSO LARISSA | I79: 363.83 | K79: =if(E79="pago",(I79-J79),"") -> 363.83 | L79: Única | N79: EMBALAGENS/FITAS/GERAL | O79: =if(A79="","", TEXT(A79,"mm/yyyy")) -> 08/2024 | P79: =if(C79="","", TEXT(C79,"mm/yyyy")) -> 08/2024 | Q79: {=IFERROR(XLOOKUP(N79,'Classificação'!A:A,'Classificação'!B:B),"")} -> EMBALAGENS/FITAS/GERAL | R79: {=IFERROR(XLOOKUP(Q79,'Classificação'!B:B,'Classificação'!C:C),"")} -> CUSTOS VARIÁVEIS | S79: =iferror(DAY(A79),"") -> 20 | T79: =iferror(MONTH(O79),"") -> 8 | U79: =iferror(YEAR(O79),"") -> 2024 | V79: =if(C79="","", IFERROR(DAY(C79),"")) -> 20 | W79: =if(C79="","",IFERROR(MONTH(C79),"")) -> 8 | X79: =if(C79="","",iferror(YEAR(C79),"")) -> 2024
A80: 45524 | C80: =IF(E80="pago",A80,"") -> 45524 | D80: MERCADO LIVRE | E80: Pago | F80: Pix | G80: MERCADO PAGO SINCE - 9511092439-1 | H80: ENVELOPES, CABO E FITAS - REEMBOLSO LARISSA | I80: 65 | K80: =if(E80="pago",(I80-J80),"") -> 65 | L80: Parcelado | M80: 45323 | N80: EMBALAGENS/FITAS/GERAL | O80: =if(A80="","", TEXT(A80,"mm/yyyy")) -> 08/2024 | P80: =if(C80="","", TEXT(C80,"mm/yyyy")) -> 08/2024 | Q80: {=IFERROR(XLOOKUP(N80,'Classificação'!A:A,'Classificação'!B:B),"")} -> EMBALAGENS/FITAS/GERAL | R80: {=IFERROR(XLOOKUP(Q80,'Classificação'!B:B,'Classificação'!C:C),"")} -> CUSTOS VARIÁVEIS | S80: =iferror(DAY(A80),"") -> 20 | T80: =iferror(MONTH(O80),"") -> 8 | U80: =iferror(YEAR(O80),"") -> 2024 | V80: =if(C80="","", IFERROR(DAY(C80),"")) -> 20 | W80: =if(C80="","",IFERROR(MONTH(C80),"")) -> 8 | X80: =if(C80="","",iferror(YEAR(C80),"")) -> 2024
A81: 45524 | B81: 45508 | C81: =IF(E81="pago",A81,"") -> 45524 | D81: MICROSOFT SÃO PAULO | E81: Pago | F81: Cartão de Crédito ELO | G81: BANCO DO BRASIL - 65204-0 | H81: SISTEMA - PACOTE OFFICE | I81: 45 | K81: =if(E81="pago",(I81-J81),"") -> 45 | L81: Única | N81: DESPESA COM SISTEMAS | O81: =if(A81="","", TEXT(A81,"mm/yyyy")) -> 08/2024 | P81: =if(C81="","", TEXT(C81,"mm/yyyy")) -> 08/2024 | Q81: {=IFERROR(XLOOKUP(N81,'Classificação'!A:A,'Classificação'!B:B),"")} -> DESPESAS ADMINISTRATIVAS | R81: {=IFERROR(XLOOKUP(Q81,'Classificação'!B:B,'Classificação'!C:C),"")} -> DESPESAS FIXAS (-) | S81: =iferror(DAY(A81),"") -> 20 | T81: =iferror(MONTH(O81),"") -> 8 | U81: =iferror(YEAR(O81),"") -> 2024 | V81: =if(C81="","", IFERROR(DAY(C81),"")) -> 20 | W81: =if(C81="","",IFERROR(MONTH(C81),"")) -> 8 | X81: =if(C81="","",iferror(YEAR(C81),"")) -> 2024
A82: 45524 | C82: =IF(E82="pago",A82,"") -> 45524 | D82: MR VARIEDADES | E82: Pago | F82: Cartão de Crédito ELO | G82: BANCO DO BRASIL - 65204-0 | H82: CARTÃO ELO - PEÇAS DECORATIVAS SALA MEZANINO | I82: 96.45 | K82: =if(E82="pago",(I82-J82),"") -> 96.45 | L82: Parcelado | M82: 45444 | N82: COMPRA DE BENS/EQUIPAMENTOS | O82: =if(A82="","", TEXT(A82,"mm/yyyy")) -> 08/2024 | P82: =if(C82="","", TEXT(C82,"mm/yyyy")) -> 08/2024 | Q82: {=IFERROR(XLOOKUP(N82,'Classificação'!A:A,'Classificação'!B:B),"")} -> DESPESAS NÃO OPERACIONAIS | R82: {=IFERROR(XLOOKUP(Q82,'Classificação'!B:B,'Classificação'!C:C),"")} -> RESULTADO NÃO OPERACIONAL (+/-) | S82: =iferror(DAY(A82),"") -> 20 | T82: =iferror(MONTH(O82),"") -> 8 | U82: =iferror(YEAR(O82),"") -> 2024 | V82: =if(C82="","", IFERROR(DAY(C82),"")) -> 20 | W82: =if(C82="","",IFERROR(MONTH(C82),"")) -> 8 | X82: =if(C82="","",iferror(YEAR(C82),"")) -> 2024
A83: 45524 | B83: 45486 | C83: =IF(E83="pago",A83,"") -> 45524 | D83: MR VARIEDADES | E83: Pago | F83: Cartão de Crédito ELO | G83: BANCO DO BRASIL - 65204-0 | H83: CARTÃO ELO - PEÇAS DECORATIVAS SALA MEZANINO | I83: 144.15 | K83: =if(E83="pago",(I83-J83),"") -> 144.15 | L83: Parcelado | M83: 45627 | N83: COMPRA DE BENS/EQUIPAMENTOS | O83: =if(A83="","", TEXT(A83,"mm/yyyy")) -> 08/2024 | P83: =if(C83="","", TEXT(C83,"mm/yyyy")) -> 08/2024 | Q83: {=IFERROR(XLOOKUP(N83,'Classificação'!A:A,'Classificação'!B:B),"")} -> DESPESAS NÃO OPERACIONAIS | R83: {=IFERROR(XLOOKUP(Q83,'Classificação'!B:B,'Classificação'!C:C),"")} -> RESULTADO NÃO OPERACIONAL (+/-) | S83: =iferror(DAY(A83),"") -> 20 | T83: =iferror(MONTH(O83),"") -> 8 | U83: =iferror(YEAR(O83),"") -> 2024 | V83: =if(C83="","", IFERROR(DAY(C83),"")) -> 20 | W83: =if(C83="","",IFERROR(MONTH(C83),"")) -> 8 | X83: =if(C83="","",iferror(YEAR(C83),"")) -> 2024
A84: 45524 | B84: 45484 | C84: =IF(E84="pago",A84,"") -> 45524 | D84: P AMP A PANIFICADORA INDAIATUBA | E84: Pago | F84: Cartão de Crédito ELO | G84: BANCO DO BRASIL - 65204-0 | H84: Cartão Elo - Café da manhã | I84: 35.99 | K84: =if(E84="pago",(I84-J84),"") -> 35.99 | L84: Única | N84: COMPRA DE MERCADO/PADARIA | O84: =if(A84="","", TEXT(A84,"mm/yyyy")) -> 08/2024 | P84: =if(C84="","", TEXT(C84,"mm/yyyy")) -> 08/2024 | Q84: {=IFERROR(XLOOKUP(N84,'Classificação'!A:A,'Classificação'!B:B),"")} -> DESPESAS DIVERSAS | R84: {=IFERROR(XLOOKUP(Q84,'Classificação'!B:B,'Classificação'!C:C),"")} -> DESPESAS FIXAS (-) | S84: =iferror(DAY(A84),"") -> 20 | T84: =iferror(MONTH(O84),"") -> 8 | U84: =iferror(YEAR(O84),"") -> 2024 | V84: =if(C84="","", IFERROR(DAY(C84),"")) -> 20 | W84: =if(C84="","",IFERROR(MONTH(C84),"")) -> 8 | X84: =if(C84="","",iferror(YEAR(C84),"")) -> 2024
A85: 45524 | C85: =IF(E85="pago",A85,"") -> 45524 | D85: PANELA VELHA RESTAURANTE | E85: Pago | F85: Cartão de Crédito VISA | G85: BANCO DO BRASIL - 65204-0 | H85: CARTÃO VISA - ALMOÇO FREELANCER VITOR | I85: 31 | K85: =if(E85="pago",(I85-J85),"") -> 31 | L85: Única | N85: ALIMENTAÇÃO FUNCIONARIOS | O85: =if(A85="","", TEXT(A85,"mm/yyyy")) -> 08/2024 | P85: =if(C85="","", TEXT(C85,"mm/yyyy")) -> 08/2024 | Q85: {=IFERROR(XLOOKUP(N85,'Classificação'!A:A,'Classificação'!B:B),"")} -> DESPESAS COM PESSOAL | R85: {=IFERROR(XLOOKUP(Q85,'Classificação'!B:B,'Classificação'!C:C),"")} -> DESPESAS FIXAS (-) | S85: =iferror(DAY(A85),"") -> 20 | T85: =iferror(MONTH(O85),"") -> 8 | U85: =iferror(YEAR(O85),"") -> 2024 | V85: =if(C85="","", IFERROR(DAY(C85),"")) -> 20 | W85: =if(C85="","",IFERROR(MONTH(C85),"")) -> 8 | X85: =if(C85="","",iferror(YEAR(C85),"")) -> 2024
A86: 45524 | C86: =IF(E86="pago",A86,"") -> 45524 | D86: PANELA VELHA RESTAURANTE | E86: Pago | F86: Cartão de Crédito VISA | G86: BANCO DO BRASIL - 65204-0 | H86: CARTÃO VISA - ALMOÇO FREELANCER VITOR | I86: 31 | K86: =if(E86="pago",(I86-J86),"") -> 31 | L86: Única | N86: ALIMENTAÇÃO FUNCIONARIOS | O86: =if(A86="","", TEXT(A86,"mm/yyyy")) -> 08/2024 | P86: =if(C86="","", TEXT(C86,"mm/yyyy")) -> 08/2024 | Q86: {=IFERROR(XLOOKUP(N86,'Classificação'!A:A,'Classificação'!B:B),"")} -> DESPESAS COM PESSOAL | R86: {=IFERROR(XLOOKUP(Q86,'Classificação'!B:B,'Classificação'!C:C),"")} -> DESPESAS FIXAS (-) | S86: =iferror(DAY(A86),"") -> 20 | T86: =iferror(MONTH(O86),"") -> 8 | U86: =iferror(YEAR(O86),"") -> 2024 | V86: =if(C86="","", IFERROR(DAY(C86),"")) -> 20 | W86: =if(C86="","",IFERROR(MONTH(C86),"")) -> 8 | X86: =if(C86="","",iferror(YEAR(C86),"")) -> 2024
A87: 45524 | C87: =IF(E87="pago",A87,"") -> 45524 | D87: PANELA VELHA RESTAURANTE | E87: Pago | F87: Cartão de Crédito VISA | G87: BANCO DO BRASIL - 65204-0 | H87: CARTÃO VISA - ALMOÇO FREELANCER VITOR | I87: 31 | K87: =if(E87="pago",(I87-J87),"") -> 31 | L87: Única | N87: ALIMENTAÇÃO FUNCIONARIOS | O87: =if(A87="","", TEXT(A87,"mm/yyyy")) -> 08/2024 | P87: =if(C87="","", TEXT(C87,"mm/yyyy")) -> 08/2024 | Q87: {=IFERROR(XLOOKUP(N87,'Classificação'!A:A,'Classificação'!B:B),"")} -> DESPESAS COM PESSOAL | R87: {=IFERROR(XLOOKUP(Q87,'Classificação'!B:B,'Classificação'!C:C),"")} -> DESPESAS FIXAS (-) | S87: =iferror(DAY(A87),"") -> 20 | T87: =iferror(MONTH(O87),"") -> 8 | U87: =iferror(YEAR(O87),"") -> 2024 | V87: =if(C87="","", IFERROR(DAY(C87),"")) -> 20 | W87: =if(C87="","",IFERROR(MONTH(C87),"")) -> 8 | X87: =if(C87="","",iferror(YEAR(C87),"")) -> 2024
A88: 45524 | C88: =IF(E88="pago",A88,"") -> 45524 | D88: PANELA VELHA RESTAURANTE | E88: Pago | F88: Cartão de Crédito VISA | G88: BANCO DO BRASIL - 65204-0 | H88: CARTÃO VISA - ALMOÇO FREELANCER VITOR | I88: 25 | K88: =if(E88="pago",(I88-J88),"") -> 25 | L88: Única | N88: ALIMENTAÇÃO FUNCIONARIOS | O88: =if(A88="","", TEXT(A88,"mm/yyyy")) -> 08/2024 | P88: =if(C88="","", TEXT(C88,"mm/yyyy")) -> 08/2024 | Q88: {=IFERROR(XLOOKUP(N88,'Classificação'!A:A,'Classificação'!B:B),"")} -> DESPESAS COM PESSOAL | R88: {=IFERROR(XLOOKUP(Q88,'Classificação'!B:B,'Classificação'!C:C),"")} -> DESPESAS FIXAS (-) | S88: =iferror(DAY(A88),"") -> 20 | T88: =iferror(MONTH(O88),"") -> 8 | U88: =iferror(YEAR(O88),"") -> 2024 | V88: =if(C88="","", IFERROR(DAY(C88),"")) -> 20 | W88: =if(C88="","",IFERROR(MONTH(C88),"")) -> 8 | X88: =if(C88="","",iferror(YEAR(C88),"")) -> 2024
A89: 45524 | C89: =IF(E89="pago",A89,"") -> 45524 | D89: PANELA VELHA RESTAURANTE | E89: Pago | F89: Cartão de Crédito VISA | G89: BANCO DO BRASIL - 65204-0 | H89: CARTÃO VISA - ALMOÇO FREELANCER VITOR | I89: 25 | K89: =if(E89="pago",(I89-J89),"") -> 25 | L89: Única | N89: ALIMENTAÇÃO FUNCIONARIOS | O89: =if(A89="","", TEXT(A89,"mm/yyyy")) -> 08/2024 | P89: =if(C89="","", TEXT(C89,"mm/yyyy")) -> 08/2024 | Q89: {=IFERROR(XLOOKUP(N89,'Classificação'!A:A,'Classificação'!B:B),"")} -> DESPESAS COM PESSOAL | R89: {=IFERROR(XLOOKUP(Q89,'Classificação'!B:B,'Classificação'!C:C),"")} -> DESPESAS FIXAS (-) | S89: =iferror(DAY(A89),"") -> 20 | T89: =iferror(MONTH(O89),"") -> 8 | U89: =iferror(YEAR(O89),"") -> 2024 | V89: =if(C89="","", IFERROR(DAY(C89),"")) -> 20 | W89: =if(C89="","",IFERROR(MONTH(C89),"")) -> 8 | X89: =if(C89="","",iferror(YEAR(C89),"")) -> 2024
A90: 45524 | B90: 45488 | C90: =IF(E90="pago",A90,"") -> 45524 | D90: PANIFICADORA E CONFEIT INDAIATUBA | E90: Pago | F90: Cartão de Crédito ELO | G90: BANCO DO BRASIL - 65204-0 | H90: Cartão Elo - Café da manhã | I90: 6.66 | K90: =if(E90="pago",(I90-J90),"") -> 6.66 | L90: Única | N90: COMPRA DE MERCADO/PADARIA | O90: =if(A90="","", TEXT(A90,"mm/yyyy")) -> 08/2024 | P90: =if(C90="","", TEXT(C90,"mm/yyyy")) -> 08/2024 | Q90: {=IFERROR(XLOOKUP(N90,'Classificação'!A:A,'Classificação'!B:B),"")} -> DESPESAS DIVERSAS | R90: {=IFERROR(XLOOKUP(Q90,'Classificação'!B:B,'Classificação'!C:C),"")} -> DESPESAS FIXAS (-) | S90: =iferror(DAY(A90),"") -> 20 | T90: =iferror(MONTH(O90),"") -> 8 | U90: =iferror(YEAR(O90),"") -> 2024 | V90: =if(C90="","", IFERROR(DAY(C90),"")) -> 20 | W90: =if(C90="","",IFERROR(MONTH(C90),"")) -> 8 | X90: =if(C90="","",iferror(YEAR(C90),"")) -> 2024
A91: 45524 | C91: =IF(E91="pago",A91,"") -> 45524 | D91: SAAE - COMPANHIA DE ÁGUA E ESGOTO | E91: Pago | F91: Boleto | G91: BANCO DO BRASIL - 65204-0 | I91: 107.64 | K91: =if(E91="pago",(I91-J91),"") -> 107.64 | L91: Mensal | N91: ÁGUA E ESGOTO | O91: =if(A91="","", TEXT(A91,"mm/yyyy")) -> 08/2024 | P91: =if(C91="","", TEXT(C91,"mm/yyyy")) -> 08/2024 | Q91: {=IFERROR(XLOOKUP(N91,'Classificação'!A:A,'Classificação'!B:B),"")} -> DESPESAS COM OCUPAÇÃO | R91: {=IFERROR(XLOOKUP(Q91,'Classificação'!B:B,'Classificação'!C:C),"")} -> DESPESAS FIXAS (-) | S91: =iferror(DAY(A91),"") -> 20 | T91: =iferror(MONTH(O91),"") -> 8 | U91: =iferror(YEAR(O91),"") -> 2024 | V91: =if(C91="","", IFERROR(DAY(C91),"")) -> 20 | W91: =if(C91="","",IFERROR(MONTH(C91),"")) -> 8 | X91: =if(C91="","",iferror(YEAR(C91),"")) -> 2024
A92: 45524 | B92: 45421 | C92: =IF(E92="pago",A92,"") -> 45524 | D92: SOL ABDELNOR | E92: Pago | F92: Cartão de Crédito ELO | G92: BANCO DO BRASIL - 65204-0 | H92: Cartão Elo - Revisão Veicular | I92: 298.9 | K92: =if(E92="pago",(I92-J92),"") -> 298.9 | L92: Parcelado | M92: 45568 | N92: MANUTENÇÃO DE VEÍCULOS | O92: =if(A92="","", TEXT(A92,"mm/yyyy")) -> 08/2024 | P92: =if(C92="","", TEXT(C92,"mm/yyyy")) -> 08/2024 | Q92: {=IFERROR(XLOOKUP(N92,'Classificação'!A:A,'Classificação'!B:B),"")} -> DESPESAS COM VEICULOS | R92: {=IFERROR(XLOOKUP(Q92,'Classificação'!B:B,'Classificação'!C:C),"")} -> DESPESAS FIXAS (-) | S92: =iferror(DAY(A92),"") -> 20 | T92: =iferror(MONTH(O92),"") -> 8 | U92: =iferror(YEAR(O92),"") -> 2024 | V92: =if(C92="","", IFERROR(DAY(C92),"")) -> 20 | W92: =if(C92="","",IFERROR(MONTH(C92),"")) -> 8 | X92: =if(C92="","",iferror(YEAR(C92),"")) -> 2024
A93: 45524 | C93: =IF(E93="pago",A93,"") -> 45524 | D93: Sumerbol Supermercados Ltda | E93: Pago | F93: Cartão de Crédito VISA | G93: BANCO DO BRASIL - 65204-0 | H93: CARTÃO VISA - COMPRA DE PAPEL HIGIENICO E DETERGENTE | I93: 22.07 | K93: =if(E93="pago",(I93-J93),"") -> 22.07 | L93: Única | N93: COMPRA DE MERCADO/PADARIA | O93: =if(A93="","", TEXT(A93,"mm/yyyy")) -> 08/2024 | P93: =if(C93="","", TEXT(C93,"mm/yyyy")) -> 08/2024 | Q93: {=IFERROR(XLOOKUP(N93,'Classificação'!A:A,'Classificação'!B:B),"")} -> DESPESAS DIVERSAS | R93: {=IFERROR(XLOOKUP(Q93,'Classificação'!B:B,'Classificação'!C:C),"")} -> DESPESAS FIXAS (-) | S93: =iferror(DAY(A93),"") -> 20 | T93: =iferror(MONTH(O93),"") -> 8 | U93: =iferror(YEAR(O93),"") -> 2024 | V93: =if(C93="","", IFERROR(DAY(C93),"")) -> 20 | W93: =if(C93="","",IFERROR(MONTH(C93),"")) -> 8 | X93: =if(C93="","",iferror(YEAR(C93),"")) -> 2024
A94: 45524 | C94: =IF(E94="pago",A94,"") -> 45524 | D94: TOKIO MARINE SEGURADORA S.A. - SEGURADORA | E94: Pago | F94: Cartão de Crédito ELO | G94: BANCO DO BRASIL - 65204-0 | I94: 149.25 | K94: =if(E94="pago",(I94-J94),"") -> 149.25 | L94: Parcelado | M94: 45416 | N94: SEGURO PATRIMONIO | O94: =if(A94="","", TEXT(A94,"mm/yyyy")) -> 08/2024 | P94: =if(C94="","", TEXT(C94,"mm/yyyy")) -> 08/2024 | Q94: {=IFERROR(XLOOKUP(N94,'Classificação'!A:A,'Classificação'!B:B),"")} -> DESPESAS COM OCUPAÇÃO | R94: {=IFERROR(XLOOKUP(Q94,'Classificação'!B:B,'Classificação'!C:C),"")} -> DESPESAS FIXAS (-) | S94: =iferror(DAY(A94),"") -> 20 | T94: =iferror(MONTH(O94),"") -> 8 | U94: =iferror(YEAR(O94),"") -> 2024 | V94: =if(C94="","", IFERROR(DAY(C94),"")) -> 20 | W94: =if(C94="","",IFERROR(MONTH(C94),"")) -> 8 | X94: =if(C94="","",iferror(YEAR(C94),"")) -> 2024
A95: 45524 | B95: 45484 | C95: =IF(E95="pago",A95,"") -> 45524 | D95: Top Flex Posto de Gasolina | E95: Pago | F95: Cartão de Crédito ELO | G95: BANCO DO BRASIL - 65204-0 | H95: Cartão Elo - COMBUSTIVEL | I95: 150 | K95: =if(E95="pago",(I95-J95),"") -> 150 | L95: Única | N95: COMBUSTIVEIS | O95: =if(A95="","", TEXT(A95,"mm/yyyy")) -> 08/2024 | P95: =if(C95="","", TEXT(C95,"mm/yyyy")) -> 08/2024 | Q95: {=IFERROR(XLOOKUP(N95,'Classificação'!A:A,'Classificação'!B:B),"")} -> DESPESAS COM VEICULOS | R95: {=IFERROR(XLOOKUP(Q95,'Classificação'!B:B,'Classificação'!C:C),"")} -> DESPESAS FIXAS (-) | S95: =iferror(DAY(A95),"") -> 20 | T95: =iferror(MONTH(O95),"") -> 8 | U95: =iferror(YEAR(O95),"") -> 2024 | V95: =if(C95="","", IFERROR(DAY(C95),"")) -> 20 | W95: =if(C95="","",IFERROR(MONTH(C95),"")) -> 8 | X95: =if(C95="","",iferror(YEAR(C95),"")) -> 2024
A96: 45524 | B96: 45505 | C96: =IF(E96="pago",A96,"") -> 45524 | D96: Top Flex Posto de Gasolina | E96: Pago | F96: Cartão de Crédito ELO | G96: BANCO DO BRASIL - 65204-0 | H96: Cartão Elo - COMBUSTIVEL | I96: 100 | K96: =if(E96="pago",(I96-J96),"") -> 100 | L96: Única | N96: COMBUSTIVEIS | O96: =if(A96="","", TEXT(A96,"mm/yyyy")) -> 08/2024 | P96: =if(C96="","", TEXT(C96,"mm/yyyy")) -> 08/2024 | Q96: {=IFERROR(XLOOKUP(N96,'Classificação'!A:A,'Classificação'!B:B),"")} -> DESPESAS COM VEICULOS | R96: {=IFERROR(XLOOKUP(Q96,'Classificação'!B:B,'Classificação'!C:C),"")} -> DESPESAS FIXAS (-) | S96: =iferror(DAY(A96),"") -> 20 | T96: =iferror(MONTH(O96),"") -> 8 | U96: =iferror(YEAR(O96),"") -> 2024 | V96: =if(C96="","", IFERROR(DAY(C96),"")) -> 20 | W96: =if(C96="","",IFERROR(MONTH(C96),"")) -> 8 | X96: =if(C96="","",iferror(YEAR(C96),"")) -> 2024
A97: 45524 | B97: 45483 | C97: =IF(E97="pago",A97,"") -> 45524 | D97: UBER | E97: Pago | F97: Cartão de Crédito ELO | G97: BANCO DO BRASIL - 65204-0 | H97: Cartão Elo - | I97: 17.94 | K97: =if(E97="pago",(I97-J97),"") -> 17.94 | L97: Única | N97: TRANSPORTE URBANO (TÁXI, UBER) | O97: =if(A97="","", TEXT(A97,"mm/yyyy")) -> 08/2024 | P97: =if(C97="","", TEXT(C97,"mm/yyyy")) -> 08/2024 | Q97: {=IFERROR(XLOOKUP(N97,'Classificação'!A:A,'Classificação'!B:B),"")} -> DESPESAS ADMINISTRATIVAS | R97: {=IFERROR(XLOOKUP(Q97,'Classificação'!B:B,'Classificação'!C:C),"")} -> DESPESAS FIXAS (-) | S97: =iferror(DAY(A97),"") -> 20 | T97: =iferror(MONTH(O97),"") -> 8 | U97: =iferror(YEAR(O97),"") -> 2024 | V97: =if(C97="","", IFERROR(DAY(C97),"")) -> 20 | W97: =if(C97="","",IFERROR(MONTH(C97),"")) -> 8 | X97: =if(C97="","",iferror(YEAR(C97),"")) -> 2024
A98: 45524 | B98: 45489 | C98: =IF(E98="pago",A98,"") -> 45524 | D98: UBER | E98: Pago | F98: Cartão de Crédito ELO | G98: BANCO DO BRASIL - 65204-0 | H98: Cartão Elo - | I98: 8.92 | K98: =if(E98="pago",(I98-J98),"") -> 8.92 | L98: Única | N98: TRANSPORTE URBANO (TÁXI, UBER) | O98: =if(A98="","", TEXT(A98,"mm/yyyy")) -> 08/2024 | P98: =if(C98="","", TEXT(C98,"mm/yyyy")) -> 08/2024 | Q98: {=IFERROR(XLOOKUP(N98,'Classificação'!A:A,'Classificação'!B:B),"")} -> DESPESAS ADMINISTRATIVAS | R98: {=IFERROR(XLOOKUP(Q98,'Classificação'!B:B,'Classificação'!C:C),"")} -> DESPESAS FIXAS (-) | S98: =iferror(DAY(A98),"") -> 20 | T98: =iferror(MONTH(O98),"") -> 8 | U98: =iferror(YEAR(O98),"") -> 2024 | V98: =if(C98="","", IFERROR(DAY(C98),"")) -> 20 | W98: =if(C98="","",IFERROR(MONTH(C98),"")) -> 8 | X98: =if(C98="","",iferror(YEAR(C98),"")) -> 2024
A99: 45524 | B99: 45489 | C99: =IF(E99="pago",A99,"") -> 45524 | D99: UBER | E99: Pago | F99: Cartão de Crédito ELO | G99: BANCO DO BRASIL - 65204-0 | H99: Cartão Elo - | I99: 9.95 | K99: =if(E99="pago",(I99-J99),"") -> 9.95 | L99: Única | N99: TRANSPORTE URBANO (TÁXI, UBER) | O99: =if(A99="","", TEXT(A99,"mm/yyyy")) -> 08/2024 | P99: =if(C99="","", TEXT(C99,"mm/yyyy")) -> 08/2024 | Q99: {=IFERROR(XLOOKUP(N99,'Classificação'!A:A,'Classificação'!B:B),"")} -> DESPESAS ADMINISTRATIVAS | R99: {=IFERROR(XLOOKUP(Q99,'Classificação'!B:B,'Classificação'!C:C),"")} -> DESPESAS FIXAS (-) | S99: =iferror(DAY(A99),"") -> 20 | T99: =iferror(MONTH(O99),"") -> 8 | U99: =iferror(YEAR(O99),"") -> 2024 | V99: =if(C99="","", IFERROR(DAY(C99),"")) -> 20 | W99: =if(C99="","",IFERROR(MONTH(C99),"")) -> 8 | X99: =if(C99="","",iferror(YEAR(C99),"")) -> 2024
A100: 45524 | B100: 45461 | C100: =IF(E100="pago",A100,"") -> 45524 | D100: WA ELETRECIST | E100: Pago | F100: Cartão de Crédito ELO | G100: BANCO DO BRASIL - 65204-0 | H100: CARTÃO ELO - JARDIM VERTICAL | I100: 300 | K100: =if(E100="pago",(I100-J100),"") -> 300 | L100: Parcelado | M100: 45414 | N100: COMPRA DE BENS/EQUIPAMENTOS | O100: =if(A100="","", TEXT(A100,"mm/yyyy")) -> 08/2024 | P100: =if(C100="","", TEXT(C100,"mm/yyyy")) -> 08/2024 | Q100: {=IFERROR(XLOOKUP(N100,'Classificação'!A:A,'Classificação'!B:B),"")} -> DESPESAS NÃO OPERACIONAIS | R100: {=IFERROR(XLOOKUP(Q100,'Classificação'!B:B,'Classificação'!C:C),"")} -> RESULTADO NÃO OPERACIONAL (+/-) | S100: =iferror(DAY(A100),"") -> 20 | T100: =iferror(MONTH(O100),"") -> 8 | U100: =iferror(YEAR(O100),"") -> 2024 | V100: =if(C100="","", IFERROR(DAY(C100),"")) -> 20 | W100: =if(C100="","",IFERROR(MONTH(C100),"")) -> 8 | X100: =if(C100="","",iferror(YEAR(C100),"")) -> 2024
...

Sheet Lançamentos de receitas
A1: Vencimento | B1: Fornecedor | C1: Banco/conta | D1: Descrição | E1: Valor recebido | F1: SITUAÇÃO | G1: PREVISÃO DO RECEBIMENTO | H1: DIA DO RECEBIMENTO | I1: MES DO RECEBIMENTO | J1: ANO DO RECEBIMENTO | K1: MES ANO
A2: 45505 | B2: MERCADO LIVRE LIVRE FARMEL | C2: BANCO DO BRASIL - 65204-0 | D2: VENDAS MERCADO LIVRE FARMEL | E2: 4377.26 | F2: TRANSFERÊNCIA | G2: 45505 | H2: =if(A2="","", iferror(DAY(A2),"")) -> 1 | I2: =if(A2="","", IFERROR(MONTH(A2),"")) -> 8 | J2: =if(A2="","", IFERROR(year(A2),"")) -> 2024 | K2: =TEXT(A2,"mm/yyyy") -> 08/2024
A3: 45505 | B3: MERCADO LIVRE LIVRE FARMEL | C3: BANCO DO BRASIL - 65204-0 | D3: VENDAS MERCADO LIVRE FARMEL | E3: 1629.46 | F3: TRANSFERÊNCIA | G3: 45505 | H3: =if(A3="","", iferror(DAY(A3),"")) -> 1 | I3: =if(A3="","", IFERROR(MONTH(A3),"")) -> 8 | J3: =if(A3="","", IFERROR(year(A3),"")) -> 2024 | K3: =TEXT(A3,"mm/yyyy") -> 08/2024
A4: 45505 | B4: MERCADO LIVRE SINCE | C4: MERCADO PAGO SINCE - 9511092439-1 | D4: VENDAS MERCADO LIVRE SINCE | E4: 886.86 | F4: PAGO | G4: 45505 | H4: =if(A4="","", iferror(DAY(A4),"")) -> 1 | I4: =if(A4="","", IFERROR(MONTH(A4),"")) -> 8 | J4: =if(A4="","", IFERROR(year(A4),"")) -> 2024 | K4: =TEXT(A4,"mm/yyyy") -> 08/2024
A5: 45505 | B5: AMERICANAS | C5: BANCO DO BRASIL - 65204-0 | D5: VENDAS AMERICANAS | E5: 122.98 | F5: TRANSFERÊNCIA | G5: 45505 | H5: =if(A5="","", iferror(DAY(A5),"")) -> 1 | I5: =if(A5="","", IFERROR(MONTH(A5),"")) -> 8 | J5: =if(A5="","", IFERROR(year(A5),"")) -> 2024 | K5: =TEXT(A5,"mm/yyyy") -> 08/2024
A6: 45505 | B6: AMERICANAS | C6: BANCO DO BRASIL - 65204-0 | D6: VENDAS AMERICANAS | E6: 588.82 | F6: TRANSFERÊNCIA | G6: 45505 | H6: =if(A6="","", iferror(DAY(A6),"")) -> 1 | I6: =if(A6="","", IFERROR(MONTH(A6),"")) -> 8 | J6: =if(A6="","", IFERROR(year(A6),"")) -> 2024 | K6: =TEXT(A6,"mm/yyyy") -> 08/2024
A7: 45506 | B7: MERCADO LIVRE LIVRE FARMEL | C7: BANCO DO BRASIL - 65204-0 | D7: VENDAS MERCADO LIVRE FARMEL | E7: 2499.56 | F7: TRANSFERÊNCIA | G7: 45506 | H7: =if(A7="","", iferror(DAY(A7),"")) -> 2 | I7: =if(A7="","", IFERROR(MONTH(A7),"")) -> 8 | J7: =if(A7="","", IFERROR(year(A7),"")) -> 2024 | K7: =TEXT(A7,"mm/yyyy") -> 08/2024
A8: 45506 | B8: MERCADO LIVRE SINCE | C8: MERCADO PAGO SINCE - 9511092439-1 | D8: VENDAS MERCADO LIVRE SINCE | E8: 179.63 | F8: PAGO | G8: 45506 | H8: =if(A8="","", iferror(DAY(A8),"")) -> 2 | I8: =if(A8="","", IFERROR(MONTH(A8),"")) -> 8 | J8: =if(A8="","", IFERROR(year(A8),"")) -> 2024 | K8: =TEXT(A8,"mm/yyyy") -> 08/2024
A9: 45507 | B9: MERCADO LIVRE LIVRE FARMEL | C9: BANCO DO BRASIL - 65204-0 | D9: VENDAS MERCADO LIVRE FARMEL | E9: 3247.92 | F9: TRANSFERÊNCIA | G9: 45507 | H9: =if(A9="","", iferror(DAY(A9),"")) -> 3 | I9: =if(A9="","", IFERROR(MONTH(A9),"")) -> 8 | J9: =if(A9="","", IFERROR(year(A9),"")) -> 2024 | K9: =TEXT(A9,"mm/yyyy") -> 08/2024
A10: 45507 | B10: MERCADO LIVRE SINCE | C10: MERCADO PAGO SINCE - 9511092439-1 | D10: VENDAS MERCADO LIVRE SINCE | E10: 1205.61 | F10: PAGO | G10: 45507 | H10: =if(A10="","", iferror(DAY(A10),"")) -> 3 | I10: =if(A10="","", IFERROR(MONTH(A10),"")) -> 8 | J10: =if(A10="","", IFERROR(year(A10),"")) -> 2024 | K10: =TEXT(A10,"mm/yyyy") -> 08/2024
A11: 45508 | B11: MERCADO LIVRE LIVRE FARMEL | C11: BANCO DO BRASIL - 65204-0 | D11: VENDAS MERCADO LIVRE FARMEL | E11: 1407.97 | F11: TRANSFERÊNCIA | G11: 45508 | H11: =if(A11="","", iferror(DAY(A11),"")) -> 4 | I11: =if(A11="","", IFERROR(MONTH(A11),"")) -> 8 | J11: =if(A11="","", IFERROR(year(A11),"")) -> 2024 | K11: =TEXT(A11,"mm/yyyy") -> 08/2024
A12: 45508 | B12: MERCADO LIVRE SINCE | C12: MERCADO PAGO SINCE - 9511092439-1 | D12: VENDAS MERCADO LIVRE SINCE | E12: 908.67 | F12: PAGO | G12: 45508 | H12: =if(A12="","", iferror(DAY(A12),"")) -> 4 | I12: =if(A12="","", IFERROR(MONTH(A12),"")) -> 8 | J12: =if(A12="","", IFERROR(year(A12),"")) -> 2024 | K12: =TEXT(A12,"mm/yyyy") -> 08/2024
A13: 45509 | B13: MERCADO LIVRE LIVRE FARMEL | C13: BANCO DO BRASIL - 65204-0 | D13: VENDAS MERCADO LIVRE FARMEL | E13: 626.33 | F13: TRANSFERÊNCIA | G13: 45509 | H13: =if(A13="","", iferror(DAY(A13),"")) -> 5 | I13: =if(A13="","", IFERROR(MONTH(A13),"")) -> 8 | J13: =if(A13="","", IFERROR(year(A13),"")) -> 2024 | K13: =TEXT(A13,"mm/yyyy") -> 08/2024
... A1466: 46146 | B1466: AMAZON | C1466: BANCO DO BRASIL - 65204-0 | D1466: VENDAS AMAZON | E1466: 5767 | F1466: ABERTO | G1466: 46146 | H1466: =if(A1466="","", iferror(DAY(A1466),"")) -> 4 | I1466: =if(A1466="","", IFERROR(MONTH(A1466),"")) -> 5 | J1466: =if(A1466="","", IFERROR(year(A1466),"")) -> 2026 | K1466: =TEXT(A1466,"mm/yyyy") -> 05/2026
H1467: =if(A1467="","", iferror(DAY(A1467),"")) | I1467: =if(A1467="","", IFERROR(MONTH(A1467),"")) | J1467: =if(A1467="","", IFERROR(year(A1467),"")) | K1467: =TEXT(A1467,"mm/yyyy") -> 12/1899
H1468: =if(A1468="","", iferror(DAY(A1468),"")) | I1468: =if(A1468="","", IFERROR(MONTH(A1468),"")) | J1468: =if(A1468="","", IFERROR(year(A1468),"")) | K1468: =TEXT(A1468,"mm/yyyy") -> 12/1899
H1469: =if(A1469="","", iferror(DAY(A1469),"")) | I1469: =if(A1469="","", IFERROR(MONTH(A1469),"")) | J1469: =if(A1469="","", IFERROR(year(A1469),"")) | K1469: =TEXT(A1469,"mm/yyyy") -> 12/1899
H1470: =if(A1470="","", iferror(DAY(A1470),"")) | I1470: =if(A1470="","", IFERROR(MONTH(A1470),"")) | J1470: =if(A1470="","", IFERROR(year(A1470),"")) | K1470: =TEXT(A1470,"mm/yyyy") -> 12/1899
H1471: =if(A1471="","", iferror(DAY(A1471),"")) | I1471: =if(A1471="","", IFERROR(MONTH(A1471),"")) | J1471: =if(A1471="","", IFERROR(year(A1471),"")) | K1471: =TEXT(A1471,"mm/yyyy") -> 12/1899
H1472: =if(A1472="","", iferror(DAY(A1472),"")) | I1472: =if(A1472="","", IFERROR(MONTH(A1472),"")) | J1472: =if(A1472="","", IFERROR(year(A1472),"")) | K1472: =TEXT(A1472,"mm/yyyy") -> 12/1899
H1473: =if(A1473="","", iferror(DAY(A1473),"")) | I1473: =if(A1473="","", IFERROR(MONTH(A1473),"")) | J1473: =if(A1473="","", IFERROR(year(A1473),"")) | K1473: =TEXT(A1473,"mm/yyyy") -> 12/1899
H1474: =if(A1474="","", iferror(DAY(A1474),"")) | I1474: =if(A1474="","", IFERROR(MONTH(A1474),"")) | J1474: =if(A1474="","", IFERROR(year(A1474),"")) | K1474: =TEXT(A1474,"mm/yyyy") -> 12/1899
H1475: =if(A1475="","", iferror(DAY(A1475),"")) | I1475: =if(A1475="","", IFERROR(MONTH(A1475),"")) | J1475: =if(A1475="","", IFERROR(year(A1475),"")) | K1475: =TEXT(A1475,"mm/yyyy") -> 12/1899
H1476: =if(A1476="","", iferror(DAY(A1476),"")) | I1476: =if(A1476="","", IFERROR(MONTH(A1476),"")) | J1476: =if(A1476="","", IFERROR(year(A1476),"")) | K1476: =TEXT(A1476,"mm/yyyy") -> 12/1899
H1477: =if(A1477="","", iferror(DAY(A1477),"")) | I1477: =if(A1477="","", IFERROR(MONTH(A1477),"")) | J1477: =if(A1477="","", IFERROR(year(A1477),"")) | K1477: =TEXT(A1477,"mm/yyyy") -> 12/1899
H1478: =if(A1478="","", iferror(DAY(A1478),"")) | I1478: =if(A1478="","", IFERROR(MONTH(A1478),"")) | J1478: =if(A1478="","", IFERROR(year(A1478),"")) | K1478: =TEXT(A1478,"mm/yyyy") -> 12/1899
... H1999: =if(A1999="","", iferror(DAY(A1999),"")) | I1999: =if(A1999="","", IFERROR(MONTH(A1999),"")) | J1999: =if(A1999="","", IFERROR(year(A1999),"")) | K1999: =TEXT(A1999,"mm/yyyy") -> 12/1899

Sheet Simulador de caixa
A1: MÊS | B1: 2026
A2: ANO | B2: 3
A4: DATA | C4: VALOR TRANSFERIDO PARA A CONTA BB | D4: VALOR PAGO DA CONTA SINCE+VALOR PAGO DA CONTA FARMEL | E4: VALOR LIBERADO | F4: VALOR A RECEBER | G4: ENTRADAS TOTAIS | H4: DESPESAS PAGAS | I4: DESPESAS EM ABERTO | J4: DESPESAS AGENDADAS | K4: DESPESAS TOTAIS | L4: ENTRADAS TOTAIS-DESPESAS TOTAIS | M4: SALDO FINAL
A5: 1 | B5: =SUMIFS('COLOQUE AQUI OS SALDOS DAS CONT'!$B:$B,'COLOQUE AQUI OS SALDOS DAS CONT'!$D:$D,$A$5,'COLOQUE AQUI OS SALDOS DAS CONT'!$E:$E,$B$2,'COLOQUE AQUI OS SALDOS DAS CONT'!$F:$F,$B$1) -> 109736.1 | C5: =SUMIFS('Lançamentos de receitas'!$E:$E,'Lançamentos de receitas'!$C:$C,'Contas dos banco'!$C$2,'Lançamentos de receitas'!$H:$H,A5,'Lançamentos de receitas'!$I:$I,$B$2,'Lançamentos de receitas'!$J:$J,$B$1,'Lançamentos de receitas'!$F:$F,"TRANSFERÊNCIA") -> 2615.78 | D5: =+SUMIFS('Lançamentos de receitas'!$E:$E,'Lançamentos de receitas'!$C:$C,'Contas dos banco'!$C$3,'Lançamentos de receitas'!$H:$H,A5,'Lançamentos de receitas'!$I:$I,$B$2,'Lançamentos de receitas'!$J:$J,$B$1,'Lançamentos de receitas'!$F:$F,"PAGO")+SUMIFS('Lançamentos de receitas'!$E:$E,'Lançamentos de receitas'!$C:$C,'Contas dos banco'!$C$4,'Lançamentos de receitas'!$H:$H,A5,'Lançamentos de receitas'!$I:$I,$B$2,'Lançamentos de receitas'!$J:$J,$B$1,'Lançamentos de receitas'!$F:$F,"PAGO") -> 4887.4 | E5: =+SUMIFS('Lançamentos de receitas'!$E:$E,'Lançamentos de receitas'!$F:$F,"liberado",'Lançamentos de receitas'!$H:$H,$A5,'Lançamentos de receitas'!$I:$I,$B$2,'Lançamentos de receitas'!$J:$J,$B$1) -> 0 | F5: =SUMIFS('Lançamentos de receitas'!$E:$E,'Lançamentos de receitas'!$F:$F,"aberto",'Lançamentos de receitas'!$H:$H,$A5,'Lançamentos de receitas'!$I:$I,$B$2,'Lançamentos de receitas'!$J:$J,$B$1) -> 0 | G5: =C5+E5+F5+D5 -> 7503.18 | H5: =SUMIFS('Lançamentos de despesas'!$I:$I,'Lançamentos de despesas'!$E:$E,"pago",'Lançamentos de despesas'!$V:$V,$A5,'Lançamentos de despesas'!$W:$W,$B$2,'Lançamentos de despesas'!$X:$X,$B$1) -> 0 | I5: =SUMIFs('Lançamentos de despesas'!$I:$I,'Lançamentos de despesas'!$E:$E,"aberto",'Lançamentos de despesas'!$S:$S,A5,'Lançamentos de despesas'!$T:$T,$B$2,'Lançamentos de despesas'!$U:$U,$B$1) -> 0 | J5: =SUMIFs('Lançamentos de despesas'!$I:$I,'Lançamentos de despesas'!$E:$E,"agendado",'Lançamentos de despesas'!$S:$S,A5,'Lançamentos de despesas'!$T:$T,$B$2,'Lançamentos de despesas'!$U:$U,$B$1) -> 0 | K5: =H5+I5+J5 -> 0 | L5: =G5-K5 -> 7503.18 | M5: =L5+B5 -> 117239.28
A6: 2 | B6: =M5 -> 117239.28 | C6: =SUMIFS('Lançamentos de receitas'!$E:$E,'Lançamentos de receitas'!$C:$C,'Contas dos banco'!$C$2,'Lançamentos de receitas'!$H:$H,A6,'Lançamentos de receitas'!$I:$I,$B$2,'Lançamentos de receitas'!$J:$J,$B$1,'Lançamentos de receitas'!$F:$F,"TRANSFERÊNCIA") -> 109.72 | D6: =+SUMIFS('Lançamentos de receitas'!$E:$E,'Lançamentos de receitas'!$C:$C,'Contas dos banco'!$C$3,'Lançamentos de receitas'!$H:$H,A6,'Lançamentos de receitas'!$I:$I,$B$2,'Lançamentos de receitas'!$J:$J,$B$1,'Lançamentos de receitas'!$F:$F,"PAGO")+SUMIFS('Lançamentos de receitas'!$E:$E,'Lançamentos de receitas'!$C:$C,'Contas dos banco'!$C$4,'Lançamentos de receitas'!$H:$H,A6,'Lançamentos de receitas'!$I:$I,$B$2,'Lançamentos de receitas'!$J:$J,$B$1,'Lançamentos de receitas'!$F:$F,"PAGO") -> 226.04 | E6: =+SUMIFS('Lançamentos de receitas'!$E:$E,'Lançamentos de receitas'!$F:$F,"liberado",'Lançamentos de receitas'!$H:$H,$A6,'Lançamentos de receitas'!$I:$I,$B$2,'Lançamentos de receitas'!$J:$J,$B$1) -> 0 | F6: =SUMIFS('Lançamentos de receitas'!$E:$E,'Lançamentos de receitas'!$F:$F,"aberto",'Lançamentos de receitas'!$H:$H,$A6,'Lançamentos de receitas'!$I:$I,$B$2,'Lançamentos de receitas'!$J:$J,$B$1) -> 0 | G6: =C6+E6+F6+D6 -> 335.76 | H6: =SUMIFS('Lançamentos de despesas'!$I:$I,'Lançamentos de despesas'!$E:$E,"pago",'Lançamentos de despesas'!$V:$V,$A6,'Lançamentos de despesas'!$W:$W,$B$2,'Lançamentos de despesas'!$X:$X,$B$1) -> 7283.42 | I6: =SUMIFs('Lançamentos de despesas'!$I:$I,'Lançamentos de despesas'!$E:$E,"aberto",'Lançamentos de despesas'!$S:$S,A6,'Lançamentos de despesas'!$T:$T,$B$2,'Lançamentos de despesas'!$U:$U,$B$1) -> 0 | J6: =SUMIFs('Lançamentos de despesas'!$I:$I,'Lançamentos de despesas'!$E:$E,"agendado",'Lançamentos de despesas'!$S:$S,A6,'Lançamentos de despesas'!$T:$T,$B$2,'Lançamentos de despesas'!$U:$U,$B$1) -> 0 | K6: =H6+I6+J6 -> 7283.42 | L6: =G6-K6 -> -6947.66 | M6: =L6+M5 -> 110291.62
A7: 3 | B7: =M6 -> 110291.62 | C7: =SUMIFS('Lançamentos de receitas'!$E:$E,'Lançamentos de receitas'!$C:$C,'Contas dos banco'!$C$2,'Lançamentos de receitas'!$H:$H,A7,'Lançamentos de receitas'!$I:$I,$B$2,'Lançamentos de receitas'!$J:$J,$B$1,'Lançamentos de receitas'!$F:$F,"TRANSFERÊNCIA") -> 34441.04 | D7: =+SUMIFS('Lançamentos de receitas'!$E:$E,'Lançamentos de receitas'!$C:$C,'Contas dos banco'!$C$3,'Lançamentos de receitas'!$H:$H,A7,'Lançamentos de receitas'!$I:$I,$B$2,'Lançamentos de receitas'!$J:$J,$B$1,'Lançamentos de receitas'!$F:$F,"PAGO")+SUMIFS('Lançamentos de receitas'!$E:$E,'Lançamentos de receitas'!$C:$C,'Contas dos banco'!$C$4,'Lançamentos de receitas'!$H:$H,A7,'Lançamentos de receitas'!$I:$I,$B$2,'Lançamentos de receitas'!$J:$J,$B$1,'Lançamentos de receitas'!$F:$F,"PAGO") -> 3119.85 | E7: =+SUMIFS('Lançamentos de receitas'!$E:$E,'Lançamentos de receitas'!$F:$F,"liberado",'Lançamentos de receitas'!$H:$H,$A7,'Lançamentos de receitas'!$I:$I,$B$2,'Lançamentos de receitas'!$J:$J,$B$1) -> 0 | F7: =SUMIFS('Lançamentos de receitas'!$E:$E,'Lançamentos de receitas'!$F:$F,"aberto",'Lançamentos de receitas'!$H:$H,$A7,'Lançamentos de receitas'!$I:$I,$B$2,'Lançamentos de receitas'!$J:$J,$B$1) -> 0 | G7: =C7+E7+F7+D7 -> 37560.89 | H7: =SUMIFS('Lançamentos de despesas'!$I:$I,'Lançamentos de despesas'!$E:$E,"pago",'Lançamentos de despesas'!$V:$V,$A7,'Lançamentos de despesas'!$W:$W,$B$2,'Lançamentos de despesas'!$X:$X,$B$1) -> 10408.63 | I7: =SUMIFs('Lançamentos de despesas'!$I:$I,'Lançamentos de despesas'!$E:$E,"aberto",'Lançamentos de despesas'!$S:$S,A7,'Lançamentos de despesas'!$T:$T,$B$2,'Lançamentos de despesas'!$U:$U,$B$1) -> 0 | J7: =SUMIFs('Lançamentos de despesas'!$I:$I,'Lançamentos de despesas'!$E:$E,"agendado",'Lançamentos de despesas'!$S:$S,A7,'Lançamentos de despesas'!$T:$T,$B$2,'Lançamentos de despesas'!$U:$U,$B$1) -> 0 | K7: =H7+I7+J7 -> 10408.63 | L7: =G7-K7 -> 27152.26 | M7: =L7+M6 -> 137443.88
A8: 4 | B8: =M7 -> 137443.88 | C8: =SUMIFS('Lançamentos de receitas'!$E:$E,'Lançamentos de receitas'!$C:$C,'Contas dos banco'!$C$2,'Lançamentos de receitas'!$H:$H,A8,'Lançamentos de receitas'!$I:$I,$B$2,'Lançamentos de receitas'!$J:$J,$B$1,'Lançamentos de receitas'!$F:$F,"TRANSFERÊNCIA") -> 2026.12 | D8: =+SUMIFS('Lançamentos de receitas'!$E:$E,'Lançamentos de receitas'!$C:$C,'Contas dos banco'!$C$3,'Lançamentos de receitas'!$H:$H,A8,'Lançamentos de receitas'!$I:$I,$B$2,'Lançamentos de receitas'!$J:$J,$B$1,'Lançamentos de receitas'!$F:$F,"PAGO")+SUMIFS('Lançamentos de receitas'!$E:$E,'Lançamentos de receitas'!$C:$C,'Contas dos banco'!$C$4,'Lançamentos de receitas'!$H:$H,A8,'Lançamentos de receitas'!$I:$I,$B$2,'Lançamentos de receitas'!$J:$J,$B$1,'Lançamentos de receitas'!$F:$F,"PAGO") -> 4431.24 | E8: =+SUMIFS('Lançamentos de receitas'!$E:$E,'Lançamentos de receitas'!$F:$F,"liberado",'Lançamentos de receitas'!$H:$H,$A8,'Lançamentos de receitas'!$I:$I,$B$2,'Lançamentos de receitas'!$J:$J,$B$1) -> 0 | F8: =SUMIFS('Lançamentos de receitas'!$E:$E,'Lançamentos de receitas'!$F:$F,"aberto",'Lançamentos de receitas'!$H:$H,$A8,'Lançamentos de receitas'!$I:$I,$B$2,'Lançamentos de receitas'!$J:$J,$B$1) -> 0 | G8: =C8+E8+F8+D8 -> 6457.36 | H8: =SUMIFS('Lançamentos de despesas'!$I:$I,'Lançamentos de despesas'!$E:$E,"pago",'Lançamentos de despesas'!$V:$V,$A8,'Lançamentos de despesas'!$W:$W,$B$2,'Lançamentos de despesas'!$X:$X,$B$1) -> 0 | I8: =SUMIFs('Lançamentos de despesas'!$I:$I,'Lançamentos de despesas'!$E:$E,"aberto",'Lançamentos de despesas'!$S:$S,A8,'Lançamentos de despesas'!$T:$T,$B$2,'Lançamentos de despesas'!$U:$U,$B$1) -> 0 | J8: =SUMIFs('Lançamentos de despesas'!$I:$I,'Lançamentos de despesas'!$E:$E,"agendado",'Lançamentos de despesas'!$S:$S,A8,'Lançamentos de despesas'!$T:$T,$B$2,'Lançamentos de despesas'!$U:$U,$B$1) -> 0 | K8: =H8+I8+J8 -> 0 | L8: =G8-K8 -> 6457.36 | M8: =L8+M7 -> 143901.24
A9: 5 | B9: =M8 -> 143901.24 | C9: =SUMIFS('Lançamentos de receitas'!$E:$E,'Lançamentos de receitas'!$C:$C,'Contas dos banco'!$C$2,'Lançamentos de receitas'!$H:$H,A9,'Lançamentos de receitas'!$I:$I,$B$2,'Lançamentos de receitas'!$J:$J,$B$1,'Lançamentos de receitas'!$F:$F,"TRANSFERÊNCIA") -> 1890.17 | D9: =+SUMIFS('Lançamentos de receitas'!$E:$E,'Lançamentos de receitas'!$C:$C,'Contas dos banco'!$C$3,'Lançamentos de receitas'!$H:$H,A9,'Lançamentos de receitas'!$I:$I,$B$2,'Lançamentos de receitas'!$J:$J,$B$1,'Lançamentos de receitas'!$F:$F,"PAGO")+SUMIFS('Lançamentos de receitas'!$E:$E,'Lançamentos de receitas'!$C:$C,'Contas dos banco'!$C$4,'Lançamentos de receitas'!$H:$H,A9,'Lançamentos de receitas'!$I:$I,$B$2,'Lançamentos de receitas'!$J:$J,$B$1,'Lançamentos de receitas'!$F:$F,"PAGO") -> 4815.19 | E9: =+SUMIFS('Lançamentos de receitas'!$E:$E,'Lançamentos de receitas'!$F:$F,"liberado",'Lançamentos de receitas'!$H:$H,$A9,'Lançamentos de receitas'!$I:$I,$B$2,'Lançamentos de receitas'!$J:$J,$B$1) -> 0 | F9: =SUMIFS('Lançamentos de receitas'!$E:$E,'Lançamentos de receitas'!$F:$F,"aberto",'Lançamentos de receitas'!$H:$H,$A9,'Lançamentos de receitas'!$I:$I,$B$2,'Lançamentos de receitas'!$J:$J,$B$1) -> 0 | G9: =C9+E9+F9+D9 -> 6705.36 | H9: =SUMIFS('Lançamentos de despesas'!$I:$I,'Lançamentos de despesas'!$E:$E,"pago",'Lançamentos de despesas'!$V:$V,$A9,'Lançamentos de despesas'!$W:$W,$B$2,'Lançamentos de despesas'!$X:$X,$B$1) -> 0 | I9: =SUMIFs('Lançamentos de despesas'!$I:$I,'Lançamentos de despesas'!$E:$E,"aberto",'Lançamentos de despesas'!$S:$S,A9,'Lançamentos de despesas'!$T:$T,$B$2,'Lançamentos de despesas'!$U:$U,$B$1) -> 0 | J9: =SUMIFs('Lançamentos de despesas'!$I:$I,'Lançamentos de despesas'!$E:$E,"agendado",'Lançamentos de despesas'!$S:$S,A9,'Lançamentos de despesas'!$T:$T,$B$2,'Lançamentos de despesas'!$U:$U,$B$1) -> 0 | K9: =H9+I9+J9 -> 0 | L9: =G9-K9 -> 6705.36 | M9: =L9+M8 -> 150606.6
A10: 6 | B10: =M9 -> 150606.6 | C10: =SUMIFS('Lançamentos de receitas'!$E:$E,'Lançamentos de receitas'!$C:$C,'Contas dos banco'!$C$2,'Lançamentos de receitas'!$H:$H,A10,'Lançamentos de receitas'!$I:$I,$B$2,'Lançamentos de receitas'!$J:$J,$B$1,'Lançamentos de receitas'!$F:$F,"TRANSFERÊNCIA") -> 7639.453 | D10: =+SUMIFS('Lançamentos de receitas'!$E:$E,'Lançamentos de receitas'!$C:$C,'Contas dos banco'!$C$3,'Lançamentos de receitas'!$H:$H,A10,'Lançamentos de receitas'!$I:$I,$B$2,'Lançamentos de receitas'!$J:$J,$B$1,'Lançamentos de receitas'!$F:$F,"PAGO")+SUMIFS('Lançamentos de receitas'!$E:$E,'Lançamentos de receitas'!$C:$C,'Contas dos banco'!$C$4,'Lançamentos de receitas'!$H:$H,A10,'Lançamentos de receitas'!$I:$I,$B$2,'Lançamentos de receitas'!$J:$J,$B$1,'Lançamentos de receitas'!$F:$F,"PAGO") -> 3131.67 | E10: =+SUMIFS('Lançamentos de receitas'!$E:$E,'Lançamentos de receitas'!$F:$F,"liberado",'Lançamentos de receitas'!$H:$H,$A10,'Lançamentos de receitas'!$I:$I,$B$2,'Lançamentos de receitas'!$J:$J,$B$1) -> 0 | F10: =SUMIFS('Lançamentos de receitas'!$E:$E,'Lançamentos de receitas'!$F:$F,"aberto",'Lançamentos de receitas'!$H:$H,$A10,'Lançamentos de receitas'!$I:$I,$B$2,'Lançamentos de receitas'!$J:$J,$B$1) -> 0 | G10: =C10+E10+F10+D10 -> 10771.123 | H10: =SUMIFS('Lançamentos de despesas'!$I:$I,'Lançamentos de despesas'!$E:$E,"pago",'Lançamentos de despesas'!$V:$V,$A10,'Lançamentos de despesas'!$W:$W,$B$2,'Lançamentos de despesas'!$X:$X,$B$1) -> 0 | I10: =SUMIFs('Lançamentos de despesas'!$I:$I,'Lançamentos de despesas'!$E:$E,"aberto",'Lançamentos de despesas'!$S:$S,A10,'Lançamentos de despesas'!$T:$T,$B$2,'Lançamentos de despesas'!$U:$U,$B$1) -> 0 | J10: =SUMIFs('Lançamentos de despesas'!$I:$I,'Lançamentos de despesas'!$E:$E,"agendado",'Lançamentos de despesas'!$S:$S,A10,'Lançamentos de despesas'!$T:$T,$B$2,'Lançamentos de despesas'!$U:$U,$B$1) -> 0 | K10: =H10+I10+J10 -> 0 | L10: =G10-K10 -> 10771.123 | M10: =L10+M9 -> 161377.72
A11: 7 | B11: =M10 -> 161377.72 | C11: =SUMIFS('Lançamentos de receitas'!$E:$E,'Lançamentos de receitas'!$C:$C,'Contas dos banco'!$C$2,'Lançamentos de receitas'!$H:$H,A11,'Lançamentos de receitas'!$I:$I,$B$2,'Lançamentos de receitas'!$J:$J,$B$1,'Lançamentos de receitas'!$F:$F,"TRANSFERÊNCIA") -> 2319.39 | D11: =+SUMIFS('Lançamentos de receitas'!$E:$E,'Lançamentos de receitas'!$C:$C,'Contas dos banco'!$C$3,'Lançamentos de receitas'!$H:$H,A11,'Lançamentos de receitas'!$I:$I,$B$2,'Lançamentos de receitas'!$J:$J,$B$1,'Lançamentos de receitas'!$F:$F,"PAGO")+SUMIFS('Lançamentos de receitas'!$E:$E,'Lançamentos de receitas'!$C:$C,'Contas dos banco'!$C$4,'Lançamentos de receitas'!$H:$H,A11,'Lançamentos de receitas'!$I:$I,$B$2,'Lançamentos de receitas'!$J:$J,$B$1,'Lançamentos de receitas'!$F:$F,"PAGO") -> 2991.85 | E11: =+SUMIFS('Lançamentos de receitas'!$E:$E,'Lançamentos de receitas'!$F:$F,"liberado",'Lançamentos de receitas'!$H:$H,$A11,'Lançamentos de receitas'!$I:$I,$B$2,'Lançamentos de receitas'!$J:$J,$B$1) -> 0 | F11: =SUMIFS('Lançamentos de receitas'!$E:$E,'Lançamentos de receitas'!$F:$F,"aberto",'Lançamentos de receitas'!$H:$H,$A11,'Lançamentos de receitas'!$I:$I,$B$2,'Lançamentos de receitas'!$J:$J,$B$1) -> 0 | G11: =C11+E11+F11+D11 -> 5311.24 | H11: =SUMIFS('Lançamentos de despesas'!$I:$I,'Lançamentos de despesas'!$E:$E,"pago",'Lançamentos de despesas'!$V:$V,$A11,'Lançamentos de despesas'!$W:$W,$B$2,'Lançamentos de despesas'!$X:$X,$B$1) -> 0 | I11: =SUMIFs('Lançamentos de despesas'!$I:$I,'Lançamentos de despesas'!$E:$E,"aberto",'Lançamentos de despesas'!$S:$S,A11,'Lançamentos de despesas'!$T:$T,$B$2,'Lançamentos de despesas'!$U:$U,$B$1) -> 0 | J11: =SUMIFs('Lançamentos de despesas'!$I:$I,'Lançamentos de despesas'!$E:$E,"agendado",'Lançamentos de despesas'!$S:$S,A11,'Lançamentos de despesas'!$T:$T,$B$2,'Lançamentos de despesas'!$U:$U,$B$1) -> 0 | K11: =H11+I11+J11 -> 0 | L11: =G11-K11 -> 5311.24 | M11: =L11+M10 -> 166688.96
A12: 8 | B12: =M11 -> 166688.96 | C12: =SUMIFS('Lançamentos de receitas'!$E:$E,'Lançamentos de receitas'!$C:$C,'Contas dos banco'!$C$2,'Lançamentos de receitas'!$H:$H,A12,'Lançamentos de receitas'!$I:$I,$B$2,'Lançamentos de receitas'!$J:$J,$B$1,'Lançamentos de receitas'!$F:$F,"TRANSFERÊNCIA") -> 2433.91 | D12: =+SUMIFS('Lançamentos de receitas'!$E:$E,'Lançamentos de receitas'!$C:$C,'Contas dos banco'!$C$3,'Lançamentos de receitas'!$H:$H,A12,'Lançamentos de receitas'!$I:$I,$B$2,'Lançamentos de receitas'!$J:$J,$B$1,'Lançamentos de receitas'!$F:$F,"PAGO")+SUMIFS('Lançamentos de receitas'!$E:$E,'Lançamentos de receitas'!$C:$C,'Contas dos banco'!$C$4,'Lançamentos de receitas'!$H:$H,A12,'Lançamentos de receitas'!$I:$I,$B$2,'Lançamentos de receitas'!$J:$J,$B$1,'Lançamentos de receitas'!$F:$F,"PAGO") -> 2726.63 | E12: =+SUMIFS('Lançamentos de receitas'!$E:$E,'Lançamentos de receitas'!$F:$F,"liberado",'Lançamentos de receitas'!$H:$H,$A12,'Lançamentos de receitas'!$I:$I,$B$2,'Lançamentos de receitas'!$J:$J,$B$1) -> 0 | F12: =SUMIFS('Lançamentos de receitas'!$E:$E,'Lançamentos de receitas'!$F:$F,"aberto",'Lançamentos de receitas'!$H:$H,$A12,'Lançamentos de receitas'!$I:$I,$B$2,'Lançamentos de receitas'!$J:$J,$B$1) -> 0 | G12: =C12+E12+F12+D12 -> 5160.54 | H12: =SUMIFS('Lançamentos de despesas'!$I:$I,'Lançamentos de despesas'!$E:$E,"pago",'Lançamentos de despesas'!$V:$V,$A12,'Lançamentos de despesas'!$W:$W,$B$2,'Lançamentos de despesas'!$X:$X,$B$1) -> 0 | I12: =SUMIFs('Lançamentos de despesas'!$I:$I,'Lançamentos de despesas'!$E:$E,"aberto",'Lançamentos de despesas'!$S:$S,A12,'Lançamentos de despesas'!$T:$T,$B$2,'Lançamentos de despesas'!$U:$U,$B$1) -> 0 | J12: =SUMIFs('Lançamentos de despesas'!$I:$I,'Lançamentos de despesas'!$E:$E,"agendado",'Lançamentos de despesas'!$S:$S,A12,'Lançamentos de despesas'!$T:$T,$B$2,'Lançamentos de despesas'!$U:$U,$B$1) -> 0 | K12: =H12+I12+J12 -> 0 | L12: =G12-K12 -> 5160.54 | M12: =L12+M11 -> 171849.5
A13: 9 | B13: =M12 -> 171849.5 | C13: =SUMIFS('Lançamentos de receitas'!$E:$E,'Lançamentos de receitas'!$C:$C,'Contas dos banco'!$C$2,'Lançamentos de receitas'!$H:$H,A13,'Lançamentos de receitas'!$I:$I,$B$2,'Lançamentos de receitas'!$J:$J,$B$1,'Lançamentos de receitas'!$F:$F,"TRANSFERÊNCIA") -> 14647.84 | D13: =+SUMIFS('Lançamentos de receitas'!$E:$E,'Lançamentos de receitas'!$C:$C,'Contas dos banco'!$C$3,'Lançamentos de receitas'!$H:$H,A13,'Lançamentos de receitas'!$I:$I,$B$2,'Lançamentos de receitas'!$J:$J,$B$1,'Lançamentos de receitas'!$F:$F,"PAGO")+SUMIFS('Lançamentos de receitas'!$E:$E,'Lançamentos de receitas'!$C:$C,'Contas dos banco'!$C$4,'Lançamentos de receitas'!$H:$H,A13,'Lançamentos de receitas'!$I:$I,$B$2,'Lançamentos de receitas'!$J:$J,$B$1,'Lançamentos de receitas'!$F:$F,"PAGO") -> 46.53 | E13: =+SUMIFS('Lançamentos de receitas'!$E:$E,'Lançamentos de receitas'!$F:$F,"liberado",'Lançamentos de receitas'!$H:$H,$A13,'Lançamentos de receitas'!$I:$I,$B$2,'Lançamentos de receitas'!$J:$J,$B$1) -> 0 | F13: =SUMIFS('Lançamentos de receitas'!$E:$E,'Lançamentos de receitas'!$F:$F,"aberto",'Lançamentos de receitas'!$H:$H,$A13,'Lançamentos de receitas'!$I:$I,$B$2,'Lançamentos de receitas'!$J:$J,$B$1) -> 0 | G13: =C13+E13+F13+D13 -> 14694.37 | H13: =SUMIFS('Lançamentos de despesas'!$I:$I,'Lançamentos de despesas'!$E:$E,"pago",'Lançamentos de despesas'!$V:$V,$A13,'Lançamentos de despesas'!$W:$W,$B$2,'Lançamentos de despesas'!$X:$X,$B$1) -> 3084.59 | I13: =SUMIFs('Lançamentos de despesas'!$I:$I,'Lançamentos de despesas'!$E:$E,"aberto",'Lançamentos de despesas'!$S:$S,A13,'Lançamentos de despesas'!$T:$T,$B$2,'Lançamentos de despesas'!$U:$U,$B$1) -> 0 | J13: =SUMIFs('Lançamentos de despesas'!$I:$I,'Lançamentos de despesas'!$E:$E,"agendado",'Lançamentos de despesas'!$S:$S,A13,'Lançamentos de despesas'!$T:$T,$B$2,'Lançamentos de despesas'!$U:$U,$B$1) -> 0 | K13: =H13+I13+J13 -> 3084.59 | L13: =G13-K13 -> 11609.78 | M13: =L13+M12 -> 183459.28
A14: 10 | B14: =M13 -> 183459.28 | C14: =SUMIFS('Lançamentos de receitas'!$E:$E,'Lançamentos de receitas'!$C:$C,'Contas dos banco'!$C$2,'Lançamentos de receitas'!$H:$H,A14,'Lançamentos de receitas'!$I:$I,$B$2,'Lançamentos de receitas'!$J:$J,$B$1,'Lançamentos de receitas'!$F:$F,"TRANSFERÊNCIA") -> 1996.75 | D14: =+SUMIFS('Lançamentos de receitas'!$E:$E,'Lançamentos de receitas'!$C:$C,'Contas dos banco'!$C$3,'Lançamentos de receitas'!$H:$H,A14,'Lançamentos de receitas'!$I:$I,$B$2,'Lançamentos de receitas'!$J:$J,$B$1,'Lançamentos de receitas'!$F:$F,"PAGO")+SUMIFS('Lançamentos de receitas'!$E:$E,'Lançamentos de receitas'!$C:$C,'Contas dos banco'!$C$4,'Lançamentos de receitas'!$H:$H,A14,'Lançamentos de receitas'!$I:$I,$B$2,'Lançamentos de receitas'!$J:$J,$B$1,'Lançamentos de receitas'!$F:$F,"PAGO") -> 2631.87 | E14: =+SUMIFS('Lançamentos de receitas'!$E:$E,'Lançamentos de receitas'!$F:$F,"liberado",'Lançamentos de receitas'!$H:$H,$A14,'Lançamentos de receitas'!$I:$I,$B$2,'Lançamentos de receitas'!$J:$J,$B$1) -> 0 | F14: =SUMIFS('Lançamentos de receitas'!$E:$E,'Lançamentos de receitas'!$F:$F,"aberto",'Lançamentos de receitas'!$H:$H,$A14,'Lançamentos de receitas'!$I:$I,$B$2,'Lançamentos de receitas'!$J:$J,$B$1) -> 0 | G14: =C14+E14+F14+D14 -> 4628.62 | H14: =SUMIFS('Lançamentos de despesas'!$I:$I,'Lançamentos de despesas'!$E:$E,"pago",'Lançamentos de despesas'!$V:$V,$A14,'Lançamentos de despesas'!$W:$W,$B$2,'Lançamentos de despesas'!$X:$X,$B$1) -> 7592.09 | I14: =SUMIFs('Lançamentos de despesas'!$I:$I,'Lançamentos de despesas'!$E:$E,"aberto",'Lançamentos de despesas'!$S:$S,A14,'Lançamentos de despesas'!$T:$T,$B$2,'Lançamentos de despesas'!$U:$U,$B$1) -> 0 | J14: =SUMIFs('Lançamentos de despesas'!$I:$I,'Lançamentos de despesas'!$E:$E,"agendado",'Lançamentos de despesas'!$S:$S,A14,'Lançamentos de despesas'!$T:$T,$B$2,'Lançamentos de despesas'!$U:$U,$B$1) -> 0 | K14: =H14+I14+J14 -> 7592.09 | L14: =G14-K14 -> -2963.47 | M14: =L14+M13 -> 180495.81
A15: 11 | B15: =M14 -> 180495.81 | C15: =SUMIFS('Lançamentos de receitas'!$E:$E,'Lançamentos de receitas'!$C:$C,'Contas dos banco'!$C$2,'Lançamentos de receitas'!$H:$H,A15,'Lançamentos de receitas'!$I:$I,$B$2,'Lançamentos de receitas'!$J:$J,$B$1,'Lançamentos de receitas'!$F:$F,"TRANSFERÊNCIA") -> 0 | D15: =+SUMIFS('Lançamentos de receitas'!$E:$E,'Lançamentos de receitas'!$C:$C,'Contas dos banco'!$C$3,'Lançamentos de receitas'!$H:$H,A15,'Lançamentos de receitas'!$I:$I,$B$2,'Lançamentos de receitas'!$J:$J,$B$1,'Lançamentos de receitas'!$F:$F,"PAGO")+SUMIFS('Lançamentos de receitas'!$E:$E,'Lançamentos de receitas'!$C:$C,'Contas dos banco'!$C$4,'Lançamentos de receitas'!$H:$H,A15,'Lançamentos de receitas'!$I:$I,$B$2,'Lançamentos de receitas'!$J:$J,$B$1,'Lançamentos de receitas'!$F:$F,"PAGO") -> 2900.47 | E15: =+SUMIFS('Lançamentos de receitas'!$E:$E,'Lançamentos de receitas'!$F:$F,"liberado",'Lançamentos de receitas'!$H:$H,$A15,'Lançamentos de receitas'!$I:$I,$B$2,'Lançamentos de receitas'!$J:$J,$B$1) -> 0 | F15: =SUMIFS('Lançamentos de receitas'!$E:$E,'Lançamentos de receitas'!$F:$F,"aberto",'Lançamentos de receitas'!$H:$H,$A15,'Lançamentos de receitas'!$I:$I,$B$2,'Lançamentos de receitas'!$J:$J,$B$1) -> 0 | G15: =C15+E15+F15+D15 -> 2900.47 | H15: =SUMIFS('Lançamentos de despesas'!$I:$I,'Lançamentos de despesas'!$E:$E,"pago",'Lançamentos de despesas'!$V:$V,$A15,'Lançamentos de despesas'!$W:$W,$B$2,'Lançamentos de despesas'!$X:$X,$B$1) -> 1035.15 | I15: =SUMIFs('Lançamentos de despesas'!$I:$I,'Lançamentos de despesas'!$E:$E,"aberto",'Lançamentos de despesas'!$S:$S,A15,'Lançamentos de despesas'!$T:$T,$B$2,'Lançamentos de despesas'!$U:$U,$B$1) -> 0 | J15: =SUMIFs('Lançamentos de despesas'!$I:$I,'Lançamentos de despesas'!$E:$E,"agendado",'Lançamentos de despesas'!$S:$S,A15,'Lançamentos de despesas'!$T:$T,$B$2,'Lançamentos de despesas'!$U:$U,$B$1) -> 0 | K15: =H15+I15+J15 -> 1035.15 | L15: =G15-K15 -> 1865.32 | M15: =L15+M14 -> 182361.13
A16: 12 | B16: =M15 -> 182361.13 | C16: =SUMIFS('Lançamentos de receitas'!$E:$E,'Lançamentos de receitas'!$C:$C,'Contas dos banco'!$C$2,'Lançamentos de receitas'!$H:$H,A16,'Lançamentos de receitas'!$I:$I,$B$2,'Lançamentos de receitas'!$J:$J,$B$1,'Lançamentos de receitas'!$F:$F,"TRANSFERÊNCIA") -> 3444.4 | D16: =+SUMIFS('Lançamentos de receitas'!$E:$E,'Lançamentos de receitas'!$C:$C,'Contas dos banco'!$C$3,'Lançamentos de receitas'!$H:$H,A16,'Lançamentos de receitas'!$I:$I,$B$2,'Lançamentos de receitas'!$J:$J,$B$1,'Lançamentos de receitas'!$F:$F,"PAGO")+SUMIFS('Lançamentos de receitas'!$E:$E,'Lançamentos de receitas'!$C:$C,'Contas dos banco'!$C$4,'Lançamentos de receitas'!$H:$H,A16,'Lançamentos de receitas'!$I:$I,$B$2,'Lançamentos de receitas'!$J:$J,$B$1,'Lançamentos de receitas'!$F:$F,"PAGO") -> 2881.51 | E16: =+SUMIFS('Lançamentos de receitas'!$E:$E,'Lançamentos de receitas'!$F:$F,"liberado",'Lançamentos de receitas'!$H:$H,$A16,'Lançamentos de receitas'!$I:$I,$B$2,'Lançamentos de receitas'!$J:$J,$B$1) -> 0 | F16: =SUMIFS('Lançamentos de receitas'!$E:$E,'Lançamentos de receitas'!$F:$F,"aberto",'Lançamentos de receitas'!$H:$H,$A16,'Lançamentos de receitas'!$I:$I,$B$2,'Lançamentos de receitas'!$J:$J,$B$1) -> 0 | G16: =C16+E16+F16+D16 -> 6325.91 | H16: =SUMIFS('Lançamentos de despesas'!$I:$I,'Lançamentos de despesas'!$E:$E,"pago",'Lançamentos de despesas'!$V:$V,$A16,'Lançamentos de despesas'!$W:$W,$B$2,'Lançamentos de despesas'!$X:$X,$B$1) -> 60 | I16: =SUMIFs('Lançamentos de despesas'!$I:$I,'Lançamentos de despesas'!$E:$E,"aberto",'Lançamentos de despesas'!$S:$S,A16,'Lançamentos de despesas'!$T:$T,$B$2,'Lançamentos de despesas'!$U:$U,$B$1) -> 0 | J16: =SUMIFs('Lançamentos de despesas'!$I:$I,'Lançamentos de despesas'!$E:$E,"agendado",'Lançamentos de despesas'!$S:$S,A16,'Lançamentos de despesas'!$T:$T,$B$2,'Lançamentos de despesas'!$U:$U,$B$1) -> 0 | K16: =H16+I16+J16 -> 60 | L16: =G16-K16 -> 6265.91 | M16: =L16+M15 -> 188627.04
A17: 13 | B17: =M16 -> 188627.04 | C17: =SUMIFS('Lançamentos de receitas'!$E:$E,'Lançamentos de receitas'!$C:$C,'Contas dos banco'!$C$2,'Lançamentos de receitas'!$H:$H,A17,'Lançamentos de receitas'!$I:$I,$B$2,'Lançamentos de receitas'!$J:$J,$B$1,'Lançamentos de receitas'!$F:$F,"TRANSFERÊNCIA") -> 2077.12 | D17: =+SUMIFS('Lançamentos de receitas'!$E:$E,'Lançamentos de receitas'!$C:$C,'Contas dos banco'!$C$3,'Lançamentos de receitas'!$H:$H,A17,'Lançamentos de receitas'!$I:$I,$B$2,'Lançamentos de receitas'!$J:$J,$B$1,'Lançamentos de receitas'!$F:$F,"PAGO")+SUMIFS('Lançamentos de receitas'!$E:$E,'Lançamentos de receitas'!$C:$C,'Contas dos banco'!$C$4,'Lançamentos de receitas'!$H:$H,A17,'Lançamentos de receitas'!$I:$I,$B$2,'Lançamentos de receitas'!$J:$J,$B$1,'Lançamentos de receitas'!$F:$F,"PAGO") -> 2225.92 | E17: =+SUMIFS('Lançamentos de receitas'!$E:$E,'Lançamentos de receitas'!$F:$F,"liberado",'Lançamentos de receitas'!$H:$H,$A17,'Lançamentos de receitas'!$I:$I,$B$2,'Lançamentos de receitas'!$J:$J,$B$1) -> 0 | F17: =SUMIFS('Lançamentos de receitas'!$E:$E,'Lançamentos de receitas'!$F:$F,"aberto",'Lançamentos de receitas'!$H:$H,$A17,'Lançamentos de receitas'!$I:$I,$B$2,'Lançamentos de receitas'!$J:$J,$B$1) -> 0 | G17: =C17+E17+F17+D17 -> 4303.04 | H17: =SUMIFS('Lançamentos de despesas'!$I:$I,'Lançamentos de despesas'!$E:$E,"pago",'Lançamentos de despesas'!$V:$V,$A17,'Lançamentos de despesas'!$W:$W,$B$2,'Lançamentos de despesas'!$X:$X,$B$1) -> 8712.38 | I17: =SUMIFs('Lançamentos de despesas'!$I:$I,'Lançamentos de despesas'!$E:$E,"aberto",'Lançamentos de despesas'!$S:$S,A17,'Lançamentos de despesas'!$T:$T,$B$2,'Lançamentos de despesas'!$U:$U,$B$1) -> 0 | J17: =SUMIFs('Lançamentos de despesas'!$I:$I,'Lançamentos de despesas'!$E:$E,"agendado",'Lançamentos de despesas'!$S:$S,A17,'Lançamentos de despesas'!$T:$T,$B$2,'Lançamentos de despesas'!$U:$U,$B$1) -> 0 | K17: =H17+I17+J17 -> 8712.38 | L17: =G17-K17 -> -4409.34 | M17: =L17+M16 -> 184217.7
... A35: 31 | B35: =M34 -> 73041.083 | C35: =SUMIFS('Lançamentos de receitas'!$E:$E,'Lançamentos de receitas'!$C:$C,'Contas dos banco'!$C$2,'Lançamentos de receitas'!$H:$H,A35,'Lançamentos de receitas'!$I:$I,$B$2,'Lançamentos de receitas'!$J:$J,$B$1,'Lançamentos de receitas'!$F:$F,"TRANSFERÊNCIA") -> 0 | D35: =+SUMIFS('Lançamentos de receitas'!$E:$E,'Lançamentos de receitas'!$C:$C,'Contas dos banco'!$C$3,'Lançamentos de receitas'!$H:$H,A35,'Lançamentos de receitas'!$I:$I,$B$2,'Lançamentos de receitas'!$J:$J,$B$1,'Lançamentos de receitas'!$F:$F,"PAGO")+SUMIFS('Lançamentos de receitas'!$E:$E,'Lançamentos de receitas'!$C:$C,'Contas dos banco'!$C$4,'Lançamentos de receitas'!$H:$H,A35,'Lançamentos de receitas'!$I:$I,$B$2,'Lançamentos de receitas'!$J:$J,$B$1,'Lançamentos de receitas'!$F:$F,"PAGO") -> 0 | E35: =+SUMIFS('Lançamentos de receitas'!$E:$E,'Lançamentos de receitas'!$F:$F,"liberado",'Lançamentos de receitas'!$H:$H,$A35,'Lançamentos de receitas'!$I:$I,$B$2,'Lançamentos de receitas'!$J:$J,$B$1) -> 0 | F35: =SUMIFS('Lançamentos de receitas'!$E:$E,'Lançamentos de receitas'!$F:$F,"aberto",'Lançamentos de receitas'!$H:$H,$A35,'Lançamentos de receitas'!$I:$I,$B$2,'Lançamentos de receitas'!$J:$J,$B$1) -> 2028.55 | G35: =C35+E35+F35+D35 -> 2028.55 | H35: =SUMIFS('Lançamentos de despesas'!$I:$I,'Lançamentos de despesas'!$E:$E,"pago",'Lançamentos de despesas'!$V:$V,$A35,'Lançamentos de despesas'!$W:$W,$B$2,'Lançamentos de despesas'!$X:$X,$B$1) -> 0 | I35: =SUMIFs('Lançamentos de despesas'!$I:$I,'Lançamentos de despesas'!$E:$E,"aberto",'Lançamentos de despesas'!$S:$S,A35,'Lançamentos de despesas'!$T:$T,$B$2,'Lançamentos de despesas'!$U:$U,$B$1) -> 100 | J35: =SUMIFs('Lançamentos de despesas'!$I:$I,'Lançamentos de despesas'!$E:$E,"agendado",'Lançamentos de despesas'!$S:$S,A35,'Lançamentos de despesas'!$T:$T,$B$2,'Lançamentos de despesas'!$U:$U,$B$1) -> 0 | K35: =H35+I35+J35 -> 100 | L35: =G35-K35 -> 1928.55 | M35: =L35+M34 -> 74969.633
A36: TOTAL DO PERÍODO | C36: =SUBTOTAL(9,C5:C35) -> 134147.67 | D36: =SUBTOTAL(9,D5:D35) -> 68454.51 | E36: =SUBTOTAL(9,E5:E35) -> 0 | F36: =SUBTOTAL(9,F5:F35) -> 31655.11 | G36: =SUBTOTAL(9,G5:G35) -> 234257.29 | H36: =SUBTOTAL(9,H5:H35) -> 106059.75 | I36: =SUBTOTAL(9,I5:I35) -> 158506 | J36: =SUBTOTAL(9,J5:J35) -> 4458.01 | ... L36: =SUBTOTAL(9,L5:L35) -> -34766.467

Sheet TABELA SALDO DAS CONTAS

Sheet COLOQUE AQUI OS SALDOS DAS CONT
A1: CONTA | B1: SALDO | C1: DATA | D1: DIA | E1: MÊS | F1: ANO
A2: BANCO DO BRASIL - 65204-0 | B2: 32217.53 | C2: 45505 | D2: =DAY(C2) -> 1 | E2: =MONTH(C2) -> 8 | F2: =YEAR(C2) -> 2024
B3: 128802.85 | C3: 45536 | D3: =DAY(C3) -> 1 | E3: =MONTH(C3) -> 9 | F3: =YEAR(C3) -> 2024
B4: 59029.8 | C4: 45566 | D4: =DAY(C4) -> 1 | E4: =MONTH(C4) -> 10 | F4: =YEAR(C4) -> 2024
B5: 124413.41 | C5: 45597 | D5: =DAY(C5) -> 1 | E5: =MONTH(C5) -> 11 | F5: =YEAR(C5) -> 2024
B6: 151003.49 | C6: 45627 | D6: =DAY(C6) -> 1 | E6: =MONTH(C6) -> 12 | F6: =YEAR(C6) -> 2024
B7: 104230.66 | C7: 45658 | D7: =DAY(C7) -> 1 | E7: =MONTH(C7) -> 1 | F7: =YEAR(C7) -> 2025
B8: 96832.38 | C8: 45689 | D8: =DAY(C8) -> 1 | E8: =MONTH(C8) -> 2 | F8: =YEAR(C8) -> 2025
B9: 59937.11 | C9: 45717 | D9: =DAY(C9) -> 1 | E9: =MONTH(C9) -> 3 | F9: =YEAR(C9) -> 2025
B10: 23910.58 | C10: 45748 | D10: =DAY(C10) -> 1 | E10: =MONTH(C10) -> 4 | F10: =YEAR(C10) -> 2025
B11: 33760.6 | C11: 45778 | D11: =DAY(C11) -> 1 | E11: =MONTH(C11) -> 5 | F11: =YEAR(C11) -> 2025
B12: 94931.8 | C12: 45809 | D12: =DAY(C12) -> 1 | E12: =MONTH(C12) -> 6 | F12: =YEAR(C12) -> 2025
B13: 66417.3 | C13: 45839 | D13: =DAY(C13) -> 1 | E13: =MONTH(C13) -> 7 | F13: =YEAR(C13) -> 2025
B14: 129400.54 | C14: 45870 | D14: =DAY(C14) -> 1 | E14: =MONTH(C14) -> 8 | F14: =YEAR(C14) -> 2025
... B26: -450027.08 | C26: 46235 | D26: =DAY(C26) -> 1 | E26: =MONTH(C26) -> 8 | F26: =YEAR(C26) -> 2026
D27: =DAY(C27) -> 30 | E27: =MONTH(C27) -> 12 | F27: =YEAR(C27) -> 1899
D28: =DAY(C28) -> 30 | E28: =MONTH(C28) -> 12 | F28: =YEAR(C28) -> 1899
D29: =DAY(C29) -> 30 | E29: =MONTH(C29) -> 12 | F29: =YEAR(C29) -> 1899
D30: =DAY(C30) -> 30 | E30: =MONTH(C30) -> 12 | F30: =YEAR(C30) -> 1899
D31: =DAY(C31) -> 30 | E31: =MONTH(C31) -> 12 | F31: =YEAR(C31) -> 1899
D32: =DAY(C32) -> 30 | E32: =MONTH(C32) -> 12 | F32: =YEAR(C32) -> 1899
D33: =DAY(C33) -> 30 | E33: =MONTH(C33) -> 12 | F33: =YEAR(C33) -> 1899
D34: =DAY(C34) -> 30 | E34: =MONTH(C34) -> 12 | F34: =YEAR(C34) -> 1899
D35: =DAY(C35) -> 30 | E35: =MONTH(C35) -> 12 | F35: =YEAR(C35) -> 1899
D36: =DAY(C36) -> 30 | E36: =MONTH(C36) -> 12 | F36: =YEAR(C36) -> 1899
D37: =DAY(C37) -> 30 | E37: =MONTH(C37) -> 12 | F37: =YEAR(C37) -> 1899
D38: =DAY(C38) -> 30 | E38: =MONTH(C38) -> 12 | F38: =YEAR(C38) -> 1899
... D1000: =DAY(C1000) -> 30 | E1000: =MONTH(C1000) -> 12 | F1000: =YEAR(C1000) -> 1899

Sheet SALDO DAS CONTAS
A1: CONTA | B1: DATA | C1: ITEM | D1: VALOR | E1: ANO | F1: MÊS | G1: DIA
A2: BANCO DO BRASIL - 65204-0 | B2: 45505 | C2: a-SALDO INICIAL | D2: 21460.86 | E2: =YEAR(B2) -> 2024 | F2: =MONTH(B2) -> 8 | G2: =DAY(B2) -> 1
A3: BANCO DO BRASIL - 65204-0 | B3: 45505 | C3: b-ENTRADAS | D3: =SUMIFS('Lançamentos de receitas'!$E:$E,'Lançamentos de receitas'!$A:$A,B3,'Lançamentos de receitas'!$C:$C,A3,'Lançamentos de receitas'!$F:$F,"TRANSFERÊNCIA") -> 6718.52 | E3: =YEAR(B3) -> 2024 | F3: =MONTH(B3) -> 8 | G3: =DAY(B3) -> 1
A4: BANCO DO BRASIL - 65204-0 | B4: 45505 | C4: c-SAÍDAS | D4: =SUMIFS('Lançamentos de despesas'!$K:$K,'Lançamentos de despesas'!$C:$C,B4,'Lançamentos de despesas'!$G:$G,A4,'Lançamentos de despesas'!$E:$E,"pago") -> 6000.63 | E4: =YEAR(B4) -> 2024 | F4: =MONTH(B4) -> 8 | G4: =DAY(B4) -> 1
A5: BANCO DO BRASIL - 65204-0 | B5: 45505 | C5: d-SALDO FINAL | D5: =D2+D3-D4 -> 22178.75 | E5: =YEAR(B5) -> 2024 | F5: =MONTH(B5) -> 8 | G5: =DAY(B5) -> 1
A6: BANCO DO BRASIL - 65204-0 | B6: 45506 | C6: a-SALDO INICIAL | D6: =D5 -> 22178.75 | E6: =YEAR(B6) -> 2024 | F6: =MONTH(B6) -> 8 | G6: =DAY(B6) -> 2
A7: BANCO DO BRASIL - 65204-0 | B7: 45506 | C7: b-ENTRADAS | D7: =SUMIFS('Lançamentos de receitas'!$E:$E,'Lançamentos de receitas'!$A:$A,B7,'Lançamentos de receitas'!$C:$C,A7,'Lançamentos de receitas'!$F:$F,"TRANSFERÊNCIA") -> 2499.56 | E7: =YEAR(B7) -> 2024 | F7: =MONTH(B7) -> 8 | G7: =DAY(B7) -> 2
A8: BANCO DO BRASIL - 65204-0 | B8: 45506 | C8: c-SAÍDAS | D8: =SUMIFS('Lançamentos de despesas'!$K:$K,'Lançamentos de despesas'!$C:$C,B8,'Lançamentos de despesas'!$G:$G,A8,'Lançamentos de despesas'!$E:$E,"pago") -> 7610 | E8: =YEAR(B8) -> 2024 | F8: =MONTH(B8) -> 8 | G8: =DAY(B8) -> 2
A9: BANCO DO BRASIL - 65204-0 | B9: 45506 | C9: d-SALDO FINAL | D9: =D6+D7-D8 -> 17068.31 | E9: =YEAR(B9) -> 2024 | F9: =MONTH(B9) -> 8 | G9: =DAY(B9) -> 2
A10: BANCO DO BRASIL - 65204-0 | B10: =B6+1 -> 45507 | C10: a-SALDO INICIAL | D10: =D9 -> 17068.31 | E10: =YEAR(B10) -> 2024 | F10: =MONTH(B10) -> 8 | G10: =DAY(B10) -> 3
A11: BANCO DO BRASIL - 65204-0 | B11: =B7+1 -> 45507 | C11: b-ENTRADAS | D11: =SUMIFS('Lançamentos de receitas'!$E:$E,'Lançamentos de receitas'!$A:$A,B11,'Lançamentos de receitas'!$C:$C,A11,'Lançamentos de receitas'!$F:$F,"TRANSFERÊNCIA") -> 3247.92 | E11: =YEAR(B11) -> 2024 | F11: =MONTH(B11) -> 8 | G11: =DAY(B11) -> 3
A12: BANCO DO BRASIL - 65204-0 | B12: =B8+1 -> 45507 | C12: c-SAÍDAS | D12: =SUMIFS('Lançamentos de despesas'!$K:$K,'Lançamentos de despesas'!$C:$C,B12,'Lançamentos de despesas'!$G:$G,A12,'Lançamentos de despesas'!$E:$E,"pago") -> 0 | E12: =YEAR(B12) -> 2024 | F12: =MONTH(B12) -> 8 | G12: =DAY(B12) -> 3
A13: BANCO DO BRASIL - 65204-0 | B13: =B9+1 -> 45507 | C13: d-SALDO FINAL | D13: =D10+D11-D12 -> 20316.23 | E13: =YEAR(B13) -> 2024 | F13: =MONTH(B13) -> 8 | G13: =DAY(B13) -> 3
A14: BANCO DO BRASIL - 65204-0 | B14: =B10+1 -> 45508 | C14: a-SALDO INICIAL | D14: =D13 -> 20316.23 | E14: =YEAR(B14) -> 2024 | F14: =MONTH(B14) -> 8 | G14: =DAY(B14) -> 4
A15: BANCO DO BRASIL - 65204-0 | B15: =B11+1 -> 45508 | C15: b-ENTRADAS | D15: =SUMIFS('Lançamentos de receitas'!$E:$E,'Lançamentos de receitas'!$A:$A,B15,'Lançamentos de receitas'!$C:$C,A15,'Lançamentos de receitas'!$F:$F,"TRANSFERÊNCIA") -> 1407.97 | E15: =YEAR(B15) -> 2024 | F15: =MONTH(B15) -> 8 | G15: =DAY(B15) -> 4
A16: BANCO DO BRASIL - 65204-0 | B16: =B12+1 -> 45508 | C16: c-SAÍDAS | D16: =SUMIFS('Lançamentos de despesas'!$K:$K,'Lançamentos de despesas'!$C:$C,B16,'Lançamentos de despesas'!$G:$G,A16,'Lançamentos de despesas'!$E:$E,"pago") -> 0 | E16: =YEAR(B16) -> 2024 | F16: =MONTH(B16) -> 8 | G16: =DAY(B16) -> 4
A17: BANCO DO BRASIL - 65204-0 | B17: =B13+1 -> 45508 | C17: d-SALDO FINAL | D17: =D14+D15-D16 -> 21724.2 | E17: =YEAR(B17) -> 2024 | F17: =MONTH(B17) -> 8 | G17: =DAY(B17) -> 4
A18: BANCO DO BRASIL - 65204-0 | B18: =B14+1 -> 45509 | C18: a-SALDO INICIAL | D18: =D17 -> 21724.2 | E18: =YEAR(B18) -> 2024 | F18: =MONTH(B18) -> 8 | G18: =DAY(B18) -> 5
A19: BANCO DO BRASIL - 65204-0 | B19: =B15+1 -> 45509 | C19: b-ENTRADAS | D19: =SUMIFS('Lançamentos de receitas'!$E:$E,'Lançamentos de receitas'!$A:$A,B19,'Lançamentos de receitas'!$C:$C,A19,'Lançamentos de receitas'!$F:$F,"TRANSFERÊNCIA") -> 626.33 | E19: =YEAR(B19) -> 2024 | F19: =MONTH(B19) -> 8 | G19: =DAY(B19) -> 5
A20: BANCO DO BRASIL - 65204-0 | B20: =B16+1 -> 45509 | C20: c-SAÍDAS | D20: =SUMIFS('Lançamentos de despesas'!$K:$K,'Lançamentos de despesas'!$C:$C,B20,'Lançamentos de despesas'!$G:$G,A20,'Lançamentos de despesas'!$E:$E,"pago") -> 222.66 | E20: =YEAR(B20) -> 2024 | F20: =MONTH(B20) -> 8 | G20: =DAY(B20) -> 5
A21: BANCO DO BRASIL - 65204-0 | B21: =B17+1 -> 45509 | C21: d-SALDO FINAL | D21: =D18+D19-D20 -> 22127.87 | E21: =YEAR(B21) -> 2024 | F21: =MONTH(B21) -> 8 | G21: =DAY(B21) -> 5
A22: BANCO DO BRASIL - 65204-0 | B22: =B18+1 -> 45510 | C22: a-SALDO INICIAL | D22: =D21 -> 22127.87 | E22: =YEAR(B22) -> 2024 | F22: =MONTH(B22) -> 8 | G22: =DAY(B22) -> 6
A23: BANCO DO BRASIL - 65204-0 | B23: =B19+1 -> 45510 | C23: b-ENTRADAS | D23: =SUMIFS('Lançamentos de receitas'!$E:$E,'Lançamentos de receitas'!$A:$A,B23,'Lançamentos de receitas'!$C:$C,A23,'Lançamentos de receitas'!$F:$F,"TRANSFERÊNCIA") -> 38637.57 | E23: =YEAR(B23) -> 2024 | F23: =MONTH(B23) -> 8 | G23: =DAY(B23) -> 6
A24: BANCO DO BRASIL - 65204-0 | B24: =B20+1 -> 45510 | C24: c-SAÍDAS | D24: =SUMIFS('Lançamentos de despesas'!$K:$K,'Lançamentos de despesas'!$C:$C,B24,'Lançamentos de despesas'!$G:$G,A24,'Lançamentos de despesas'!$E:$E,"pago") -> 2573.8 | E24: =YEAR(B24) -> 2024 | F24: =MONTH(B24) -> 8 | G24: =DAY(B24) -> 6
A25: BANCO DO BRASIL - 65204-0 | B25: =B21+1 -> 45510 | C25: d-SALDO FINAL | D25: =D22+D23-D24 -> 58191.64 | E25: =YEAR(B25) -> 2024 | F25: =MONTH(B25) -> 8 | G25: =DAY(B25) -> 6
A26: BANCO DO BRASIL - 65204-0 | B26: =B22+1 -> 45511 | C26: a-SALDO INICIAL | D26: =D25 -> 58191.64 | E26: =YEAR(B26) -> 2024 | F26: =MONTH(B26) -> 8 | G26: =DAY(B26) -> 7
A27: BANCO DO BRASIL - 65204-0 | B27: =B23+1 -> 45511 | C27: b-ENTRADAS | D27: =SUMIFS('Lançamentos de receitas'!$E:$E,'Lançamentos de receitas'!$A:$A,B27,'Lançamentos de receitas'!$C:$C,A27,'Lançamentos de receitas'!$F:$F,"TRANSFERÊNCIA") -> 2090.04 | E27: =YEAR(B27) -> 2024 | F27: =MONTH(B27) -> 8 | G27: =DAY(B27) -> 7
A28: BANCO DO BRASIL - 65204-0 | B28: =B24+1 -> 45511 | C28: c-SAÍDAS | D28: =SUMIFS('Lançamentos de despesas'!$K:$K,'Lançamentos de despesas'!$C:$C,B28,'Lançamentos de despesas'!$G:$G,A28,'Lançamentos de despesas'!$E:$E,"pago") -> 0 | E28: =YEAR(B28) -> 2024 | F28: =MONTH(B28) -> 8 | G28: =DAY(B28) -> 7
A29: BANCO DO BRASIL - 65204-0 | B29: =B25+1 -> 45511 | C29: d-SALDO FINAL | D29: =D26+D27-D28 -> 60281.68 | E29: =YEAR(B29) -> 2024 | F29: =MONTH(B29) -> 8 | G29: =DAY(B29) -> 7
A30: BANCO DO BRASIL - 65204-0 | B30: =B26+1 -> 45512 | C30: a-SALDO INICIAL | D30: =D29 -> 60281.68 | E30: =YEAR(B30) -> 2024 | F30: =MONTH(B30) -> 8 | G30: =DAY(B30) -> 8
A31: BANCO DO BRASIL - 65204-0 | B31: =B27+1 -> 45512 | C31: b-ENTRADAS | D31: =SUMIFS('Lançamentos de receitas'!$E:$E,'Lançamentos de receitas'!$A:$A,B31,'Lançamentos de receitas'!$C:$C,A31,'Lançamentos de receitas'!$F:$F,"TRANSFERÊNCIA") -> 2594.3 | E31: =YEAR(B31) -> 2024 | F31: =MONTH(B31) -> 8 | G31: =DAY(B31) -> 8
A32: BANCO DO BRASIL - 65204-0 | B32: =B28+1 -> 45512 | C32: c-SAÍDAS | D32: =SUMIFS('Lançamentos de despesas'!$K:$K,'Lançamentos de despesas'!$C:$C,B32,'Lançamentos de despesas'!$G:$G,A32,'Lançamentos de despesas'!$E:$E,"pago") -> 0 | E32: =YEAR(B32) -> 2024 | F32: =MONTH(B32) -> 8 | G32: =DAY(B32) -> 8
A33: BANCO DO BRASIL - 65204-0 | B33: =B29+1 -> 45512 | C33: d-SALDO FINAL | D33: =D30+D31-D32 -> 62875.98 | E33: =YEAR(B33) -> 2024 | F33: =MONTH(B33) -> 8 | G33: =DAY(B33) -> 8
A34: BANCO DO BRASIL - 65204-0 | B34: =B30+1 -> 45513 | C34: a-SALDO INICIAL | D34: =D33 -> 62875.98 | E34: =YEAR(B34) -> 2024 | F34: =MONTH(B34) -> 8 | G34: =DAY(B34) -> 9
A35: BANCO DO BRASIL - 65204-0 | B35: =B31+1 -> 45513 | C35: b-ENTRADAS | D35: =SUMIFS('Lançamentos de receitas'!$E:$E,'Lançamentos de receitas'!$A:$A,B35,'Lançamentos de receitas'!$C:$C,A35,'Lançamentos de receitas'!$F:$F,"TRANSFERÊNCIA") -> 1963.96 | E35: =YEAR(B35) -> 2024 | F35: =MONTH(B35) -> 8 | G35: =DAY(B35) -> 9
A36: BANCO DO BRASIL - 65204-0 | B36: =B32+1 -> 45513 | C36: c-SAÍDAS | D36: =SUMIFS('Lançamentos de despesas'!$K:$K,'Lançamentos de despesas'!$C:$C,B36,'Lançamentos de despesas'!$G:$G,A36,'Lançamentos de despesas'!$E:$E,"pago") -> 0 | E36: =YEAR(B36) -> 2024 | F36: =MONTH(B36) -> 8 | G36: =DAY(B36) -> 9
A37: BANCO DO BRASIL - 65204-0 | B37: =B33+1 -> 45513 | C37: d-SALDO FINAL | D37: =D34+D35-D36 -> 64839.94 | E37: =YEAR(B37) -> 2024 | F37: =MONTH(B37) -> 8 | G37: =DAY(B37) -> 9
A38: BANCO DO BRASIL - 65204-0 | B38: =B34+1 -> 45514 | C38: a-SALDO INICIAL | D38: =D37 -> 64839.94 | E38: =YEAR(B38) -> 2024 | F38: =MONTH(B38) -> 8 | G38: =DAY(B38) -> 10
A39: BANCO DO BRASIL - 65204-0 | B39: =B35+1 -> 45514 | C39: b-ENTRADAS | D39: =SUMIFS('Lançamentos de receitas'!$E:$E,'Lançamentos de receitas'!$A:$A,B39,'Lançamentos de receitas'!$C:$C,A39,'Lançamentos de receitas'!$F:$F,"TRANSFERÊNCIA") -> 1731.53 | E39: =YEAR(B39) -> 2024 | F39: =MONTH(B39) -> 8 | G39: =DAY(B39) -> 10
A40: BANCO DO BRASIL - 65204-0 | B40: =B36+1 -> 45514 | C40: c-SAÍDAS | D40: =SUMIFS('Lançamentos de despesas'!$K:$K,'Lançamentos de despesas'!$C:$C,B40,'Lançamentos de despesas'!$G:$G,A40,'Lançamentos de despesas'!$E:$E,"pago") -> 0 | E40: =YEAR(B40) -> 2024 | F40: =MONTH(B40) -> 8 | G40: =DAY(B40) -> 10
A41: BANCO DO BRASIL - 65204-0 | B41: =B37+1 -> 45514 | C41: d-SALDO FINAL | D41: =D38+D39-D40 -> 66571.47 | E41: =YEAR(B41) -> 2024 | F41: =MONTH(B41) -> 8 | G41: =DAY(B41) -> 10
A42: BANCO DO BRASIL - 65204-0 | B42: =B38+1 -> 45515 | C42: a-SALDO INICIAL | D42: =D41 -> 66571.47 | E42: =YEAR(B42) -> 2024 | F42: =MONTH(B42) -> 8 | G42: =DAY(B42) -> 11
A43: BANCO DO BRASIL - 65204-0 | B43: =B39+1 -> 45515 | C43: b-ENTRADAS | D43: =SUMIFS('Lançamentos de receitas'!$E:$E,'Lançamentos de receitas'!$A:$A,B43,'Lançamentos de receitas'!$C:$C,A43,'Lançamentos de receitas'!$F:$F,"TRANSFERÊNCIA") -> 591.01 | E43: =YEAR(B43) -> 2024 | F43: =MONTH(B43) -> 8 | G43: =DAY(B43) -> 11
A44: BANCO DO BRASIL - 65204-0 | B44: =B40+1 -> 45515 | C44: c-SAÍDAS | D44: =SUMIFS('Lançamentos de despesas'!$K:$K,'Lançamentos de despesas'!$C:$C,B44,'Lançamentos de despesas'!$G:$G,A44,'Lançamentos de despesas'!$E:$E,"pago") -> 0 | E44: =YEAR(B44) -> 2024 | F44: =MONTH(B44) -> 8 | G44: =DAY(B44) -> 11
A45: BANCO DO BRASIL - 65204-0 | B45: =B41+1 -> 45515 | C45: d-SALDO FINAL | D45: =D42+D43-D44 -> 67162.48 | E45: =YEAR(B45) -> 2024 | F45: =MONTH(B45) -> 8 | G45: =DAY(B45) -> 11
A46: BANCO DO BRASIL - 65204-0 | B46: =B42+1 -> 45516 | C46: a-SALDO INICIAL | D46: =D45 -> 67162.48 | E46: =YEAR(B46) -> 2024 | F46: =MONTH(B46) -> 8 | G46: =DAY(B46) -> 12
A47: BANCO DO BRASIL - 65204-0 | B47: =B43+1 -> 45516 | C47: b-ENTRADAS | D47: =SUMIFS('Lançamentos de receitas'!$E:$E,'Lançamentos de receitas'!$A:$A,B47,'Lançamentos de receitas'!$C:$C,A47,'Lançamentos de receitas'!$F:$F,"TRANSFERÊNCIA") -> 31125.84 | E47: =YEAR(B47) -> 2024 | F47: =MONTH(B47) -> 8 | G47: =DAY(B47) -> 12
A48: BANCO DO BRASIL - 65204-0 | B48: =B44+1 -> 45516 | C48: c-SAÍDAS | D48: =SUMIFS('Lançamentos de despesas'!$K:$K,'Lançamentos de despesas'!$C:$C,B48,'Lançamentos de despesas'!$G:$G,A48,'Lançamentos de despesas'!$E:$E,"pago") -> 5539.13 | E48: =YEAR(B48) -> 2024 | F48: =MONTH(B48) -> 8 | G48: =DAY(B48) -> 12
A49: BANCO DO BRASIL - 65204-0 | B49: =B45+1 -> 45516 | C49: d-SALDO FINAL | D49: =D46+D47-D48 -> 92749.19 | E49: =YEAR(B49) -> 2024 | F49: =MONTH(B49) -> 8 | G49: =DAY(B49) -> 12
A50: BANCO DO BRASIL - 65204-0 | B50: =B46+1 -> 45517 | C50: a-SALDO INICIAL | D50: =D49 -> 92749.19 | E50: =YEAR(B50) -> 2024 | F50: =MONTH(B50) -> 8 | G50: =DAY(B50) -> 13
A51: BANCO DO BRASIL - 65204-0 | B51: =B47+1 -> 45517 | C51: b-ENTRADAS | D51: =SUMIFS('Lançamentos de receitas'!$E:$E,'Lançamentos de receitas'!$A:$A,B51,'Lançamentos de receitas'!$C:$C,A51,'Lançamentos de receitas'!$F:$F,"TRANSFERÊNCIA") -> 2080.36 | E51: =YEAR(B51) -> 2024 | F51: =MONTH(B51) -> 8 | G51: =DAY(B51) -> 13
A52: BANCO DO BRASIL - 65204-0 | B52: =B48+1 -> 45517 | C52: c-SAÍDAS | D52: =SUMIFS('Lançamentos de despesas'!$K:$K,'Lançamentos de despesas'!$C:$C,B52,'Lançamentos de despesas'!$G:$G,A52,'Lançamentos de despesas'!$E:$E,"pago") -> 0 | E52: =YEAR(B52) -> 2024 | F52: =MONTH(B52) -> 8 | G52: =DAY(B52) -> 13
A53: BANCO DO BRASIL - 65204-0 | B53: =B49+1 -> 45517 | C53: d-SALDO FINAL | D53: =D50+D51-D52 -> 94829.55 | E53: =YEAR(B53) -> 2024 | F53: =MONTH(B53) -> 8 | G53: =DAY(B53) -> 13
A54: BANCO DO BRASIL - 65204-0 | B54: =B50+1 -> 45518 | C54: a-SALDO INICIAL | D54: =D53 -> 94829.55 | E54: =YEAR(B54) -> 2024 | F54: =MONTH(B54) -> 8 | G54: =DAY(B54) -> 14
A55: BANCO DO BRASIL - 65204-0 | B55: =B51+1 -> 45518 | C55: b-ENTRADAS | D55: =SUMIFS('Lançamentos de receitas'!$E:$E,'Lançamentos de receitas'!$A:$A,B55,'Lançamentos de receitas'!$C:$C,A55,'Lançamentos de receitas'!$F:$F,"TRANSFERÊNCIA") -> 2971.71 | E55: =YEAR(B55) -> 2024 | F55: =MONTH(B55) -> 8 | G55: =DAY(B55) -> 14
A56: BANCO DO BRASIL - 65204-0 | B56: =B52+1 -> 45518 | C56: c-SAÍDAS | D56: =SUMIFS('Lançamentos de despesas'!$K:$K,'Lançamentos de despesas'!$C:$C,B56,'Lançamentos de despesas'!$G:$G,A56,'Lançamentos de despesas'!$E:$E,"pago") -> 2786.78 | E56: =YEAR(B56) -> 2024 | F56: =MONTH(B56) -> 8 | G56: =DAY(B56) -> 14
A57: BANCO DO BRASIL - 65204-0 | B57: =B53+1 -> 45518 | C57: d-SALDO FINAL | D57: =D54+D55-D56 -> 95014.48 | E57: =YEAR(B57) -> 2024 | F57: =MONTH(B57) -> 8 | G57: =DAY(B57) -> 14
A58: BANCO DO BRASIL - 65204-0 | B58: =B54+1 -> 45519 | C58: a-SALDO INICIAL | D58: =D57 -> 95014.48 | E58: =YEAR(B58) -> 2024 | F58: =MONTH(B58) -> 8 | G58: =DAY(B58) -> 15
A59: BANCO DO BRASIL - 65204-0 | B59: =B55+1 -> 45519 | C59: b-ENTRADAS | D59: =SUMIFS('Lançamentos de receitas'!$E:$E,'Lançamentos de receitas'!$A:$A,B59,'Lançamentos de receitas'!$C:$C,A59,'Lançamentos de receitas'!$F:$F,"TRANSFERÊNCIA") -> 3891.85 | E59: =YEAR(B59) -> 2024 | F59: =MONTH(B59) -> 8 | G59: =DAY(B59) -> 15
A60: BANCO DO BRASIL - 65204-0 | B60: =B56+1 -> 45519 | C60: c-SAÍDAS | D60: =SUMIFS('Lançamentos de despesas'!$K:$K,'Lançamentos de despesas'!$C:$C,B60,'Lançamentos de despesas'!$G:$G,A60,'Lançamentos de despesas'!$E:$E,"pago") -> 3988 | E60: =YEAR(B60) -> 2024 | F60: =MONTH(B60) -> 8 | G60: =DAY(B60) -> 15
A61: BANCO DO BRASIL - 65204-0 | B61: =B57+1 -> 45519 | C61: d-SALDO FINAL | D61: =D58+D59-D60 -> 94918.33 | E61: =YEAR(B61) -> 2024 | F61: =MONTH(B61) -> 8 | G61: =DAY(B61) -> 15
A62: BANCO DO BRASIL - 65204-0 | B62: =B58+1 -> 45520 | C62: a-SALDO INICIAL | D62: =D61 -> 94918.33 | E62: =YEAR(B62) -> 2024 | F62: =MONTH(B62) -> 8 | G62: =DAY(B62) -> 16
A63: BANCO DO BRASIL - 65204-0 | B63: =B59+1 -> 45520 | C63: b-ENTRADAS | D63: =SUMIFS('Lançamentos de receitas'!$E:$E,'Lançamentos de receitas'!$A:$A,B63,'Lançamentos de receitas'!$C:$C,A63,'Lançamentos de receitas'!$F:$F,"TRANSFERÊNCIA") -> 2250.23 | E63: =YEAR(B63) -> 2024 | F63: =MONTH(B63) -> 8 | G63: =DAY(B63) -> 16
A64: BANCO DO BRASIL - 65204-0 | B64: =B60+1 -> 45520 | C64: c-SAÍDAS | D64: =SUMIFS('Lançamentos de despesas'!$K:$K,'Lançamentos de despesas'!$C:$C,B64,'Lançamentos de despesas'!$G:$G,A64,'Lançamentos de despesas'!$E:$E,"pago") -> 3042.66 | E64: =YEAR(B64) -> 2024 | F64: =MONTH(B64) -> 8 | G64: =DAY(B64) -> 16
A65: BANCO DO BRASIL - 65204-0 | B65: =B61+1 -> 45520 | C65: d-SALDO FINAL | D65: =D62+D63-D64 -> 94125.9 | E65: =YEAR(B65) -> 2024 | F65: =MONTH(B65) -> 8 | G65: =DAY(B65) -> 16
A66: BANCO DO BRASIL - 65204-0 | B66: =B62+1 -> 45521 | C66: a-SALDO INICIAL | D66: =D65 -> 94125.9 | E66: =YEAR(B66) -> 2024 | F66: =MONTH(B66) -> 8 | G66: =DAY(B66) -> 17
A67: BANCO DO BRASIL - 65204-0 | B67: =B63+1 -> 45521 | C67: b-ENTRADAS | D67: =SUMIFS('Lançamentos de receitas'!$E:$E,'Lançamentos de receitas'!$A:$A,B67,'Lançamentos de receitas'!$C:$C,A67,'Lançamentos de receitas'!$F:$F,"TRANSFERÊNCIA") -> 3321.6 | E67: =YEAR(B67) -> 2024 | F67: =MONTH(B67) -> 8 | G67: =DAY(B67) -> 17
A68: BANCO DO BRASIL - 65204-0 | B68: =B64+1 -> 45521 | C68: c-SAÍDAS | D68: =SUMIFS('Lançamentos de despesas'!$K:$K,'Lançamentos de despesas'!$C:$C,B68,'Lançamentos de despesas'!$G:$G,A68,'Lançamentos de despesas'!$E:$E,"pago") -> 0 | E68: =YEAR(B68) -> 2024 | F68: =MONTH(B68) -> 8 | G68: =DAY(B68) -> 17
A69: BANCO DO BRASIL - 65204-0 | B69: =B65+1 -> 45521 | C69: d-SALDO FINAL | D69: =D66+D67-D68 -> 97447.5 | E69: =YEAR(B69) -> 2024 | F69: =MONTH(B69) -> 8 | G69: =DAY(B69) -> 17
A70: BANCO DO BRASIL - 65204-0 | B70: =B66+1 -> 45522 | C70: a-SALDO INICIAL | D70: =D69 -> 97447.5 | E70: =YEAR(B70) -> 2024 | F70: =MONTH(B70) -> 8 | G70: =DAY(B70) -> 18
A71: BANCO DO BRASIL - 65204-0 | B71: =B67+1 -> 45522 | C71: b-ENTRADAS | D71: =SUMIFS('Lançamentos de receitas'!$E:$E,'Lançamentos de receitas'!$A:$A,B71,'Lançamentos de receitas'!$C:$C,A71,'Lançamentos de receitas'!$F:$F,"TRANSFERÊNCIA") -> 1763.25 | E71: =YEAR(B71) -> 2024 | F71: =MONTH(B71) -> 8 | G71: =DAY(B71) -> 18
A72: BANCO DO BRASIL - 65204-0 | B72: =B68+1 -> 45522 | C72: c-SAÍDAS | D72: =SUMIFS('Lançamentos de despesas'!$K:$K,'Lançamentos de despesas'!$C:$C,B72,'Lançamentos de despesas'!$G:$G,A72,'Lançamentos de despesas'!$E:$E,"pago") -> 0 | E72: =YEAR(B72) -> 2024 | F72: =MONTH(B72) -> 8 | G72: =DAY(B72) -> 18
A73: BANCO DO BRASIL - 65204-0 | B73: =B69+1 -> 45522 | C73: d-SALDO FINAL | D73: =D70+D71-D72 -> 99210.75 | E73: =YEAR(B73) -> 2024 | F73: =MONTH(B73) -> 8 | G73: =DAY(B73) -> 18
A74: BANCO DO BRASIL - 65204-0 | B74: =B70+1 -> 45523 | C74: a-SALDO INICIAL | D74: =D73 -> 99210.75 | E74: =YEAR(B74) -> 2024 | F74: =MONTH(B74) -> 8 | G74: =DAY(B74) -> 19
A75: BANCO DO BRASIL - 65204-0 | B75: =B71+1 -> 45523 | C75: b-ENTRADAS | D75: =SUMIFS('Lançamentos de receitas'!$E:$E,'Lançamentos de receitas'!$A:$A,B75,'Lançamentos de receitas'!$C:$C,A75,'Lançamentos de receitas'!$F:$F,"TRANSFERÊNCIA") -> 538.9 | E75: =YEAR(B75) -> 2024 | F75: =MONTH(B75) -> 8 | G75: =DAY(B75) -> 19
A76: BANCO DO BRASIL - 65204-0 | B76: =B72+1 -> 45523 | C76: c-SAÍDAS | D76: =SUMIFS('Lançamentos de despesas'!$K:$K,'Lançamentos de despesas'!$C:$C,B76,'Lançamentos de despesas'!$G:$G,A76,'Lançamentos de despesas'!$E:$E,"pago") -> 3511.72 | E76: =YEAR(B76) -> 2024 | F76: =MONTH(B76) -> 8 | G76: =DAY(B76) -> 19
A77: BANCO DO BRASIL - 65204-0 | B77: =B73+1 -> 45523 | C77: d-SALDO FINAL | D77: =D74+D75-D76 -> 96237.93 | E77: =YEAR(B77) -> 2024 | F77: =MONTH(B77) -> 8 | G77: =DAY(B77) -> 19
A78: BANCO DO BRASIL - 65204-0 | B78: =B74+1 -> 45524 | C78: a-SALDO INICIAL | D78: =D77 -> 96237.93 | E78: =YEAR(B78) -> 2024 | F78: =MONTH(B78) -> 8 | G78: =DAY(B78) -> 20
A79: BANCO DO BRASIL - 65204-0 | B79: =B75+1 -> 45524 | C79: b-ENTRADAS | D79: =SUMIFS('Lançamentos de receitas'!$E:$E,'Lançamentos de receitas'!$A:$A,B79,'Lançamentos de receitas'!$C:$C,A79,'Lançamentos de receitas'!$F:$F,"TRANSFERÊNCIA") -> 2125.62 | E79: =YEAR(B79) -> 2024 | F79: =MONTH(B79) -> 8 | G79: =DAY(B79) -> 20
A80: BANCO DO BRASIL - 65204-0 | B80: =B76+1 -> 45524 | C80: c-SAÍDAS | D80: =SUMIFS('Lançamentos de despesas'!$K:$K,'Lançamentos de despesas'!$C:$C,B80,'Lançamentos de despesas'!$G:$G,A80,'Lançamentos de despesas'!$E:$E,"pago") -> 28336.451 | E80: =YEAR(B80) -> 2024 | F80: =MONTH(B80) -> 8 | G80: =DAY(B80) -> 20
A81: BANCO DO BRASIL - 65204-0 | B81: =B77+1 -> 45524 | C81: d-SALDO FINAL | D81: =D78+D79-D80 -> 70027.099 | E81: =YEAR(B81) -> 2024 | F81: =MONTH(B81) -> 8 | G81: =DAY(B81) -> 20
A82: BANCO DO BRASIL - 65204-0 | B82: =B78+1 -> 45525 | C82: a-SALDO INICIAL | D82: =D81 -> 70027.099 | E82: =YEAR(B82) -> 2024 | F82: =MONTH(B82) -> 8 | G82: =DAY(B82) -> 21
A83: BANCO DO BRASIL - 65204-0 | B83: =B79+1 -> 45525 | C83: b-ENTRADAS | D83: =SUMIFS('Lançamentos de receitas'!$E:$E,'Lançamentos de receitas'!$A:$A,B83,'Lançamentos de receitas'!$C:$C,A83,'Lançamentos de receitas'!$F:$F,"TRANSFERÊNCIA") -> 3550.19 | E83: =YEAR(B83) -> 2024 | F83: =MONTH(B83) -> 8 | G83: =DAY(B83) -> 21
A84: BANCO DO BRASIL - 65204-0 | B84: =B80+1 -> 45525 | C84: c-SAÍDAS | D84: =SUMIFS('Lançamentos de despesas'!$K:$K,'Lançamentos de despesas'!$C:$C,B84,'Lançamentos de despesas'!$G:$G,A84,'Lançamentos de despesas'!$E:$E,"pago") -> 0 | E84: =YEAR(B84) -> 2024 | F84: =MONTH(B84) -> 8 | G84: =DAY(B84) -> 21
A85: BANCO DO BRASIL - 65204-0 | B85: =B81+1 -> 45525 | C85: d-SALDO FINAL | D85: =D82+D83-D84 -> 73577.289 | E85: =YEAR(B85) -> 2024 | F85: =MONTH(B85) -> 8 | G85: =DAY(B85) -> 21
A86: BANCO DO BRASIL - 65204-0 | B86: =B82+1 -> 45526 | C86: a-SALDO INICIAL | D86: =D85 -> 73577.289 | E86: =YEAR(B86) -> 2024 | F86: =MONTH(B86) -> 8 | G86: =DAY(B86) -> 22
A87: BANCO DO BRASIL - 65204-0 | B87: =B83+1 -> 45526 | C87: b-ENTRADAS | D87: =SUMIFS('Lançamentos de receitas'!$E:$E,'Lançamentos de receitas'!$A:$A,B87,'Lançamentos de receitas'!$C:$C,A87,'Lançamentos de receitas'!$F:$F,"TRANSFERÊNCIA") -> 2101.14 | E87: =YEAR(B87) -> 2024 | F87: =MONTH(B87) -> 8 | G87: =DAY(B87) -> 22
A88: BANCO DO BRASIL - 65204-0 | B88: =B84+1 -> 45526 | C88: c-SAÍDAS | D88: =SUMIFS('Lançamentos de despesas'!$K:$K,'Lançamentos de despesas'!$C:$C,B88,'Lançamentos de despesas'!$G:$G,A88,'Lançamentos de despesas'!$E:$E,"pago") -> 1449.25 | E88: =YEAR(B88) -> 2024 | F88: =MONTH(B88) -> 8 | G88: =DAY(B88) -> 22
A89: BANCO DO BRASIL - 65204-0 | B89: =B85+1 -> 45526 | C89: d-SALDO FINAL | D89: =D86+D87-D88 -> 74229.179 | E89: =YEAR(B89) -> 2024 | F89: =MONTH(B89) -> 8 | G89: =DAY(B89) -> 22
A90: BANCO DO BRASIL - 65204-0 | B90: =B86+1 -> 45527 | C90: a-SALDO INICIAL | D90: =D89 -> 74229.179 | E90: =YEAR(B90) -> 2024 | F90: =MONTH(B90) -> 8 | G90: =DAY(B90) -> 23
A91: BANCO DO BRASIL - 65204-0 | B91: =B87+1 -> 45527 | C91: b-ENTRADAS | D91: =SUMIFS('Lançamentos de receitas'!$E:$E,'Lançamentos de receitas'!$A:$A,B91,'Lançamentos de receitas'!$C:$C,A91,'Lançamentos de receitas'!$F:$F,"TRANSFERÊNCIA") -> 8109.02 | E91: =YEAR(B91) -> 2024 | F91: =MONTH(B91) -> 8 | G91: =DAY(B91) -> 23
A92: BANCO DO BRASIL - 65204-0 | B92: =B88+1 -> 45527 | C92: c-SAÍDAS | D92: =SUMIFS('Lançamentos de despesas'!$K:$K,'Lançamentos de despesas'!$C:$C,B92,'Lançamentos de despesas'!$G:$G,A92,'Lançamentos de despesas'!$E:$E,"pago") -> 10 | E92: =YEAR(B92) -> 2024 | F92: =MONTH(B92) -> 8 | G92: =DAY(B92) -> 23
A93: BANCO DO BRASIL - 65204-0 | B93: =B89+1 -> 45527 | C93: d-SALDO FINAL | D93: =D90+D91-D92 -> 82328.199 | E93: =YEAR(B93) -> 2024 | F93: =MONTH(B93) -> 8 | G93: =DAY(B93) -> 23
A94: BANCO DO BRASIL - 65204-0 | B94: =B90+1 -> 45528 | C94: a-SALDO INICIAL | D94: =D93 -> 82328.199 | E94: =YEAR(B94) -> 2024 | F94: =MONTH(B94) -> 8 | G94: =DAY(B94) -> 24
A95: BANCO DO BRASIL - 65204-0 | B95: =B91+1 -> 45528 | C95: b-ENTRADAS | D95: =SUMIFS('Lançamentos de receitas'!$E:$E,'Lançamentos de receitas'!$A:$A,B95,'Lançamentos de receitas'!$C:$C,A95,'Lançamentos de receitas'!$F:$F,"TRANSFERÊNCIA") -> 1962.3 | E95: =YEAR(B95) -> 2024 | F95: =MONTH(B95) -> 8 | G95: =DAY(B95) -> 24
A96: BANCO DO BRASIL - 65204-0 | B96: =B92+1 -> 45528 | C96: c-SAÍDAS | D96: =SUMIFS('Lançamentos de despesas'!$K:$K,'Lançamentos de despesas'!$C:$C,B96,'Lançamentos de despesas'!$G:$G,A96,'Lançamentos de despesas'!$E:$E,"pago") -> 0 | E96: =YEAR(B96) -> 2024 | F96: =MONTH(B96) -> 8 | G96: =DAY(B96) -> 24
A97: BANCO DO BRASIL - 65204-0 | B97: =B93+1 -> 45528 | C97: d-SALDO FINAL | D97: =D94+D95-D96 -> 84290.499 | E97: =YEAR(B97) -> 2024 | F97: =MONTH(B97) -> 8 | G97: =DAY(B97) -> 24
A98: BANCO DO BRASIL - 65204-0 | B98: =B94+1 -> 45529 | C98: a-SALDO INICIAL | D98: =D97 -> 84290.499 | E98: =YEAR(B98) -> 2024 | F98: =MONTH(B98) -> 8 | G98: =DAY(B98) -> 25
A99: BANCO DO BRASIL - 65204-0 | B99: =B95+1 -> 45529 | C99: b-ENTRADAS | D99: =SUMIFS('Lançamentos de receitas'!$E:$E,'Lançamentos de receitas'!$A:$A,B99,'Lançamentos de receitas'!$C:$C,A99,'Lançamentos de receitas'!$F:$F,"TRANSFERÊNCIA") -> 1911.01 | E99: =YEAR(B99) -> 2024 | F99: =MONTH(B99) -> 8 | G99: =DAY(B99) -> 25
A100: BANCO DO BRASIL - 65204-0 | B100: =B96+1 -> 45529 | C100: c-SAÍDAS | D100: =SUMIFS('Lançamentos de despesas'!$K:$K,'Lançamentos de despesas'!$C:$C,B100,'Lançamentos de despesas'!$G:$G,A100,'Lançamentos de despesas'!$E:$E,"pago") -> 0 | E100: =YEAR(B100) -> 2024 | F100: =MONTH(B100) -> 8 | G100: =DAY(B100) -> 25
...

Sheet Balanço 
A1: DATA
A3: ATIVO | B3: =B4+B13 -> 0 | C3: Passivo | D3: =D4+D8 -> 0
A4: Ativo circulante | C4: Passivo circulante
A5: Caixas e bancos | C5: Empréstimo e financiamentos
A6: conta 1 | C6: Fornecedores
A7: conta 2 | C7: Outras obrigações
A8: Aplicações financeiras | C8: Passivo Não circulante
A9: Contas a receber de clientes | C9: Empréstimo e financiamentos
A10: Estoques | C10: Outras obrigações
A11: Impostos a recuperar | C11: Patrimônio Liquido | D11: =SUM(D12:D19) -> 0
A12: Outros créditos | C12: Capital social
A13: Ativo Não circulante | C13: Reserva de capital
A14: Realizável a longo prazo | C14: Reservas de lucros
A15: Aplicações financeiras | C15: Reserva de incentivos fiscais
A16: Contas a receber de clientes | C16: Outros resultados abrangentes
A17: Impostos de renda e contribuição social deferidos | C17: Lucros acumulados
A18: Outros créditos | C18: Dividendos adicionais propostos
A19: Propriedade para investimento
A20: Imobilizado
A21: Intangível

Sheet CADASTROS DE FORNECEDORES
A1: FORNECEDOR | B1: CNPJ/CPF | C1: TELEFONE | D1: E-MAIL
A2: MERCADO LIVRE
A3: Flaneg Embalagens | B3: 20.959.125/0001-50
A4: DRE ASSESSORIA CONTÁBIL EIRELI | B4: 20.951.799/0001-09 | C4: (11) 98854-9921 | D4: fiscal@drecontabil.com.br
A5: DONGGUAN LOYAL INDUSTRIAL CO., LTD. | C5: 0086-13926823
A6: DHL EXPRESS BRASIL | B6: 58.890.252/0028-33 | C6: (15) 99131-4832
A7: BL IMPRESSORAS | B7: 45.879.238/0001-77 | C7: (19) 99143-6789 | D7: financeiro.blcartuchos@gmail.com
A8: Erick Renato Rufino hernandes -Marketing | B8: 344.111.158-32 | C8: (19) 92000-5775
A9: FLS Embalagens e Mats de Limpeza | B9: 31.247.350/0001-80 | C9: (11) 97632-2898
A10: MARCELO ANTONIO KUHL - MPK TRICOT | B10: 14.553.678/0001-06 | C10: (19) 93824-1500
A11: Regina Celia Moura de Oliveira - Barbara Bolsas | B11: 38.405.665/0001-58 | C11: (11) 99625-1596 | D11: barbarabolsasecia@gmail.com
A12: Royal Agenciamentos de Cargas Ltda | B12: 17.050.532/0001-36 | D12: k.godoy@royalcargo.com.br
A13: Casa das Embalagens e Limpeza Ltda | B13: 02.805.507/0002-29
A14: Duas Cerejas - Bolos
A15: Bazar 10
A16: DSC SOURCING CO., LTD
A17: LARISSA FARINCHON BORGES | B17: 33126324800 | C17: 19991426854 | D17: larissa.farinchon@farmelimport.com.br
A18: ELAINE CRISTINA DE MELO | B18: 260.577.858-43 | C18: 19983170220 | D18: elaine.melo@farmelimport.com.br
A19: Debora Morales de Melo | B19: 316.421.728-55 | C19: 11986825521 | D19: adm@farmelimport.com.br
A20: ADRIANE CRISTINA GOMES
A21: THIAGO MAURICIO BERTI | B21: 362.204.548-55 | C21: 19920031058
A22: Priscila Zaghi Da Silva | B22: 322.180.128-98 | C22: 1998285-0064
A23: ADELINO ALVES - ALUGUEL GALPÃO
A24: BANCO DO BRASIL
A25: RIVER FREIGHT LOGISTICS SERVICES | B25: 05.850.330/0001-90 | C25: (21) 2253-5791 | D25: fabio@riverfreight.com.br
A26: TOKIO MARINE SEGURADORA S.A. - SEGURADORA | B26: 33.164.021/0001-00
A27: DESKTOP S A - INTERNET WIFI | B27: 08.170.849/0001-15
A28: AMIL ASSISTENCIA MEDICA INTERNACIONAL S.A. - CONVENIO MEDICO | B28: 29.309.127/0138-23
A29: CELIO LUIZ DE LIMA - VIGIA DA RUA | B29: 776.443.109-59 | C29: (19) 99705-3566
A30: MERCADO PAGO
A31: William Bezerra de Melo | B31: 047.677.934-08
A32: CASA DE BOLOS
A33: Sumerbol Supermercados Ltda
A34: CPFL - COMPAHIA DE FORÇA E LUZ
A35: BLING SISTEMA ERP
A36: INSS
A37: DAS - SIMPLES NACIONAL
A38: SAAE - COMPANHIA DE ÁGUA E ESGOTO
A39: GSM COMERCIO DE ELETRO
A40: SPM COSMETICOS LTDA
A41: LIBERTY SEGURO - SEGURADORA
A42: MICROSOFT SÃO PAULO
A43: SOL ABDELNOR
... A61: MR VARIEDADES
A62: UNISEGURANCA ALARMES LTDA | B62: 08.368.167/0001-11
A63: BANCO ITAU
A64: JOVINA MOREIRA MENDES DIARISTA
A65: VIVO S.A TELEFONIA
A66: SEMEAR PROJETO SOCIAL
A67: Jose Alberto | B67: 62 8264-9508
A68: Prefeitura Municipal De Indaiatuba
A69: Sidecont Contabilidade E Consultoria
A70: ALIBABA CHINA
A71: GOOGLE
A72: PATRICIA LEKEF
A73: ASSAI MERCADO
A74: MEDPREVENT EXAME ADMISSIONAL
A75: TAKATA TAKATA COMERCIO DE DOCES E SALGADOS | B75: 19971245402
A76: SECRETARIA DA FAZENDA
A77: PONTO AZUL
A78: CIA do Salgado
A79: ESTACIONAMENTO FEIRA
A80: SÓ ISOPOR
A81: TEMAKERIA E CIA
A82: CASA DO PÃO DE QUEIJO
A83: PEDAGIO C6 TAG
A84: ROBERTO BI CPF 12702467717
A85: FRENTE CORRETORA DE CAMBIO LTDA | B85: 71.677.850/0001-77
A86: CHRISTINA CHAN CHINA
A87: RECEITA FEDERAL
A88: DELL TECHNOLOGIES
A89: Marcelo Zulli - 16 997327801 PIX
A90: BANCO C6 TAG PEDAGIO
A91: RESTAURANTE SP
A92: Booking Hotel
A93: WORKANA
A94: LOCAWEB
A95: AURORA TERMINAIS
A96: Fernanda Cristina Água Mineral
A97: Jade Casa Decor
... A103: CLINK COMERCIO IMPORTAÇÃO E EXPORTAÇÃO
A104: TAG BRINDES Ana Lucia da Silva Coutinho | B104: 298.039.398-31
A105: Chaveiro Bruno
A106: SEFAZ SP
A107: JUCESP
A108: VR ALIMENTAÇÃO
A109: DRI AVAST BRAZIL SAO PAULO
A110: GLOBALFY EUA
A111: LOGIX FLASH
A112: GABRIEL RIBEIRO DE MELO
A113: PC NET INFORMÁTICA
A114: MARINA MANTOANELLI MOTORFIX
A115: AMAZON MARKETPLACE
A116: CHURRASCARIA JATOBA
... A180: JESSICA CAMILE FREELANCER
A181: MAYSA FREELANCER | C181: 19991921409
A182: JULIA NOGUEIRA FREELANCER | B182: 51954506848
A183: VERONICA KELLY DOS REIS FREELANCER | B183: 49055460877
A184: FARMACIA DROGA RAIA
A185: SINDICATO DOS EMPREGADOS NO COMERCIO DE ITU
...

Sheet Tabela diária

Sheet Tabela mensal
A4: SUM de Valor | D4: MÊS/ANO VENCIMENTO
A5: SUBCATEGORIA | B5: Classificação | C5: Fornecedor | D5: 01/2025 | E5: 01/2026 | F5: 01/2027 | G5: 01/2028 | H5: 01/2029 | I5: 02/2025 | J5: 02/2026 | K5: 02/2027 | L5: 02/2028 | M5: 02/2029 | N5: 03/2025 | O5: 03/2026 | P5: 03/2027 | Q5: 03/2028 | R5: 03/2029 | S5: 04/2025 | T5: 04/2026 | U5: 04/2027 | V5: 04/2028 | W5: 04/2029 | X5: 05/2025 | Y5: 05/2026 | Z5: 05/2027 | AA5: 05/2028 | AB5: 05/2029 | AC5: 06/2025 | AD5: 06/2026 | AE5: 06/2027 | AF5: 06/2028 | AG5: 06/2029 | AH5: 07/2025 | AI5: 07/2026 | AJ5: 07/2027 | AK5: 07/2028 | AL5: 07/2029 | AM5: 08/2024 | AN5: 08/2025 | AO5: 08/2026 | AP5: 08/2027 | AQ5: 08/2028 | AR5: 08/2029 | AS5: 09/2024 | AT5: 09/2025 | AU5: 09/2026 | AV5: 09/2027 | AW5: 09/2028 | AX5: 09/2029 | AY5: 10/2024 | AZ5: 10/2025 | BA5: 10/2026 | BB5: 10/2027 | BC5: 10/2028 | BD5: 11/2024 | BE5: 11/2025 | BF5: 11/2026 | BG5: 11/2027 | BH5: 11/2028 | BI5: 12/2024 | BJ5: 12/2025 | BK5: 12/2026 | BL5: 12/2027 | BM5: 12/2028 | BN5: Total geral
A6: DESPESAS ADMINISTRATIVAS | B6: CONTABILIDADE | C6: DRE ASSESSORIA CONTÁBIL EIRELI | D6: 380.54 | E6: 360.54 | I6: 380.54 | N6: 380.54 | O6: 814 | S6: 360.54 | T6: 406 | X6: 360.54 | Y6: 406 | AC6: 360.54 | AD6: 406 | AH6: 360.54 | AI6: 406 | AM6: 360.54 | AN6: 360.54 | AO6: 406 | AS6: 380.54 | AT6: 360.54 | AU6: 406 | AY6: 380.54 | AZ6: 360.54 | BA6: 406 | BD6: 380.54 | BF6: 406 | BI6: 380.54 | BJ6: 741.08 | BK6: 406 | BN6: 11117.72
C7: GLOBALFY EUA | AH7: 462.42 | AN7: 180.07 | BN7: 642.49
C8: LCP GROUP CONTABILIDADE LAYLA EUA | E8: 1313.49 | J8: 1313.49 | O8: 1313.49 | T8: 1313.49 | Y8: 1313.49 | AD8: 1313.49 | AH8: 196.53 | AN8: 196.53 | AT8: 196.53 | AZ8: 196.53 | BE8: 196.53 | BJ8: 196.53 | BN8: 9060.12
C9: Marcelo Zulli - 16 997327801 PIX | D9: 333.34 | BD9: 333.34 | BI9: 333.34 | BN9: 1000.02
C10: MERCADO LIVRE | J10: 20.9 | BN10: 20.9
C11: Sidecont Contabilidade E Consultoria | D11: 397 | E11: 397 | I11: 397 | J11: 447 | N11: 397 | O11: 447 | S11: 397 | T11: 447 | X11: 397 | Y11: 447 | AC11: 397 | AD11: 447 | AH11: 397 | AI11: 447 | AM11: 397 | AN11: 397 | AO11: 447 | AS11: 397 | AT11: 397 | AU11: 447 | AY11: 397 | AZ11: 397 | BA11: 447 | BD11: 397 | BE11: 397 | BF11: 447 | BI11: 397 | BJ11: 397 | BK11: 447 | BN11: 12063
B12: DESPESA COM SISTEMAS Total | D12: 1355.27 | E12: 1158.65 | I12: 1667.76 | J12: 1152.73 | N12: 1713.39 | O12: 1205.98 | S12: 1092.26 | T12: 1035.04 | X12: 1011.49 | Y12: 1035.04 | AC12: 1539.46 | AD12: 1035.04 | AH12: 887.06 | AI12: 1035.04 | AM12: 519.02 | AN12: 859.31 | AO12: 1010.88 | AS12: 781.06 | AT12: 996.6 | AU12: 1010.88 | AY12: 1204.63 | AZ12: 927.1 | BA12: 1010.88 | BD12: 1354.92 | BE12: 1153.05 | BF12: 1010.88 | BI12: 1324.87 | BJ12: 1145.19 | BK12: 1010.88 | BN12: 32244.36
B13: DOAÇÕES | C13: GABI E BIA DOAÇÃO | E13: 150 | J13: 150 | AZ13: 150 | BE13: 150 | BJ13: 150 | BN13: 750
C14: SEMEAR PROJETO SOCIAL | D14: 100 | I14: 100 | N14: 100 | O14: 100 | S14: 150 | T14: 100 | X14: 150 | Y14: 100 | AC14: 150 | AD14: 100 | AH14: 150 | AI14: 100 | AM14: 100 | AN14: 150 | AO14: 100 | AS14: 100 | AT14: 150 | AU14: 100 | AY14: 100 | BA14: 100 | BD14: 100 | BF14: 100 | BI14: 100 | BK14: 100 | BN14: 2700
B15: MANUTENÇÃO BENS DE EXPEDIENTE | C15: BANCO DO BRASIL | S15: 50 | BN15: 50
C16: MERCADO LIVRE | E16: 115.71 | AH16: 48.28 | AM16: 64.95 | BE16: 172.41 | BJ16: 115.71 | BN16: 517.06
C17: REI DO BASICO MATERIAIS DE CONSTRUÇÃO | AH17: 22.68 | BE17: 70.76 | BN17: 93.44
B18: MANUTENÇÃO EQUIPAMENTOS ADM | C18: PONTO AZUL | BI18: 40 | BN18: 40
B19: MANUTENÇÃO EQUIPAMENTOS OPERAÇÃO | C19: Chaveiro Bruno | BD19: 300 | BN19: 300
C20: DOUGLAS HENRIQUE ASSISTENCIA TECNICA | J20: 220 | O20: 220 | T20: 220 | BN20: 660
C21: MERCADO LIVRE | AC21: 109.91 | BN21: 109.91
C22: PC NET INFORMÁTICA | D22: 83.6 | I22: 83.6 | N22: 83.6 | S22: 83.6 | X22: 83.6 | BN22: 418
C23: REI DO BASICO MATERIAIS DE CONSTRUÇÃO | BE23: 9.9 | BN23: 9.9
B24: MARKETING E PUBLICIDADE | C24: AMAZON MARKETPLACE | E24: 4522.51 | O24: 993.83 | AH24: 235.84 | BJ24: 4640.4 | BN24: 10392.58
C25: AUGUSTO CESAR PINHEIRO | AT25: 170 | BN25: 170
C26: Bazar 10 | T26: 5 | BN26: 5
C27: CONSTANTE CONSULTORIA - BRUNO ARMSTRONG | S27: 295 | X27: 295 | BN27: 590
C28: EC OSASCOLAS | AM28: 288.33 | AS28: 288.33 | BN28: 576.66
C29: Erick Renato Rufino hernandes -Marketing | AC29: 120 | BN29: 120
C30: GODADDY | D30: 138.93 | E30: 470.94 | BN30: 609.87
C31: GS1 USA | AH31: 359.04 | BN31: 359.04
C32: INPI - REGISTRO DE MARCA | S32: 56 | BN32: 56
C33: JUNGLE SCOUT | AH33: 293.98 | BN33: 293.98
C34: MARCARIA.COM | S34: 237.15 | X34: 325.5 | AC34: 237.15 | BN34: 799.8
C35: TAG BRINDES Ana Lucia da Silva Coutinho | BD35: 150 | BN35: 150
B36: MATERIAL DE EXPEDIENTE | C36: AKI TEM UTILIDADES | BE36: 47.48 | BJ36: 47.47 | BN36: 94.95
C37: Casa das Embalagens e Limpeza Ltda | J37: 102.94 | T37: 376.69 | BJ37: 878.99 | BN37: 1358.62
C38: MERCADO LIVRE | E38: 422.2 | I38: 63.92 | N38: 63.91 | AC38: 86.4 | AH38: 31.25 | AS38: 256.89 | BE38: 117.71 | BN38: 1042.28
B39: OUTRAS DESPESAS ADM | C39: AKI TEM UTILIDADES | E39: 71.95 | J39: 71.94 | BN39: 143.89
C40: AMAZON MARKETPLACE | J40: 5017.49 | AZ40: 1515.22 | BE40: 2983.95 | BJ40: 2196.45 | BN40: 11713.11
C41: BANCO DO BRASIL | E41: 12027.05 | N41: 1901.24 | S41: 109.96 | AC41: 109.95 | BI41: 3651.65 | BJ41: 3061.9 | BN41: 20861.75
C42: CARTORIO INDAIATUBA | X42: 22.43 | BN42: 22.43
C43: DT SAN DEDETIZAÇÃO | O43: 490 | BN43: 490
C44: ELAINE CRISTINA DE MELO | BJ44: 3180 | BN44: 3180
C45: LARISSA FARINCHON BORGES | BJ45: 3180 | BN45: 3180
C46: LEROY MERLIN | S46: 106.36 | X46: 106.34 | AC46: 106.34 | BN46: 319.04
C47: MAGALU PAY | BE47: 180 | BN47: 180
C48: MELHOR ENVIO | D48: 92.35 | BN48: 92.35
C49: MERCADO LIVRE | AH49: -127.36 | BI49: -128.42 | BN49: -255.78
C50: NIPON PAPELARIA | BJ50: 24 | BN50: 24
C51: SULTHAM SOLUTIONS | S51: 300 | X51: 300 | AC51: 300 | BN51: 900
C52: SUMS CLUB | E52: 976.78 | BN52: 976.78
B53: SERVIÇOS TERCEIRIZADOS Total | D53: 680 | E53: 3174.5 | I53: 1180 | J53: 2808.4 | N53: 1267.5 | O53: 2315 | S53: 1356.73 | T53: 2160 | X53: 1711.36 | Y53: 2160 | AC53: 1498.86 | AD53: 2160 | AH53: 1648.46 | AI53: 2160 | AM53: 1707.92 | AN53: 735.96 | AO53: 2160 | AS53: 1456.9 | AT53: 1245.53 | AU53: 2160 | AY53: 780.92 | AZ53: 2608.86 | BA53: 2160 | BD53: 700 | BE53: 2028.86 | BF53: 2160 | BI53: 1650 | BJ53: 1649.5 | BK53: 2160 | BN53: 51645.26
B54: TRANSPORTE URBANO (TÁXI, UBER) | C54: UBER | E54: 64.72 | I54: 21.27 | N54: 177.51 | O54: 19.88 | S54: 81.19 | X54: 53.74 | AC54: 12.18 | AH54: 35.27 | AM54: 79.57 | AN54: 21.96 | AS54: 72.41 | AT54: 79.74 | AZ54: 70.11 | BE54: 11.94 | BJ54: 58.81 | BN54: 860.3
A55: DESPESAS COM OCUPAÇÃO | B55: ÁGUA E ESGOTO | C55: SAAE - COMPANHIA DE ÁGUA E ESGOTO | D55: 107.64 | E55: 107.64 | I55: 107.64 | J55: 107.64 | N55: 110.8 | O55: 107.64 | S55: 107.64 | T55: 150 | X55: 107.64 | Y55: 150 | AC55: 107.64 | AD55: 150 | AH55: 107.64 | AI55: 150 | AM55: 107.64 | AN55: 107.64 | AO55: 150 | AS55: 109.22 | AT55: 107.64 | AU55: 150 | AY55: 107.64 | AZ55: 107.64 | BA55: 150 | BD55: 107.64 | BE55: 107.64 | BF55: 150 | BI55: 107.64 | BJ55: 107.64 | BK55: 150 | BN55: 3507.54
B56: ALARME/MONITORAMENTO/VIGILÂNCIA | C56: GIBIM SEGURANÇA | E56: 170 | J56: 179.13 | N56: 173.6 | O56: 179.13 | S56: 170 | T56: 170 | X56: 170 | Y56: 170 | AC56: 170 | AD56: 170 | AH56: 170 | AI56: 170 | AN56: 170 | AO56: 170 | AT56: 170 | AU56: 170 | AZ56: 170 | BA56: 170 | BE56: 170 | BF56: 170 | BJ56: 170 | BK56: 170 | BN56: 3761.86
C57: UNISEGURANCA ALARMES LTDA | D57: 170 | I57: 170 | AM57: 170 | AS57: 170 | AY57: 170 | BD57: 170 | BI57: 170 | BN57: 1190
B58: ALUGUEIS | C58: ADELINO ALVES - ALUGUEL GALPÃO | D58: 5600 | E58: 5966.24 | I58: 5831.95 | J58: 6127.21 | N58: 6385.68 | O58: 6655.71 | S58: 6385.68 | T58: 6656 | X58: 6385.68 | Y58: 6656 | AC58: 6385.68 | AD58: 6656 | AH58: 6385.68 | AI58: 6656 | AM58: 6000.63 | AN58: 6385.68 | AO58: 6656 | AS58: 6000.63 | AT58: 6385.68 | AU58: 6656 | AY58: 6000.63 | AZ58: 6385.68 | BA58: 6656 | BD58: 6000.63 | BE58: 5922.79 | BF58: 6656 | BI58: 6000.63 | BJ58: 6385.68 | BK58: 6656 | BN58: 183482.17
B59: ALVARÁ DE FUNCIONAMENTO | C59: Prefeitura Municipal De Indaiatuba | AM59: 222.66 | BN59: 222.66
B60: ENERGIA ELETRICA | C60: CPFL - COMPAHIA DE FORÇA E LUZ | D60: 447.77 | E60: 403.88 | I60: 560.85 | J60: 367.78 | N60: 578 | O60: 437.68 | S60: 462.36 | T60: 800 | X60: 397.83 | Y60: 800 | AC60: 335.98 | AD60: 800 | AH60: 357.33 | AI60: 800 | AM60: 374.8 | AN60: 324.41 | AO60: 800 | AS60: 462.81 | AT60: 375.6 | AU60: 800 | AY60: 544.78 | AZ60: 480.39 | BA60: 800 | BD60: 526.57 | BE60: 409.86 | BF60: 800 | BI60: 578.15 | BJ60: 523.05 | BK60: 800 | BN60: 16149.88
B61: INTERNET | C61: DESKTOP S A - INTERNET WIFI | D61: 139.99 | E61: 139.99 | I61: 139.99 | J61: 144.99 | N61: 139.99 | O61: 144.99 | S61: 139.99 | T61: 139.99 | X61: 139.99 | Y61: 139.99 | AC61: 139.99 | AD61: 139.99 | AH61: 139.99 | AI61: 139.99 | AM61: 139.99 | AN61: 139.99 | AO61: 139.99 | AS61: 139.99 | AT61: 139.99 | AU61: 139.99 | AY61: 139.99 | AZ61: 139.99 | BA61: 139.99 | BD61: 139.99 | BE61: 139.99 | BF61: 139.99 | BI61: 139.99 | BJ61: 139.99 | BK61: 139.99 | BN61: 4069.71
B62: MANUTENÇÃO PREDIAL | C62: ADEMILSON BEZERRA | N62: 245 | BN62: 245
C63: ALAN ANOROSO INSULFILM PIX 383.671.438-84 | AC63: 265 | BN63: 265
C64: ASSAI MERCADO | S64: 4.58 | BN64: 4.58
C65: Chaveiro Bruno | J65: 45 | AH65: 166 | BD65: 50 | BN65: 261
C66: CRISTIANO BRAZ DOS SANOS | AH66: 51 | BN66: 51
C67: DEMILSON TOLDOS | E67: 245 | J67: 245 | O67: 245 | BN67: 735
C68: DENIS LAPA CONSERTA GELADEIRA | O68: 650 | BN68: 650
C69: ELIO ELETRICISTA | E69: 283.71 | J69: 283.71 | O69: 283.71 | BN69: 851.13
C70: Flores Do Park | E70: 197 | BN70: 197
C71: INDAIA EXTINTORES | O71: 160 | S71: 130 | BN71: 290
C72: JOSE CLAUDINEI MANUTENÇÃO | E72: 300 | BN72: 300
C73: MERCADO LIVRE | D73: 243.52 | I73: 149.46 | N73: 33.06 | S73: 33.06 | X73: 84.59 | BI73: 365.96 | BN73: 909.65
C74: REI DO BASICO MATERIAIS DE CONSTRUÇÃO | D74: 25 | E74: 8.5 | X74: 50 | BN74: 83.5
C75: V VIDROS | AZ75: 231.45 | BE75: 231.45 | BN75: 462.9
B76: MATERIAL LIMPEZA/CONSERVAÇÃO | C76: ASSAI MERCADO | D76: 59.45 | AY76: 109.94 | BD76: 65.87 | BN76: 235.26
C77: Casa das Embalagens e Limpeza Ltda | D77: 29.99 | J77: 98.36 | N77: 214.27 | AH77: 199.39 | AZ77: 497.6 | BN77: 1039.61
C78: Jade Casa Decor | BD78: 75 | BI78: 75 | BN78: 150
C79: JOVINA MOREIRA MENDES DIARISTA | AZ79: 14.5 | BN79: 14.5
C80: LIMPA MAIS | AM80: 89.35 | BN80: 89.35
C81: MERCADO LIVRE | N81: 12.56 | BN81: 12.56
C82: Sumerbol Supermercados Ltda | S82: 356.42 | BN82: 356.42
B83: MATERIAL PAPELARIA/COPA/COZINHA Total | D83: 22.1 | E83: 305.88 | J83: 286.7 | O83: 286.7 | T83: 70.13 | Y83: 70.13 | AD83: 70.13 | AM83: 162.17 | BN83: 1273.94
B84: SEGURO PATRIMONIO | C84: BANCO DO BRASIL | AY84: -91.29 | BN84: -91.29
C85: HDI SEGUROS | J85: 120.93 | N85: 110.87 | O85: 120.93 | S85: 221.74 | T85: 120.93 | Y85: 120.93 | AC85: 110.87 | AD85: 120.93 | AH85: 110.87 | AI85: 120.93 | AN85: 110.87 | AO85: 120.93 | AT85: 110.82 | BN85: 1622.55
C86: MAPFRE SEGUROS GERAIS | BJ86: 220.64 | BN86: 220.64
C87: TOKIO MARINE SEGURADORA S.A. - SEGURADORA | D87: 223.69 | E87: 158.5 | I87: 223.69 | J87: 158.5 | N87: 223.69 | O87: 158.5 | S87: 223.69 | T87: 158.5 | X87: 223.69 | Y87: 158.5 | AD87: 158.5 | AM87: 149.25 | AS87: 149.25 | BI87: 223.73 | BJ87: 162.39 | BN87: 2754.07
B88: TAXAS LICENÇA | C88: LCP GROUP CONTABILIDADE LAYLA EUA | E88: 98.93 | J88: 98.93 | O88: 98.93 | S88: 98.93 | X88: 98.93 | AC88: 98.93 | AH88: 98.93 | AN88: 98.93 | AT88: 98.93 | AZ88: 98.93 | BE88: 98.93 | BJ88: 98.93 | BN88: 1187.16
B89: TELEFONIA/CELULAR | C89: VIVO S.A TELEFONIA | D89: 171.72 | E89: 204.96 | I89: 171.72 | J89: 204.96 | N89: 171.72 | O89: 284.94 | S89: 171.72 | T89: 204.96 | X89: 171.72 | Y89: 204.96 | AC89: 171.72 | AD89: 204.96 | AH89: 174.69 | AI89: 204.96 | AM89: 164.97 | AN89: 218.65 | AO89: 204.96 | AS89: 164.97 | AT89: 205.92 | AU89: 204.96 | AY89: 171.72 | AZ89: 204.96 | BA89: 204.96 | BD89: 171.72 | BE89: 204.96 | BF89: 204.96 | BI89: 171.72 | BJ89: 204.96 | BK89: 204.96 | BN89: 5629.06
A90: DESPESAS COM PESSOAL | B90: 13 SALARIO | C90: ADRIANE CRISTINA GOMES | BD90: 452.22 | BI90: 436.81 | BN90: 889.03
C91: Debora Morales de Melo | BD91: 750 | BI91: 750 | BN91: 1500
C92: Maxwel do Carmo Prado | BJ92: 192.71 | BN92: 192.71
C93: Priscila Zaghi Da Silva | BD93: 900.38 | BE93: 1033.5 | BF93: 1150 | BI93: 895.3 | BJ93: 870.24 | BK93: 868 | BN93: 5717.42
C94: THIAGO MAURICIO BERTI | BD94: 594.59 | BE94: 1166 | BI94: 587.1 | BJ94: 978.89 | BN94: 3326.58
B95: ADIANTAMENTO DE SALARIO Total | D95: 2172 | E95: 2674.8 | I95: 2172 | J95: 1826.8 | N95: 1730 | O95: 1826.8 | S95: 1580 | T95: 1900 | X95: 2280 | Y95: 1900 | AC95: 1742.5 | AD95: 1900 | AH95: 1352.5 | AI95: 1900 | AM95: 2056 | AN95: 1742.5 | AO95: 1900 | AS95: 2056 | AT95: 942.5 | AU95: 1900 | AY95: 2056 | AZ95: 1580 | BA95: 1900 | BD95: 2056 | BE95: 1674.8 | BF95: 1900 | BI95: 2204 | BJ95: 2674 | BK95: 1780 | BN95: 55379.2
B96: ALIMENTAÇÃO FUNCIONARIOS | C96: CIA do Salgado | AS96: 118.8 | BN96: 118.8
C97: MC DONALD | D97: 133.8 | BN97: 133.8
C98: PANELA VELHA RESTAURANTE | D98: 145 | E98: 739.01 | I98: 27 | N98: 27.85 | S98: 135 | X98: 164 | AC98: 221 | AH98: 167 | AM98: 143 | AN98: 136 | AY98: 27 | BJ98: 203.27 | BN98: 2135.13
C99: VITOR FREELANCER PIX CPF 481.484.638-08 | AC99: 28 | BN99: 28
C100: William Bezerra de Melo | AM100: 24 | BN100: 24
B101: CONTRIBUIÇÃO SINDICAL | C101: SINDICATO DOS EMPREGADOS NO COMERCIO DE ITU | E101: 28 | J101: 32 | O101: 32 | T101: 28 | Y101: 28 | AD101: 28 | AI101: 28 | AO101: 28 | AU101: 28 | BA101: 28 | BE101: 28 | BJ101: 28 | BN101: 344
B102: CONVÊNIO MÉDICO Total | D102: 1275.18 | E102: 1760.67 | I102: 1290.56 | J102: 1472.06 | N102: 1304.26 | O102: 1533.05 | S102: 1282.61 | T102: 1600 | X102: 1433.18 | Y102: 1600 | AC102: 1824.26 | AD102: 1600 | AH102: 1779.69 | AI102: 1600 | AM102: 1375.64 | AN102: 1469.38 | AO102: 1600 | AS102: 1380.13 | AT102: 1778.61 | AU102: 1600 | AY102: 1444.16 | AZ102: 1968.18 | BA102: 1600 | BD102: 1240.56 | BE102: 1804.49 | BF102: 1600 | BI102: 1214.16 | BJ102: 1564.58 | BK102: 1600 | BN102: 44595.41
B103: EXAMES ADM/DEM/PER | C103: MEDPREVENT EXAME ADMISSIONAL | E103: 78 | N103: 78 | BE103: 67.5 | BN103: 223.5
...

Sheet Contas dos banco
A1: Banco | B1: Conta | C1: Banco-conta
A2: BANCO DO BRASIL | B2: 65204-0 | C2: =if(CONCATENATE(A2,"-",B2)="","",CONCATENATE(A2," - ",B2)) -> BANCO DO BRASIL - 65204-0
A3: MERCADO PAGO SINCE | B3: 9511092439-1 | C3: =if(CONCATENATE(A3,"-",B3)="","",CONCATENATE(A3," - ",B3)) -> MERCADO PAGO SINCE - 9511092439-1
A4: MERCADO PAGO FARMEL | C4: =if(CONCATENATE(A4,"-",B4)="","",CONCATENATE(A4," - ",B4)) -> MERCADO PAGO FARMEL -
C5: =if(CONCATENATE(A5,"-",B5)="","",CONCATENATE(A5," - ",B5)) -> -
C6: =if(CONCATENATE(A6,"-",B6)="","",CONCATENATE(A6," - ",B6)) -> -
C7: =if(CONCATENATE(A7,"-",B7)="","",CONCATENATE(A7," - ",B7)) -> -
C8: =if(CONCATENATE(A8,"-",B8)="","",CONCATENATE(A8," - ",B8)) -> -
C9: =if(CONCATENATE(A9,"-",B9)="","",CONCATENATE(A9," - ",B9)) -> -
C10: =if(CONCATENATE(A10,"-",B10)="","",CONCATENATE(A10," - ",B10)) -> -
C11: =if(CONCATENATE(A11,"-",B11)="","",CONCATENATE(A11," - ",B11)) -> -
C12: =if(CONCATENATE(A12,"-",B12)="","",CONCATENATE(A12," - ",B12)) -> -
C13: =if(CONCATENATE(A13,"-",B13)="","",CONCATENATE(A13," - ",B13)) -> -
C14: =if(CONCATENATE(A14,"-",B14)="","",CONCATENATE(A14," - ",B14)) -> -
C15: =if(CONCATENATE(A15,"-",B15)="","",CONCATENATE(A15," - ",B15)) -> -
C16: =if(CONCATENATE(A16,"-",B16)="","",CONCATENATE(A16," - ",B16)) -> -
... C298: =if(CONCATENATE(A298,"-",B298)="","",CONCATENATE(A298," - ",B298)) -> -

Sheet DFC
A1: NÍVEL | C1: 45292 | F1: 45323 | I1: 45352 | L1: 45383 | O1: 45413 | R1: 45444 | U1: 45474 | X1: 45505
C2: VALOR | D2: AV | E2: AH | F2: VALOR | G2: AV | H2: AH | I2: VALOR | J2: AV | K2: AH | L2: VALOR | M2: AV | N2: AH | O2: VALOR | P2: AV | Q2: AH | R2: VALOR | S2: AV | T2: AH | U2: VALOR | V2: AV | W2: AH | X2: VALOR | Y2: AV | Z2: AH
A3: 1 | B3: RECEITA OPERACIONAL BRUTA (+)
A4: 2 | B4: VENDAS DE MERCADORIAS | C4: =SUMIFS('Lançamentos de receitas'!$E:$E,'Lançamentos de receitas'!$F:$F,"pago",'Lançamentos de receitas'!$K:$K,C1) -> 0
A5: 1 | B5: DEDUÇÕES DA RECEITA BRUTA (-) | C5: =SUBTOTAL(9,C6:C10) -> 0
A6: 2 | B6: IMPOSTO SOBRE VENDA - DARF | C6: =-SUMIFS('Lançamentos de despesas'!$I:$I,'Lançamentos de despesas'!$E:$E,"pago",'Lançamentos de despesas'!$P:$P,C$1,'Lançamentos de despesas'!$N:$N,$B6) -> 0
A7: 2 | B7: SUBSTITUIÇÃO TRIBUTÁRIA | C7: =-SUMIFS('Lançamentos de despesas'!$I:$I,'Lançamentos de despesas'!$E:$E,"pago",'Lançamentos de despesas'!$P:$P,C$1,'Lançamentos de despesas'!$N:$N,$B7) -> 0
A8: 2 | B8: ISS | C8: =-SUMIFS('Lançamentos de despesas'!$I:$I,'Lançamentos de despesas'!$E:$E,"pago",'Lançamentos de despesas'!$P:$P,C$1,'Lançamentos de despesas'!$N:$N,$B8) -> 0
A9: 2 | B9: PIS | C9: =-SUMIFS('Lançamentos de despesas'!$I:$I,'Lançamentos de despesas'!$E:$E,"pago",'Lançamentos de despesas'!$P:$P,C$1,'Lançamentos de despesas'!$N:$N,$B9) -> 0
A10: 2 | B10: COFINS | C10: =-SUMIFS('Lançamentos de despesas'!$I:$I,'Lançamentos de despesas'!$E:$E,"pago",'Lançamentos de despesas'!$P:$P,C$1,'Lançamentos de despesas'!$N:$N,$B10) -> 0
A11: 1 | B11: RECEITA OPERACIONAL LÍQUIDA (=) | C11: =C3-C5 -> 0
A12: 1 | B12: CUSTOS VARIÁVEIS | C12: =SUBTOTAL(9,C13:C17) -> 0
A13: 2 | B13: CUSTO DOS SERVIÇOS PRESTADOS | C13: =-SUMIFS('Lançamentos de despesas'!$I:$I,'Lançamentos de despesas'!$E:$E,"pago",'Lançamentos de despesas'!$P:$P,C$1,'Lançamentos de despesas'!$N:$N,$B13) -> 0
A14: 2 | B14: CUSTO DA MERCADORIA VENDIDA (CMV) | C14: =-SUMIFS('Lançamentos de despesas'!$I:$I,'Lançamentos de despesas'!$E:$E,"pago",'Lançamentos de despesas'!$P:$P,C$1,'Lançamentos de despesas'!$N:$N,$B14) -> 0
A15: 2 | B15: DESPESAS COM VENDAS | C15: =-SUMIFS('Lançamentos de despesas'!$I:$I,'Lançamentos de despesas'!$E:$E,"pago",'Lançamentos de despesas'!$P:$P,C$1,'Lançamentos de despesas'!$N:$N,$B15) -> 0
A16: 2 | B16: DIÁRIA DO MOTORISTA | C16: =-SUMIFS('Lançamentos de despesas'!$I:$I,'Lançamentos de despesas'!$E:$E,"pago",'Lançamentos de despesas'!$P:$P,C$1,'Lançamentos de despesas'!$N:$N,$B16) -> 0
A17: 2 | B17: OUTROS CUSTOS VARIÁVEIS | C17: =-SUMIFS('Lançamentos de despesas'!$I:$I,'Lançamentos de despesas'!$E:$E,"pago",'Lançamentos de despesas'!$P:$P,C$1,'Lançamentos de despesas'!$N:$N,$B17) -> 0
A18: 1 | B18: LUCRO OPERACIONAL BRUTO (MC) (+/-) | C18: =C11+C12 -> 0
A19: 0
A20: 1 | B20: DESPESAS FIXAS (-) | C20: =C21+C49+C64+C66+C91+C98 -> 0
A21: 2 | B21: DESPESAS COM PESSOAL | C21: =SUBTOTAL(9,C22:C48) -> 0
A22: 3 | B22: SALARIOS | C22: =-SUMIFS('Lançamentos de despesas'!$I:$I,'Lançamentos de despesas'!$E:$E,"pago",'Lançamentos de despesas'!$P:$P,C$1,'Lançamentos de despesas'!$N:$N,$B22) -> 0
A23: 3 | B23: PRO-LABORE | C23: =-SUMIFS('Lançamentos de despesas'!$I:$I,'Lançamentos de despesas'!$E:$E,"pago",'Lançamentos de despesas'!$P:$P,C$1,'Lançamentos de despesas'!$N:$N,$B23) -> 0
A24: 3 | B24: BONIFICAÇÃO | C24: =-SUMIFS('Lançamentos de despesas'!$I:$I,'Lançamentos de despesas'!$E:$E,"pago",'Lançamentos de despesas'!$P:$P,C$1,'Lançamentos de despesas'!$N:$N,$B24) -> 0
A25: 3 | B25: CONFRATERNIZAÇÕES | C25: =-SUMIFS('Lançamentos de despesas'!$I:$I,'Lançamentos de despesas'!$E:$E,"pago",'Lançamentos de despesas'!$P:$P,C$1,'Lançamentos de despesas'!$N:$N,$B25) -> 0
A26: 3 | B26: HORAS EXTRAS | C26: =-SUMIFS('Lançamentos de despesas'!$I:$I,'Lançamentos de despesas'!$E:$E,"pago",'Lançamentos de despesas'!$P:$P,C$1,'Lançamentos de despesas'!$N:$N,$B26) -> 0
A27: 3 | B27: FÉRIAS | C27: =-SUMIFS('Lançamentos de despesas'!$I:$I,'Lançamentos de despesas'!$E:$E,"pago",'Lançamentos de despesas'!$P:$P,C$1,'Lançamentos de despesas'!$N:$N,$B27) -> 0
A28: 3 | B28: INSS | C28: =-SUMIFS('Lançamentos de despesas'!$I:$I,'Lançamentos de despesas'!$E:$E,"pago",'Lançamentos de despesas'!$P:$P,C$1,'Lançamentos de despesas'!$N:$N,$B28) -> 0
A29: 3 | B29: FGTS | C29: =-SUMIFS('Lançamentos de despesas'!$I:$I,'Lançamentos de despesas'!$E:$E,"pago",'Lançamentos de despesas'!$P:$P,C$1,'Lançamentos de despesas'!$N:$N,$B29) -> 0
A30: 3 | B30: IRRF | C30: =-SUMIFS('Lançamentos de despesas'!$I:$I,'Lançamentos de despesas'!$E:$E,"pago",'Lançamentos de despesas'!$P:$P,C$1,'Lançamentos de despesas'!$N:$N,$B30) -> 0
A31: 3 | B31: VALE ALIMENTAÇÃO | C31: =-SUMIFS('Lançamentos de despesas'!$I:$I,'Lançamentos de despesas'!$E:$E,"pago",'Lançamentos de despesas'!$P:$P,C$1,'Lançamentos de despesas'!$N:$N,$B31) -> 0
A32: 3 | B32: VALE TRANSPORTE | C32: =-SUMIFS('Lançamentos de despesas'!$I:$I,'Lançamentos de despesas'!$E:$E,"pago",'Lançamentos de despesas'!$P:$P,C$1,'Lançamentos de despesas'!$N:$N,$B32) -> 0
A33: 3 | B33: ADIANTAMENTO DE SALARIO | C33: =-SUMIFS('Lançamentos de despesas'!$I:$I,'Lançamentos de despesas'!$E:$E,"pago",'Lançamentos de despesas'!$P:$P,C$1,'Lançamentos de despesas'!$N:$N,$B33) -> 0
... A48: 3 | B48: OUTRAS DESPESAS COM PESSOAL | C48: =-SUMIFS('Lançamentos de despesas'!$I:$I,'Lançamentos de despesas'!$E:$E,"pago",'Lançamentos de despesas'!$P:$P,C$1,'Lançamentos de despesas'!$N:$N,$B48) -> 0
A49: 2 | B49: DESPESAS ADMINISTRATIVAS | C49: =SUBTOTAL(9,C50:C63) -> 0
A50: 3 | B50: CONSULTORIA/ASSESSORIA | C50: =-SUMIFS('Lançamentos de despesas'!$I:$I,'Lançamentos de despesas'!$E:$E,"pago",'Lançamentos de despesas'!$P:$P,C$1,'Lançamentos de despesas'!$N:$N,$B50) -> 0
A51: 3 | B51: CONTABILIDADE | C51: =-SUMIFS('Lançamentos de despesas'!$I:$I,'Lançamentos de despesas'!$E:$E,"pago",'Lançamentos de despesas'!$P:$P,C$1,'Lançamentos de despesas'!$N:$N,$B51) -> 0
A52: 3 | B52: CREA/ASSOCIAÇÕES | C52: =-SUMIFS('Lançamentos de despesas'!$I:$I,'Lançamentos de despesas'!$E:$E,"pago",'Lançamentos de despesas'!$P:$P,C$1,'Lançamentos de despesas'!$N:$N,$B52) -> 0
A53: 3 | B53: CORREIOS | C53: =-SUMIFS('Lançamentos de despesas'!$I:$I,'Lançamentos de despesas'!$E:$E,"pago",'Lançamentos de despesas'!$P:$P,C$1,'Lançamentos de despesas'!$N:$N,$B53) -> 0
A54: 3 | B54: CUSTAS JUDICIAIS | C54: =-SUMIFS('Lançamentos de despesas'!$I:$I,'Lançamentos de despesas'!$E:$E,"pago",'Lançamentos de despesas'!$P:$P,C$1,'Lançamentos de despesas'!$N:$N,$B54) -> 0
A55: 3 | B55: CUSTAS DE CARTÓRIO | C55: =-SUMIFS('Lançamentos de despesas'!$I:$I,'Lançamentos de despesas'!$E:$E,"pago",'Lançamentos de despesas'!$P:$P,C$1,'Lançamentos de despesas'!$N:$N,$B55) -> 0
A56: 3 | B56: DOAÇÕES | C56: =-SUMIFS('Lançamentos de despesas'!$I:$I,'Lançamentos de despesas'!$E:$E,"pago",'Lançamentos de despesas'!$P:$P,C$1,'Lançamentos de despesas'!$N:$N,$B56) -> 0
A57: 3 | B57: SERVIÇOS TERCEIRIZADOS | C57: =-SUMIFS('Lançamentos de despesas'!$I:$I,'Lançamentos de despesas'!$E:$E,"pago",'Lançamentos de despesas'!$P:$P,C$1,'Lançamentos de despesas'!$N:$N,$B57) -> 0
A58: 3 | B58: TRANSPORTE URBANO (TÁXI, UBER) | C58: =-SUMIFS('Lançamentos de despesas'!$I:$I,'Lançamentos de despesas'!$E:$E,"pago",'Lançamentos de despesas'!$P:$P,C$1,'Lançamentos de despesas'!$N:$N,$B58) -> 0
A59: 3 | B59: MARKETING E PUBLICIDADE | C59: =-SUMIFS('Lançamentos de despesas'!$I:$I,'Lançamentos de despesas'!$E:$E,"pago",'Lançamentos de despesas'!$P:$P,C$1,'Lançamentos de despesas'!$N:$N,$B59) -> 0
A60: 3 | B60: MANUTENÇÃO EQUIPAMENTOS ADM | C60: =-SUMIFS('Lançamentos de despesas'!$I:$I,'Lançamentos de despesas'!$E:$E,"pago",'Lançamentos de despesas'!$P:$P,C$1,'Lançamentos de despesas'!$N:$N,$B60) -> 0
A61: 3 | B61: MANUTENÇÃO EQUIPAMENTOS OPERAÇÃO | C61: =-SUMIFS('Lançamentos de despesas'!$I:$I,'Lançamentos de despesas'!$E:$E,"pago",'Lançamentos de despesas'!$P:$P,C$1,'Lançamentos de despesas'!$N:$N,$B61) -> 0
... A63: 3 | B63: DESPESA COM SISTEMAS | C63: =-SUMIFS('Lançamentos de despesas'!$I:$I,'Lançamentos de despesas'!$E:$E,"pago",'Lançamentos de despesas'!$P:$P,C$1,'Lançamentos de despesas'!$N:$N,$B63) -> 0
A64: 2 | B64: IMPOSTOS E TAXAS DIVERSAS | C64: =C65 -> 0
A65: 3 | B65: OUTROS IMPOSTOS E TAXAS | C65: =-SUMIFS('Lançamentos de despesas'!$I:$I,'Lançamentos de despesas'!$E:$E,"pago",'Lançamentos de despesas'!$P:$P,C$1,'Lançamentos de despesas'!$N:$N,$B65) -> 0
A66: 2 | B66: DESPESAS COM VEICULOS | C66: =SUBTOTAL(9,C67:C74) -> 0
A67: 3 | B67: ALUGUEL VEICULAR | C67: =-SUMIFS('Lançamentos de despesas'!$I:$I,'Lançamentos de despesas'!$E:$E,"pago",'Lançamentos de despesas'!$P:$P,C$1,'Lançamentos de despesas'!$N:$N,$B67) -> 0
A68: 3 | B68: COMBUSTIVEIS | C68: =-SUMIFS('Lançamentos de despesas'!$I:$I,'Lançamentos de despesas'!$E:$E,"pago",'Lançamentos de despesas'!$P:$P,C$1,'Lançamentos de despesas'!$N:$N,$B68) -> 0
A69: 3 | B69: IPVA / DPVAT / LICENCIAMENTO | C69: =-SUMIFS('Lançamentos de despesas'!$I:$I,'Lançamentos de despesas'!$E:$E,"pago",'Lançamentos de despesas'!$P:$P,C$1,'Lançamentos de despesas'!$N:$N,$B69) -> 0
A70: 3 | B70: LAVAGEM VEÍCULOS | C70: =-SUMIFS('Lançamentos de despesas'!$I:$I,'Lançamentos de despesas'!$E:$E,"pago",'Lançamentos de despesas'!$P:$P,C$1,'Lançamentos de despesas'!$N:$N,$B70) -> 0
A71: 3 | B71: MANUTENÇÃO DE VEÍCULOS | C71: =-SUMIFS('Lançamentos de despesas'!$I:$I,'Lançamentos de despesas'!$E:$E,"pago",'Lançamentos de despesas'!$P:$P,C$1,'Lançamentos de despesas'!$N:$N,$B71) -> 0
A72: 3 | B72: MULTAS DE TRÂNSITO | C72: =-SUMIFS('Lançamentos de despesas'!$I:$I,'Lançamentos de despesas'!$E:$E,"pago",'Lançamentos de despesas'!$P:$P,C$1,'Lançamentos de despesas'!$N:$N,$B72) -> 0
A73: 3 | B73: MONITORAMENTO | C73: =-SUMIFS('Lançamentos de despesas'!$I:$I,'Lançamentos de despesas'!$E:$E,"pago",'Lançamentos de despesas'!$P:$P,C$1,'Lançamentos de despesas'!$N:$N,$B73) -> 0
A74: 3 | B74: SEGUROS DE VEÍCULOS | C74: =-SUMIFS('Lançamentos de despesas'!$I:$I,'Lançamentos de despesas'!$E:$E,"pago",'Lançamentos de despesas'!$P:$P,C$1,'Lançamentos de despesas'!$N:$N,$B74) -> 0
A75: 2 | B75: DESPESAS COM OCUPAÇÃO | C75: =SUBTOTAL(9,C76:C97) -> 0
A76: 3 | B76: ALUGUEIS | C76: =-SUMIFS('Lançamentos de despesas'!$I:$I,'Lançamentos de despesas'!$E:$E,"pago",'Lançamentos de despesas'!$P:$P,C$1,'Lançamentos de despesas'!$N:$N,$B76) -> 0
A77: 3 | B77: ALVARÁ DE FUNCIONAMENTO | C77: =-SUMIFS('Lançamentos de despesas'!$I:$I,'Lançamentos de despesas'!$E:$E,"pago",'Lançamentos de despesas'!$P:$P,C$1,'Lançamentos de despesas'!$N:$N,$B77) -> 0
A78: 3 | B78: CONDOMINIO | C78: =-SUMIFS('Lançamentos de despesas'!$I:$I,'Lançamentos de despesas'!$E:$E,"pago",'Lançamentos de despesas'!$P:$P,C$1,'Lançamentos de despesas'!$N:$N,$B78) -> 0
A79: 3 | B79: INTERNET | C79: =-SUMIFS('Lançamentos de despesas'!$I:$I,'Lançamentos de despesas'!$E:$E,"pago",'Lançamentos de despesas'!$P:$P,C$1,'Lançamentos de despesas'!$N:$N,$B79) -> 0
A80: 3 | B80: ÁGUA E ESGOTO | C80: =-SUMIFS('Lançamentos de despesas'!$I:$I,'Lançamentos de despesas'!$E:$E,"pago",'Lançamentos de despesas'!$P:$P,C$1,'Lançamentos de despesas'!$N:$N,$B80) -> 0
A81: 3 | B81: ENERGIA ELETRICA | C81: =-SUMIFS('Lançamentos de despesas'!$I:$I,'Lançamentos de despesas'!$E:$E,"pago",'Lançamentos de despesas'!$P:$P,C$1,'Lançamentos de despesas'!$N:$N,$B81) -> 0
A82: 3 | B82: TELEFONIA/CELULAR | C82: =-SUMIFS('Lançamentos de despesas'!$I:$I,'Lançamentos de despesas'!$E:$E,"pago",'Lançamentos de despesas'!$P:$P,C$1,'Lançamentos de despesas'!$N:$N,$B82) -> 0
A83: 3 | B83: SEGURO PATRIMONIO | C83: =-SUMIFS('Lançamentos de despesas'!$I:$I,'Lançamentos de despesas'!$E:$E,"pago",'Lançamentos de despesas'!$P:$P,C$1,'Lançamentos de despesas'!$N:$N,$B83) -> 0
A84: 3 | B84: MATERIAL LIMPEZA/CONSERVAÇÃO | C84: =-SUMIFS('Lançamentos de despesas'!$I:$I,'Lançamentos de despesas'!$E:$E,"pago",'Lançamentos de despesas'!$P:$P,C$1,'Lançamentos de despesas'!$N:$N,$B84) -> 0
A85: 3 | B85: MATERIAL PAPELARIA/COPA/COZINHA | C85: =-SUMIFS('Lançamentos de despesas'!$I:$I,'Lançamentos de despesas'!$E:$E,"pago",'Lançamentos de despesas'!$P:$P,C$1,'Lançamentos de despesas'!$N:$N,$B85) -> 0
A86: 3 | B86: MANUTENÇÃO PREDIAL | C86: =-SUMIFS('Lançamentos de despesas'!$I:$I,'Lançamentos de despesas'!$E:$E,"pago",'Lançamentos de despesas'!$P:$P,C$1,'Lançamentos de despesas'!$N:$N,$B86) -> 0
A87: 3 | B87: SERVIÇOS GRAFICOS | C87: =-SUMIFS('Lançamentos de despesas'!$I:$I,'Lançamentos de despesas'!$E:$E,"pago",'Lançamentos de despesas'!$P:$P,C$1,'Lançamentos de despesas'!$N:$N,$B87) -> 0
... A90: 3 | B90: TAXAS LICENÇA | C90: =-SUMIFS('Lançamentos de despesas'!$I:$I,'Lançamentos de despesas'!$E:$E,"pago",'Lançamentos de despesas'!$P:$P,C$1,'Lançamentos de despesas'!$N:$N,$B90) -> 0
A91: 2 | B91: DESPESAS COM VIAGENS | C91: =SUBTOTAL(9,C92:C97) -> 0
A92: 3 | B92: HOSPEDAGEM | C92: =-SUMIFS('Lançamentos de despesas'!$I:$I,'Lançamentos de despesas'!$E:$E,"pago",'Lançamentos de despesas'!$P:$P,C$1,'Lançamentos de despesas'!$N:$N,$B92) -> 0
A93: 3 | B93: ALIMENTAÇÃO | C93: =-SUMIFS('Lançamentos de despesas'!$I:$I,'Lançamentos de despesas'!$E:$E,"pago",'Lançamentos de despesas'!$P:$P,C$1,'Lançamentos de despesas'!$N:$N,$B93) -> 0
A94: 3 | B94: PEDÁGIOS | C94: =-SUMIFS('Lançamentos de despesas'!$I:$I,'Lançamentos de despesas'!$E:$E,"pago",'Lançamentos de despesas'!$P:$P,C$1,'Lançamentos de despesas'!$N:$N,$B94) -> 0
A95: 3 | B95: FRETES E TRANSLADOS | C95: =-SUMIFS('Lançamentos de despesas'!$I:$I,'Lançamentos de despesas'!$E:$E,"pago",'Lançamentos de despesas'!$P:$P,C$1,'Lançamentos de despesas'!$N:$N,$B95) -> 0
A96: 3 | B96: ESTACIONAMENTO | C96: =-SUMIFS('Lançamentos de despesas'!$I:$I,'Lançamentos de despesas'!$E:$E,"pago",'Lançamentos de despesas'!$P:$P,C$1,'Lançamentos de despesas'!$N:$N,$B96) -> 0
A97: 3 | B97: PASSAGEM AÉREA | C97: =-SUMIFS('Lançamentos de despesas'!$I:$I,'Lançamentos de despesas'!$E:$E,"pago",'Lançamentos de despesas'!$P:$P,C$1,'Lançamentos de despesas'!$N:$N,$B97) -> 0
A98: 2 | B98: DESPESAS DIVERSAS | C98: =SUBTOTAL(9,C99:C101) -> 0
A99: 3 | B99: DESPESAS A CLASSIFICAR | C99: =-SUMIFS('Lançamentos de despesas'!$I:$I,'Lançamentos de despesas'!$E:$E,"pago",'Lançamentos de despesas'!$P:$P,C$1,'Lançamentos de despesas'!$N:$N,$B99) -> 0
A100: 3 | B100: AJUSTE DE SALDO POSITIVO | C100: =-SUMIFS('Lançamentos de despesas'!$I:$I,'Lançamentos de despesas'!$E:$E,"pago",'Lançamentos de despesas'!$P:$P,C$1,'Lançamentos de despesas'!$N:$N,$B100) -> 0
A101: 3 | B101: AJUSTE DE SALDO NEGATIVO | C101: =-SUMIFS('Lançamentos de despesas'!$I:$I,'Lançamentos de despesas'!$E:$E,"pago",'Lançamentos de despesas'!$P:$P,C$1,'Lançamentos de despesas'!$N:$N,$B101) -> 0
A102: 1 | B102: LUCRO OPERACIONAL LÍQUIDO (EBITDA) (=) | C102: =C18-C20 -> 0
A104: 1 | B104: (+/-) RESULTADO FINANCEIRO LÍQUIDO | C104: =SUM(C105:C109) -> 0
A105: 3 | B105: JUROS LIMITE DE CONTA | C105: =-SUMIFS('Lançamentos de despesas'!$I:$I,'Lançamentos de despesas'!$E:$E,"pago",'Lançamentos de despesas'!$P:$P,C$1,'Lançamentos de despesas'!$N:$N,$B105) -> 0
A106: 3 | B106: IOF | C106: =-SUMIFS('Lançamentos de despesas'!$I:$I,'Lançamentos de despesas'!$E:$E,"pago",'Lançamentos de despesas'!$P:$P,C$1,'Lançamentos de despesas'!$N:$N,$B106) -> 0
A107: 3 | B107: JUROS CONTA GARANTIDA | C107: =-SUMIFS('Lançamentos de despesas'!$I:$I,'Lançamentos de despesas'!$E:$E,"pago",'Lançamentos de despesas'!$P:$P,C$1,'Lançamentos de despesas'!$N:$N,$B107) -> 0
A108: 3 | B108: TARIFAS DE PIX | C108: =-SUMIFS('Lançamentos de despesas'!$I:$I,'Lançamentos de despesas'!$E:$E,"pago",'Lançamentos de despesas'!$P:$P,C$1,'Lançamentos de despesas'!$N:$N,$B108) -> 0
A109: 3 | B109: TARIFAS FINANCEIRAS DIVERSAS | C109: =-SUMIFS('Lançamentos de despesas'!$I:$I,'Lançamentos de despesas'!$E:$E,"pago",'Lançamentos de despesas'!$P:$P,C$1,'Lançamentos de despesas'!$N:$N,$B109) -> 0
A111: 1 | B111: RESULTADO NÃO OPERACIONAL (+/-) | C111: =-C112+C124 -> 0
A112: 2 | B112: DESPESAS NÃO OPERACIONAIS | C112: =SUBTOTAL(9,C113:C123) -> 0
A113: 3 | B113: COMPRA DE BENS/EQUIPAMENTOS | C113: =-SUMIFS('Lançamentos de despesas'!$I:$I,'Lançamentos de despesas'!$E:$E,"pago",'Lançamentos de despesas'!$P:$P,C$1,'Lançamentos de despesas'!$N:$N,$B113) -> 0
A114: 3 | B114: COMPRA DE PATRIMÔNIO | C114: =-SUMIFS('Lançamentos de despesas'!$I:$I,'Lançamentos de despesas'!$E:$E,"pago",'Lançamentos de despesas'!$P:$P,C$1,'Lançamentos de despesas'!$N:$N,$B114) -> 0
A115: 3 | B115: EMPRESTIMOS PARA TERCEIROS | C115: =-SUMIFS('Lançamentos de despesas'!$I:$I,'Lançamentos de despesas'!$E:$E,"pago",'Lançamentos de despesas'!$P:$P,C$1,'Lançamentos de despesas'!$N:$N,$B115) -> 0
A116: 3 | B116: RETIRADA DE CAPITAL | C116: =-SUMIFS('Lançamentos de despesas'!$I:$I,'Lançamentos de despesas'!$E:$E,"pago",'Lançamentos de despesas'!$P:$P,C$1,'Lançamentos de despesas'!$N:$N,$B116) -> 0
A117: 3 | B117: APLICAÇÕES | C117: =-SUMIFS('Lançamentos de despesas'!$I:$I,'Lançamentos de despesas'!$E:$E,"pago",'Lançamentos de despesas'!$P:$P,C$1,'Lançamentos de despesas'!$N:$N,$B117) -> 0
A118: 3 | B118: PARCELA CONSÓRCIOS | C118: =-SUMIFS('Lançamentos de despesas'!$I:$I,'Lançamentos de despesas'!$E:$E,"pago",'Lançamentos de despesas'!$P:$P,C$1,'Lançamentos de despesas'!$N:$N,$B118) -> 0
A119: 3 | B119: PARCELA DO FINANCIAMENTO | C119: =-SUMIFS('Lançamentos de despesas'!$I:$I,'Lançamentos de despesas'!$E:$E,"pago",'Lançamentos de despesas'!$P:$P,C$1,'Lançamentos de despesas'!$N:$N,$B119) -> 0
...

Sheet Classificação
A1: CATEGORIA | B1: NÍVEL 2 | C1: NÍVEL 1
A2: IMPOSTO DE RENDA - DAS | B2: IMPOSTO DE RENDA - DAS | C2: DEDUÇÕES DA RECEITA BRUTA (-)
A3: SUBSTITUIÇÃO TRIBUTÁRIA | B3: SUBSTITUIÇÃO TRIBUTÁRIA | C3: {=XLOOKUP(B3,'Nível 2'!B:B,'Nível 2'!A:A)} -> DEDUÇÕES DA RECEITA BRUTA (-)
A4: ISS | B4: ISS | C4: {=XLOOKUP(B4,'Nível 2'!B:B,'Nível 2'!A:A)} -> DEDUÇÕES DA RECEITA BRUTA (-)
A5: PIS | B5: PIS | C5: {=XLOOKUP(B5,'Nível 2'!B:B,'Nível 2'!A:A)} -> DEDUÇÕES DA RECEITA BRUTA (-)
A6: COFINS | B6: COFINS | C6: {=XLOOKUP(B6,'Nível 2'!B:B,'Nível 2'!A:A)} -> DEDUÇÕES DA RECEITA BRUTA (-)
A7: COMPRA DE MERCADORIA | B7: COMPRA DE MERCADORIA | C7: CUSTOS VARIÁVEIS
A8: COMISSÃO DE VENDEDORES | B8: COMISSÃO DE VENDEDORES | C8: CUSTOS VARIÁVEIS
A9: FRETE DE VENDAS | B9: FRETE DE VENDAS | C9: CUSTOS VARIÁVEIS
A10: EMBALAGENS/FITAS/GERAL | B10: EMBALAGENS/FITAS/GERAL | C10: CUSTOS VARIÁVEIS
A11: SALARIOS | B11: DESPESAS COM PESSOAL | C11: {=XLOOKUP(B11,'Nível 2'!B:B,'Nível 2'!A:A)} -> DESPESAS FIXAS (-)
A12: PRO-LABORE | B12: DESPESAS COM PESSOAL | C12: {=XLOOKUP(B12,'Nível 2'!B:B,'Nível 2'!A:A)} -> DESPESAS FIXAS (-)
A13: BONIFICAÇÃO | B13: DESPESAS COM PESSOAL | C13: {=XLOOKUP(B13,'Nível 2'!B:B,'Nível 2'!A:A)} -> DESPESAS FIXAS (-)
A14: CONFRATERNIZAÇÕES | B14: DESPESAS COM PESSOAL | C14: {=XLOOKUP(B14,'Nível 2'!B:B,'Nível 2'!A:A)} -> DESPESAS FIXAS (-)
A15: HORAS EXTRAS | B15: DESPESAS COM PESSOAL | C15: {=XLOOKUP(B15,'Nível 2'!B:B,'Nível 2'!A:A)} -> DESPESAS FIXAS (-)
A16: FÉRIAS | B16: DESPESAS COM PESSOAL | C16: {=XLOOKUP(B16,'Nível 2'!B:B,'Nível 2'!A:A)} -> DESPESAS FIXAS (-)
A17: INSS | B17: DESPESAS COM PESSOAL | C17: {=XLOOKUP(B17,'Nível 2'!B:B,'Nível 2'!A:A)} -> DESPESAS FIXAS (-)
A18: FGTS | B18: DESPESAS COM PESSOAL | C18: {=XLOOKUP(B18,'Nível 2'!B:B,'Nível 2'!A:A)} -> DESPESAS FIXAS (-)
A19: IRRF | B19: DESPESAS COM PESSOAL | C19: {=XLOOKUP(B19,'Nível 2'!B:B,'Nível 2'!A:A)} -> DESPESAS FIXAS (-)
A20: VALE ALIMENTAÇÃO | B20: DESPESAS COM PESSOAL | C20: {=XLOOKUP(B20,'Nível 2'!B:B,'Nível 2'!A:A)} -> DESPESAS FIXAS (-)
A21: VALE TRANSPORTE | B21: DESPESAS COM PESSOAL | C21: {=XLOOKUP(B21,'Nível 2'!B:B,'Nível 2'!A:A)} -> DESPESAS FIXAS (-)
A22: ADIANTAMENTO DE SALARIO | B22: DESPESAS COM PESSOAL | C22: {=XLOOKUP(B22,'Nível 2'!B:B,'Nível 2'!A:A)} -> DESPESAS FIXAS (-)
... A114: OUTRAS RECEITAS NÃO OPERACIONAIS | B114: RECEITAS NÃO OPERACIONAIS | C114: {=XLOOKUP(B114,'Nível 2'!B:B,'Nível 2'!A:A)} -> RESULTADO NÃO OPERACIONAL (+/-)
A115: TARIFAS BANCÁRIAS | B115: DESPESAS NÃO OPERACIONAIS | C115: {=IFERROR(XLOOKUP(B115,'Nível 2'!B:B,'Nível 2'!A:A),"")} -> RESULTADO NÃO OPERACIONAL (+/-)
C116: {=IFERROR(XLOOKUP(B116,'Nível 2'!B:B,'Nível 2'!A:A),"")}
C117: {=IFERROR(XLOOKUP(B117,'Nível 2'!B:B,'Nível 2'!A:A),"")}
C118: {=IFERROR(XLOOKUP(B118,'Nível 2'!B:B,'Nível 2'!A:A),"")}
C119: {=IFERROR(XLOOKUP(B119,'Nível 2'!B:B,'Nível 2'!A:A),"")}
C120: {=IFERROR(XLOOKUP(B120,'Nível 2'!B:B,'Nível 2'!A:A),"")}
C121: {=IFERROR(XLOOKUP(B121,'Nível 2'!B:B,'Nível 2'!A:A),"")}
C122: {=IFERROR(XLOOKUP(B122,'Nível 2'!B:B,'Nível 2'!A:A),"")}
C123: {=IFERROR(XLOOKUP(B123,'Nível 2'!B:B,'Nível 2'!A:A),"")}
C124: {=IFERROR(XLOOKUP(B124,'Nível 2'!B:B,'Nível 2'!A:A),"")}
C125: {=IFERROR(XLOOKUP(B125,'Nível 2'!B:B,'Nível 2'!A:A),"")}
C126: {=IFERROR(XLOOKUP(B126,'Nível 2'!B:B,'Nível 2'!A:A),"")}
C127: {=IFERROR(XLOOKUP(B127,'Nível 2'!B:B,'Nível 2'!A:A),"")}
... C437: {=IFERROR(XLOOKUP(B437,'Nível 2'!B:B,'Nível 2'!A:A),"")}

Sheet Nível 1
A1: ORDEM | B1: NÍVEL 1 | C1: SUBTOTAL
A2: 1 | B2: RECEITA OPERACIONAL BRUTA (+) | C2: A
A3: 2 | B3: DEDUÇÕES DA RECEITA BRUTA (-) | C3: A
A4: 3 | B4: RECEITA OPERACIONAL LÍQUIDA (=) | C4: ST
A5: 4 | B5: CUSTOS VARIÁVEIS | C5: A
A6: 5 | B6: RESULTADO OPERACIONAL BRUTO (MC) (+/-) | C6: ST
A7: 6 | B7: DESPESAS FIXAS (-) | C7: A
A8: 7 | B8: RESULTADO OPERACIONAL LÍQUIDO (EBITDA) (=) | C8: ST
A9: 9 | B9: RESULTADO NÃO OPERACIONAL (+/-) | C9: ST
A10: 12 | B10: RESULTADO LÍQUIDO DO EXERCÍCIO (=) | C10: ST
A11: 8 | B11: (+/-) RESULTADO FINANCEIRO LÍQUIDO | C11: A

Sheet Nível 2
A1: NÍVEL 1 | B1: NÍVEL 2
A2: RECEITA OPERACIONAL BRUTA (+) | B2: PRESTAÇÃO DE SERVIÇOS
A3: RECEITA OPERACIONAL BRUTA (+) | B3: VENDA DE PRODUTO
A4: RECEITA OPERACIONAL BRUTA (+) | B4: OUTRAS RECEITAS OPERACIONAIS
A5: (+/-) RESULTADO FINANCEIRO LÍQUIDO | B5: JUROS RECEBIDO DE CLIENTE
A6: DEDUÇÕES DA RECEITA BRUTA (-) | B6: IMPOSTO SOBRE VENDA - DARF
A7: DEDUÇÕES DA RECEITA BRUTA (-) | B7: SUBSTITUIÇÃO TRIBUTÁRIA
A8: DEDUÇÕES DA RECEITA BRUTA (-) | B8: DESCONTOS CONCEDIDOS
A9: DEDUÇÕES DA RECEITA BRUTA (-) | B9: DEVOLUÇÕES DE VENDAS
A10: CUSTOS VARIÁVEIS | B10: CUSTO DOS SERVIÇOS PRESTADOS
A11: CUSTOS VARIÁVEIS | B11: CUSTO DOS MATERIAIS VENDIDOS
A12: CUSTOS VARIÁVEIS | B12: COMPRA DE MERCADORIA
... A33: DESPESAS FIXAS (-) | B33: DESPESAS DIVERSAS
